Exercises/01) sum_1bit/sources/sum_1bit.vhd
-- Author: Francesco Cavina <francescocavina98@gmail.com>
-- Brief:  This a HW description for a 1 bit full adder

library IEEE;
use IEEE.std_logic_1164.all;

entity sum_1bit is
    port(
        x_i:  in  std_logic; 
        y_i:  in  std_logic;
        ci_i: in  std_logic;
        z_o:  out std_logic;
        co_o: out std_logic
    );
end entity sum_1bit;

architecture sum_1bit_arch of sum_1bit is
    -- Declaration

begin
    -- Description
    z_o  <= x_i xor y_i xor ci_i;
    co_o <= (y_i and ci_i) or (x_i and y_i) or (x_i and ci_i);
end architecture sum_1bit_arch;

Exercises/01) sum_1bit/sources/sum_1bit_tb.vhd
-- Author: Francesco Cavina <francescocavina98@gmail.com>
-- Brief:  This is the testbench of a 1 bit full adder

library IEEE;
use IEEE.std_logic_1164.all;

entity sum_1bit_tb is
end entity sum_1bit_tb;

architecture sum_1bit_tb_arch of sum_1bit_tb is
    -- Declaration
    component sum_1bit is
        port(
            x_i:  in  std_logic; 
            y_i:  in  std_logic;
            ci_i: in  std_logic;
            z_o:  out std_logic;
            co_o: out std_logic
        );
    end component sum_1bit;

    signal x_tb:  std_logic := '0';
    signal y_tb:  std_logic := '0';
    signal ci_tb: std_logic := '0';
    signal z_tb:  std_logic;
    signal co_tb: std_logic;

begin
    -- Description

    x_tb  <= '1' after 200 ns, '0' after 400 ns;
    -- x_tb <= not x_tb after 200 ns;
    y_tb  <= '1' after 100 ns, '0' after 200 ns, '1' after 300 ns, '0' after 400 ns;
    -- y_tb <= not y_tb after 100 ns;
    ci_tb <= '1' after  50 ns, '0' after 100 ns, '1' after 150 ns, '0' after 200 ns, '1' after 250 ns, '0' after 300 ns, '1' after 350 ns, '0' after 400 ns;
    -- ci_tb = not ci_tb after 50 ns;

    DUT: sum_1bit
        port map(
            x_i  => x_tb,
            y_i  => y_tb,
            ci_i => ci_tb,
            z_o  => z_tb,
            co_o => co_tb
        );
end architecture sum_1bit_tb_arch;

Exercises/01.0) sum_1bit/simulation/sum_1bit_tb.vcd
$date
  Sat Sep  9 23:44:41 2023
$end
$version
  GHDL v0
$end
$timescale
  1 fs
$end
$scope module standard $end
$upscope $end
$scope module std_logic_1164 $end
$upscope $end
$scope module sum_1bit_tb $end
$var reg 1 ! x_tb $end
$var reg 1 " y_tb $end
$var reg 1 # ci_tb $end
$var reg 1 $ z_tb $end
$var reg 1 % co_tb $end
$scope module dut $end
$var reg 1 & x_i $end
$var reg 1 ' y_i $end
$var reg 1 ( ci_i $end
$var reg 1 ) z_o $end
$var reg 1 * co_o $end
$upscope $end
$upscope $end
$enddefinitions $end
#0
0!
0"
0#
0$
0%
0&
0'
0(
0)
0*
#50000000
1#
1$
1(
1)
#100000000
1"
0#
1'
0(
#150000000
1#
0$
1%
1(
0)
1*
#200000000
1!
0"
0#
1$
0%
1&
0'
0(
1)
0*
#250000000
1#
0$
1%
1(
0)
1*
#300000000
1"
0#
1'
0(
#350000000
1#
1$
1(
1)
#400000000
0!
0"
0#
0$
0%
0&
0'
0(
0)
0*
