Exercises/04) mux_2x1/sources/mux_2x1.vhd
-- Author: Francesco Cavina <francescocavina98@gmail.com>
-- Brief:  This is the HW description for a 2x1 multiplexer

library IEEE;
use IEEE.std_logic_1164.all;

entity mux_2x1 is
    port(
        a_i:   in  std_logic;
        b_i:   in  std_logic;
        sel_i: in  std_logic;
        c_o:   out std_logic
    );
end entity mux_2x1;   

architecture mux_2x1_arch of mux_2x1 is
    -- Declaration

    begin
        -- Description
        c_o <= (a_i and (not sel_i)) or (b_i and sel_i); 

end architecture mux_2x1_arch;

Exercises/04.0) mux_2x1/sources/mux_2x1_tb.vhd
-- Author: Francesco Cavina <francescocavina98@gmail.com>
-- Brief:  This is the testbench of a 2x1 multiplexer

library IEEE;
use IEEE.std_logic_1164.all;

entity mux_2x1_tb is
end entity mux_2x1_tb;    

architecture mux_2x1_tb_arch of mux_2x1_tb is
    -- Declaration
    component mux_2x1 is
        port(
            a_i:   in  std_logic;
            b_i:   in  std_logic;
            sel_i: in  std_logic;
            c_o:   out std_logic
        );
    end component mux_2x1;

        signal a_tb:   std_logic := '0';
        signal b_tb:   std_logic := '0';
        signal sel_tb: std_logic := '0';
        signal c_tb:   std_logic;

begin
    -- Description
    a_tb   <= not a_tb   after 200 ns;
    b_tb   <= not b_tb   after 100 ns;
    sel_tb <= not sel_tb after  50 ns;

    DUT: mux_2x1
        port map(
            a_i   => a_tb, 
            b_i   => b_tb,
            sel_i => sel_tb,
            c_o   => c_tb
        );
end architecture mux_2x1_tb_arch;

Exercises/04) mux_2x1/simulation/mux_2x1_tb.vcd
$date
  Sun Sep 10 01:05:26 2023
$end
$version
  GHDL v0
$end
$timescale
  1 fs
$end
$scope module standard $end
$upscope $end
$scope module std_logic_1164 $end
$upscope $end
$scope module mux_2x1_tb $end
$var reg 1 ! a_tb $end
$var reg 1 " b_tb $end
$var reg 1 # sel_tb $end
$var reg 1 $ c_tb $end
$scope module dut $end
$var reg 1 % a_i $end
$var reg 1 & b_i $end
$var reg 1 ' sel_i $end
$var reg 1 ( c_o $end
$upscope $end
$upscope $end
$enddefinitions $end
#0
0!
0"
0#
0$
0%
0&
0'
0(
#50000000
1#
1'
#100000000
1"
0#
1&
0'
#150000000
1#
1$
1'
1(
#200000000
1!
0"
0#
1%
0&
0'
#250000000
1#
0$
1'
0(
#300000000
1"
0#
1$
1&
0'
1(
#350000000
1#
1'
#400000000
0!
0"
0#
0$
0%
0&
0'
0(
#450000000
1#
1'
#500000000
1"
0#
1&
0'
#550000000
1#
1$
1'
1(
#600000000
1!
0"
0#
1%
0&
0'
