Exercises/05.0) ffd/sources/ffd.vhd
-- Author: Francesco Cavina <francescocavina98@gmail.com>
-- Brief:  This is the HW description for a flip-flop D

library IEEE;
use IEEE.std_logic_1164.all;

entity ffd is
    port(
        d_i:   in  std_logic;
        ena_i: in  std_logic;
        rst_i: in  std_logic;
        clk_i: in  std_logic;
        q_o:   out std_logic
    );
end entity ffd;

architecture ffd_arch of ffd is
    -- Declaration

    begin
        -- Description
        process(clk_i) is
        begin
            if rising_edge(clk_i) then
                if rst_i = '1' then
                    q_o <= '0';
                elsif ena_i = '1' then
                    q_o <= d_i;
                end if;         
            end if;      
        end process;    
end architecture ffd_arch;

Exercises/05.0) ffd/sources/ffd_tb.vhd
-- Author: Francesco Cavina <francescocavina98@gmail.com>
-- Brief:  This is the testbench of a flip-flop D

library IEEE;
use IEEE.std_logic_1164.all;

entity ffd_tb is
end entity ffd_tb;

architecture ffd_tb_arch of ffd_tb is
    -- Declaration
    component ffd is
        port(
            d_i:   in  std_logic;
            ena_i: in  std_logic;
            rst_i: in  std_logic;
            clk_i: in  std_logic;
            q_o:   out std_logic
        );
    end component ffd;

    signal d_tb:    std_logic := '0';
    signal ena_tb:  std_logic := '1';
    signal rst_tb:  std_logic := '0';
    signal clk_tb:  std_logic := '1';
    signal q_tb:    std_logic;

begin
    -- Description
    clk_tb <= not clk_tb after  10 ns;
    d_tb   <= not   d_tb after 100 ns;
    --ena_tb <= not ena_tb after 200 ns;
    --rst_tb <= not rst_tb after 500 ns;

    DUT: ffd
        port map(
            d_i   => d_tb,
            ena_i => ena_tb,
            rst_i => rst_tb,
            clk_i => clk_tb,
            q_o   => q_tb
        );
end architecture ffd_tb_arch;

Exercises/05.0) ffd/simulation/ffd_tb.vcd
$date
  Sun Sep 17 23:29:46 2023
$end
$version
  GHDL v0
$end
$timescale
  1 fs
$end
$scope module standard $end
$upscope $end
$scope module std_logic_1164 $end
$upscope $end
$scope module ffd_tb $end
$var reg 1 ! d_tb $end
$var reg 1 " ena_tb $end
$var reg 1 # rst_tb $end
$var reg 1 $ clk_tb $end
$var reg 1 % q_tb $end
$scope module dut $end
$var reg 1 & d_i $end
$var reg 1 ' ena_i $end
$var reg 1 ( rst_i $end
$var reg 1 ) clk_i $end
$var reg 1 * q_o $end
$upscope $end
$upscope $end
$enddefinitions $end
#0
0!
1"
0#
1$
U%
0&
1'
0(
1)
U*
#10000000
0$
0)
#20000000
1$
0%
1)
0*
#30000000
0$
0)
#40000000
1$
1)
#50000000
0$
0)
#60000000
1$
1)
#70000000
0$
0)
#80000000
1$
1)
#90000000
0$
0)
#100000000
1!
1$
1%
1&
1)
1*
#110000000
0$
0)
#120000000
1$
1)
#130000000
0$
0)
#140000000
1$
1)
#150000000
0$
0)
#160000000
1$
1)
#170000000
0$
0)
#180000000
1$
1)
#190000000
0$
0)
#200000000
0!
1$
0%
0&
1)
0*
#210000000
0$
0)
#220000000
1$
1)
#230000000
0$
0)
#240000000
1$
1)
#250000000
0$
0)
#260000000
1$
1)
#270000000
0$
0)
#280000000
1$
1)
#290000000
0$
0)
#300000000
1!
1$
1%
1&
1)
1*
#310000000
0$
0)
#320000000
1$
1)
#330000000
0$
0)
#340000000
1$
1)
#350000000
0$
0)
#360000000
1$
1)
#370000000
0$
0)
#380000000
1$
1)
#390000000
0$
0)
#400000000
0!
1$
0%
0&
1)
0*
#410000000
0$
0)
#420000000
1$
1)
#430000000
0$
0)
#440000000
1$
1)
#450000000
0$
0)
#460000000
1$
1)
#470000000
0$
0)
#480000000
1$
1)
#490000000
0$
0)
#500000000
1!
1$
1%
1&
1)
1*
#510000000
0$
0)
#520000000
1$
1)
#530000000
0$
0)
#540000000
1$
1)
#550000000
0$
0)
#560000000
1$
1)
#570000000
0$
0)
#580000000
1$
1)
#590000000
0$
0)
#600000000
0!
1$
0%
0&
1)
0*
#610000000
0$
0)
#620000000
1$
1)
#630000000
0$
0)
#640000000
1$
1)
#650000000
0$
0)
#660000000
1$
1)
#670000000
0$
0)
#680000000
1$
1)
#690000000
0$
0)
#700000000
1!
1$
1%
1&
1)
1*
#710000000
0$
0)
#720000000
1$
1)
#730000000
0$
0)
#740000000
1$
1)
#750000000
0$
0)
#760000000
1$
1)
#770000000
0$
0)
#780000000
1$
1)
#790000000
0$
0)
#800000000
0!
1$
0%
0&
1)
0*
#810000000
0$
0)
#820000000
1$
1)
#830000000
0$
0)
#840000000
1$
1)
#850000000
0$
0)
#860000000
1$
1)
#870000000
0$
0)
#880000000
1$
1)
#890000000
0$
0)
#900000000
1!
1$
1%
1&
1)
1*
#910000000
0$
0)
#920000000
1$
1)
#930000000
0$
0)
#940000000
1$
1)
#950000000
0$
0)
#960000000
1$
1)
#970000000
0$
0)
#980000000
1$
1)
#990000000
0$
0)
#1000000000
0!
1$
0%
0&
1)
0*
