Exercises/05.0) ffd/sources/ffd.vhd
-- Author: Francesco Cavina <francescocavina98@gmail.com>
-- Brief:  This is the HW description for a flip-flop D

library IEEE;
use IEEE.std_logic_1164.all;

entity ffd is
    port(
        d_i:   in  std_logic;
        ena_i: in  std_logic;
        rst_i: in  std_logic;
        clk_i: in  std_logic;
        q_o:   out std_logic
    );
end entity ffd;

architecture ffd_arch of ffd is
    -- Declaration

    begin
        -- Description
        process(clk_i) is
        begin
            if rising_edge(clk_i) then
                if rst_i = '1' then
                    q_o <= '0';
                elsif ena_i = '1' then
                    q_o <= d_i;
                end if;         
            end if;      
        end process;    
end architecture ffd_arch;

Exercises/05.0) ffd/sources/ffd_tb.vhd
-- Author: Francesco Cavina <francescocavina98@gmail.com>
-- Brief:  This is the testbench of a flip-flop D

library IEEE;
use IEEE.std_logic_1164.all;

entity ffd_tb is
end entity ffd_tb;

architecture ffd_tb_arch of ffd_tb is
    -- Declaration
    component ffd is
        port(
            d_i:   in  std_logic;
            ena_i: in  std_logic;
            rst_i: in  std_logic;
            clk_i: in  std_logic;
            q_o:   out std_logic
        );
    end component ffd;

    signal d_tb:    std_logic := '0';
    signal ena_tb:  std_logic := '0';
    signal rst_tb:  std_logic := '0';
    signal clk_tb:  std_logic := '0';
    signal q_tb:    std_logic;

    begin
        -- Description
        clk_tb <= not clk_tb after  10 ns;
        d_tb   <= not   d_tb after 100 ns;
        ena_tb <= not ena_tb after 200 ns;
        rst_tb <= not rst_tb after 500 ns;

        DUT: ffd
            port map(
                d_i   => d_tb,
                ena_i => ena_tb,
                rst_i => rst_tb,
                clk_i => clk_tb,
                q_o   => q_tb
            );
end architecture ffd_tb_arch;

Exercises/05.0) ffd/simulation/ffd_tb.vcd
$date
  Tue Sep 12 23:03:42 2023
$end
$version
  GHDL v0
$end
$timescale
  1 fs
$end
$scope module standard $end
$upscope $end
$scope module std_logic_1164 $end
$upscope $end
$scope module ffd_tb $end
$var reg 1 ! d_tb $end
$var reg 1 " ena_tb $end
$var reg 1 # rst_tb $end
$var reg 1 $ clk_tb $end
$var reg 1 % q_tb $end
$scope module dut $end
$var reg 1 & d_i $end
$var reg 1 ' ena_i $end
$var reg 1 ( rst_i $end
$var reg 1 ) clk_i $end
$var reg 1 * q_o $end
$upscope $end
$upscope $end
$enddefinitions $end
#0
0!
0"
0#
0$
U%
0&
0'
0(
0)
U*
#10000000
1$
1)
#20000000
0$
0)
#30000000
1$
1)
#40000000
0$
0)
#50000000
1$
1)
#60000000
0$
0)
#70000000
1$
1)
#80000000
0$
0)
#90000000
1$
1)
#100000000
1!
0$
1&
0)
#110000000
1$
1)
#120000000
0$
0)
#130000000
1$
1)
#140000000
0$
0)
#150000000
1$
1)
#160000000
0$
0)
#170000000
1$
1)
#180000000
0$
0)
#190000000
1$
1)
#200000000
0!
1"
0$
0&
1'
0)
#210000000
1$
0%
1)
0*
#220000000
0$
0)
#230000000
1$
1)
#240000000
0$
0)
#250000000
1$
1)
#260000000
0$
0)
#270000000
1$
1)
#280000000
0$
0)
#290000000
1$
1)
#300000000
1!
0$
1&
0)
#310000000
1$
1%
1)
1*
#320000000
0$
0)
#330000000
1$
1)
#340000000
0$
0)
#350000000
1$
1)
#360000000
0$
0)
#370000000
1$
1)
#380000000
0$
0)
#390000000
1$
1)
#400000000
0!
0"
0$
0&
0'
0)
#410000000
1$
1)
#420000000
0$
0)
#430000000
1$
1)
#440000000
0$
0)
#450000000
1$
1)
#460000000
0$
0)
#470000000
1$
1)
#480000000
0$
0)
#490000000
1$
1)
#500000000
1!
1#
0$
1&
1(
0)
#510000000
1$
0%
1)
0*
#520000000
0$
0)
#530000000
1$
1)
#540000000
0$
0)
#550000000
1$
1)
#560000000
0$
0)
#570000000
1$
1)
#580000000
0$
0)
#590000000
1$
1)
#600000000
0!
1"
0$
0&
1'
0)
#610000000
1$
1)
#620000000
0$
0)
#630000000
1$
1)
#640000000
0$
0)
#650000000
1$
1)
#660000000
0$
0)
#670000000
1$
1)
#680000000
0$
0)
#690000000
1$
1)
#700000000
1!
0$
1&
0)
#710000000
1$
1)
#720000000
0$
0)
#730000000
1$
1)
#740000000
0$
0)
#750000000
1$
1)
#760000000
0$
0)
#770000000
1$
1)
#780000000
0$
0)
#790000000
1$
1)
#800000000
0!
0"
0$
0&
0'
0)
#810000000
1$
1)
#820000000
0$
0)
#830000000
1$
1)
#840000000
0$
0)
#850000000
1$
1)
#860000000
0$
0)
#870000000
1$
1)
#880000000
0$
0)
#890000000
1$
1)
#900000000
1!
0$
1&
0)
#910000000
1$
1)
#920000000
0$
0)
#930000000
1$
1)
#940000000
0$
0)
#950000000
1$
1)
#960000000
0$
0)
#970000000
1$
1)
#980000000
0$
0)
#990000000
1$
1)
#1000000000
0!
1"
0#
0$
0&
1'
0(
0)
