Exercises/14.0) count_BCD/sources/ffd.vhd
-- Author: Francesco Cavina <francescocavina98@gmail.com>
-- Brief:  This is the HW description for a flip-flop D

library IEEE;
use IEEE.std_logic_1164.all;

entity ffd is
    port(
        d_i:   in  std_logic;
        ena_i: in  std_logic;
        rst_i: in  std_logic;
        clk_i: in  std_logic;
        q_o:   out std_logic
    );
end entity ffd;

architecture ffd_arch of ffd is
    -- Declaration

begin
    -- Description
    process(clk_i) is
    begin
        if rising_edge(clk_i) then
            if rst_i = '1' then
                q_o <= '0';
            elsif ena_i = '1' then
                q_o <= d_i;
            end if;         
        end if;      
    end process;    
end architecture ffd_arch;

Exercises/06.0) shift_reg_Nbit/sources/shift_reg_Nbit.vhd
-- Author: Francesco Cavina <francescocavina98@gmail.com>
-- Brief:  This is the HW description for a N bit shift register

library IEEE;
use IEEE.std_logic_1164.all;

entity shift_reg_Nbit is
    generic(
        N: natural := 4
    );
    port(
        input_i:  in  std_logic;
        ena_i:    in  std_logic;
        rst_i:    in  std_logic;
        clk_i:    in  std_logic;
        output_o: out std_logic
    );
end entity shift_reg_Nbit;

architecture shift_reg_Nbit_arch of shift_reg_Nbit is
    -- Declaration
    component ffd is
        port(
            d_i:   in  std_logic;
            ena_i: in  std_logic;
            rst_i: in  std_logic;
            clk_i: in  std_logic;
            q_o:   out std_logic
        );
    end component ffd;
    signal d: std_logic_vector(0 to N);

begin
    -- Description
    d(0)     <= input_i;
    shift_reg_i: for i in 0 to N-1 generate
        ffd_inst: ffd
            port map(
                d_i   => d(i),
                ena_i => ena_i,
                rst_i => rst_i,
                clk_i => clk_i,
                q_o   => d(i+1)
            );
    end generate;
    output_o <= d(N);
end architecture shift_reg_Nbit_arch;

Exercises/06.0) shift_reg_Nbit/sources/shift_reg_Nbit_tb.vhd
-- Author: Francesco Cavina <francescocavina98@gmail.com>
-- Brief:  This is the testbench of an N bit shift register

library IEEE;
use IEEE.std_logic_1164.all;

entity shift_reg_Nbit_tb is
end entity shift_reg_Nbit_tb;

architecture shift_reg_Nbit_tb_arch of shift_reg_Nbit_tb is
    -- Declaration
    component shift_reg_Nbit is
        generic(
            N: natural := 4
        );
        port(
            input_i:  in  std_logic;
            ena_i:    in  std_logic;
            rst_i:    in  std_logic;
            clk_i:    in  std_logic;
            output_o: out std_logic
        );
    end component shift_reg_Nbit;

    constant N_tb:      natural   := 4;
    signal   input_tb:  std_logic := '0';
    signal   ena_tb:    std_logic := '1';
    signal   rst_tb:    std_logic := '0';
    signal   clk_tb:    std_logic := '0';
    signal   output_tb: std_logic;

begin
    -- Description
    clk_tb   <= not(clk_tb) after 50 ns;
    input_tb <= '1' after 250 ns, '0' after 450 ns, '1' after 650 ns, '0' after 850 ns;

    DUT: shift_reg_Nbit 
        generic map(
            N => N_tb
        )
        port map(
            input_i  => input_tb,
            ena_i    => ena_tb,
            rst_i    => rst_tb,
            clk_i    => clk_tb,
            output_o => output_tb
        );
end architecture shift_reg_Nbit_tb_arch;

Exercises/06.0) shift_reg_Nbit/simulation/shift_reg_Nbit_tb.vcd
$date
  Tue Sep 19 23:15:14 2023
$end
$version
  GHDL v0
$end
$timescale
  1 fs
$end
$scope module standard $end
$upscope $end
$scope module std_logic_1164 $end
$upscope $end
$scope module shift_reg_nbit_tb $end
$var reg 1 ! input_tb $end
$var reg 1 " ena_tb $end
$var reg 1 # rst_tb $end
$var reg 1 $ clk_tb $end
$var reg 1 % output_tb $end
$scope module dut $end
$var reg 1 & input_i $end
$var reg 1 ' ena_i $end
$var reg 1 ( rst_i $end
$var reg 1 ) clk_i $end
$var reg 1 * output_o $end
$var reg 5 + d[0:4] $end
$scope module shift_reg_i(0) $end
$scope module ffd_inst $end
$var reg 1 , d_i $end
$var reg 1 - ena_i $end
$var reg 1 . rst_i $end
$var reg 1 / clk_i $end
$var reg 1 0 q_o $end
$upscope $end
$upscope $end
$scope module shift_reg_i(1) $end
$scope module ffd_inst $end
$var reg 1 1 d_i $end
$var reg 1 2 ena_i $end
$var reg 1 3 rst_i $end
$var reg 1 4 clk_i $end
$var reg 1 5 q_o $end
$upscope $end
$upscope $end
$scope module shift_reg_i(2) $end
$scope module ffd_inst $end
$var reg 1 6 d_i $end
$var reg 1 7 ena_i $end
$var reg 1 8 rst_i $end
$var reg 1 9 clk_i $end
$var reg 1 : q_o $end
$upscope $end
$upscope $end
$scope module shift_reg_i(3) $end
$scope module ffd_inst $end
$var reg 1 ; d_i $end
$var reg 1 < ena_i $end
$var reg 1 = rst_i $end
$var reg 1 > clk_i $end
$var reg 1 ? q_o $end
$upscope $end
$upscope $end
$upscope $end
$upscope $end
$enddefinitions $end
#0
0!
1"
0#
0$
U%
0&
1'
0(
0)
U*
b0UUUU +
0,
1-
0.
0/
U0
U1
12
03
04
U5
U6
17
08
09
U:
U;
1<
0=
0>
U?
#50000000
1$
1)
b00UUU +
1/
00
01
14
19
1>
#100000000
0$
0)
0/
04
09
0>
#150000000
1$
1)
b000UU +
1/
14
05
06
19
1>
#200000000
0$
0)
0/
04
09
0>
#250000000
1!
1$
1&
1)
b1000U +
1,
1/
14
19
0:
0;
1>
#300000000
0$
0)
0/
04
09
0>
#350000000
1$
0%
1)
0*
b11000 +
1/
10
11
14
19
1>
0?
#400000000
0$
0)
0/
04
09
0>
#450000000
0!
1$
0&
1)
b01100 +
0,
1/
14
15
16
19
1>
#500000000
0$
0)
0/
04
09
0>
#550000000
1$
1)
b00110 +
1/
00
01
14
19
1:
1;
1>
#600000000
0$
0)
0/
04
09
0>
#650000000
1!
1$
1%
1&
1)
1*
b10011 +
1,
1/
14
05
06
19
1>
1?
#700000000
0$
0)
0/
04
09
0>
#750000000
1$
1)
b11001 +
1/
10
11
14
19
0:
0;
1>
#800000000
0$
0)
0/
04
09
0>
#850000000
0!
1$
0%
0&
1)
0*
b01100 +
0,
1/
14
15
16
19
1>
0?
#900000000
0$
0)
0/
04
09
0>
#950000000
1$
1)
b00110 +
1/
00
01
14
19
1:
1;
1>
#1000000000
0$
0)
0/
04
09
0>
#1050000000
1$
1%
1)
1*
b00011 +
1/
14
05
06
19
1>
1?
#1100000000
0$
0)
0/
04
09
0>
#1150000000
1$
1)
b00001 +
1/
14
19
0:
0;
1>
#1200000000
0$
0)
0/
04
09
0>
#1250000000
1$
0%
1)
0*
b00000 +
1/
14
19
1>
0?
