Exercises/11.0) count_4bit/sources/count_4bit.vhd
-- Author: Francesco Cavina <francescocavina98@gmail.com>
-- Brief:  This is the HW description for a 4 bit binary counter

library IEEE;
use IEEE.std_logic_1164.all;
use IEEE.numeric_std.all;

entity count_4bit is
    port(
        clk_i: in  std_logic;
        rst_i: in  std_logic;
        ena_i: in  std_logic;
        q_o:   out std_logic_vector(3 downto 0);
        max_o: out std_logic
    );
end entity count_4bit;

architecture count_4bit_arch of count_4bit is
    -- Declaration
    signal orOutput:   std_logic;
    signal andOutput:  std_logic;
    signal sumOutput:  std_logic_vector(3 downto 0);
    signal qOutput:    std_logic_vector(3 downto 0);
    signal compOutput: std_logic;

begin
    -- Description
    process(clk_i) is
    begin
        if rising_edge(clk_i) then
            if orOutput = '1' then
                qOutput <= (others => '0');
            elsif ena_i = '1' then
                qOutput <= sumOutput;
            end if;         
        end if;      
    end process;    

    sumOutput  <= std_logic_vector(unsigned(qOutput) + 1);
    compOutput <= '1' when qOutput = std_logic_vector(to_unsigned(15, 4)) else '0';
    orOutput   <= rst_i or andOutput;
    andOutput  <= ena_i and compOutput;
    max_o   <= compOutput;
    q_o     <= qOutput;
end architecture count_4bit_arch;

Exercises/11.0) count_4bit/sources/count_4bit_tb.vhd
-- Author: Francesco Cavina <francescocavina98@gmail.com>
-- Brief:  This is the testbench of a 4 bit binary counter

library IEEE;
use IEEE.std_logic_1164.all;

entity count_4bit_tb is
end entity count_4bit_tb;

architecture count_4bit_tb_arch of count_4bit_tb is
    -- Declaration
    component count_4bit is
        port(
            clk_i: in  std_logic;
            rst_i: in  std_logic;
            ena_i: in  std_logic;
            q_o:   out std_logic_vector(3 downto 0);
            max_o: out std_logic
        );
    end component count_4bit;

    signal   clk_tb:  std_logic := '0';
    signal   rst_tb:  std_logic := '1';
    signal   ena_tb:  std_logic := '1';
    signal   q_tb:    std_logic_vector(3 downto 0);
    signal   max_tb:  std_logic;

begin
    -- Description
    clk_tb <= not clk_tb after 10 ns;
    rst_tb <= '0' after    10 ns;
    ena_tb <= '0' after 10300 ns;

    DUT: count_4bit
        port map(
            clk_i => clk_tb,
            rst_i => rst_tb,
            ena_i => ena_tb,
            q_o   => q_tb,
            max_o => max_tb
        );
end architecture count_4bit_tb_arch;

Exercises/11.0) count_4bit/simulation/count_4bit_tb.vcd
$date
  Mon Oct  2 19:28:26 2023
$end
$version
  GHDL v0
$end
$timescale
  1 fs
$end
$scope module standard $end
$upscope $end
$scope module std_logic_1164 $end
$upscope $end
$scope module numeric_std $end
$upscope $end
$scope module count_4bit_tb $end
$var reg 1 ! clk_tb $end
$var reg 1 " rst_tb $end
$var reg 1 # ena_tb $end
$var reg 4 $ q_tb[3:0] $end
$var reg 1 % max_tb $end
$scope module dut $end
$var reg 1 & clk_i $end
$var reg 1 ' rst_i $end
$var reg 1 ( ena_i $end
$var reg 4 ) q_o[3:0] $end
$var reg 1 * max_o $end
$var reg 1 + oroutput $end
$var reg 1 , andoutput $end
$var reg 4 - sumoutput[3:0] $end
$var reg 4 . qoutput[3:0] $end
$var reg 1 / compoutput $end
$upscope $end
$upscope $end
$enddefinitions $end
#0
0!
1"
1#
bUUUU $
0%
0&
1'
1(
bUUUU )
0*
1+
0,
bXXXX -
bUUUU .
0/
#10000000
1!
0"
b0000 $
1&
0'
b0000 )
0+
b0001 -
b0000 .
#20000000
0!
0&
#30000000
1!
b0001 $
1&
b0001 )
b0010 -
b0001 .
#40000000
0!
0&
#50000000
1!
b0010 $
1&
b0010 )
b0011 -
b0010 .
#60000000
0!
0&
#70000000
1!
b0011 $
1&
b0011 )
b0100 -
b0011 .
#80000000
0!
0&
#90000000
1!
b0100 $
1&
b0100 )
b0101 -
b0100 .
#100000000
0!
0&
#110000000
1!
b0101 $
1&
b0101 )
b0110 -
b0101 .
#120000000
0!
0&
#130000000
1!
b0110 $
1&
b0110 )
b0111 -
b0110 .
#140000000
0!
0&
#150000000
1!
b0111 $
1&
b0111 )
b1000 -
b0111 .
#160000000
0!
0&
#170000000
1!
b1000 $
1&
b1000 )
b1001 -
b1000 .
#180000000
0!
0&
#190000000
1!
b1001 $
1&
b1001 )
b1010 -
b1001 .
#200000000
0!
0&
#210000000
1!
b1010 $
1&
b1010 )
b1011 -
b1010 .
#220000000
0!
0&
#230000000
1!
b1011 $
1&
b1011 )
b1100 -
b1011 .
#240000000
0!
0&
#250000000
1!
b1100 $
1&
b1100 )
b1101 -
b1100 .
#260000000
0!
0&
#270000000
1!
b1101 $
1&
b1101 )
b1110 -
b1101 .
#280000000
0!
0&
#290000000
1!
b1110 $
1&
b1110 )
b1111 -
b1110 .
#300000000
0!
0&
#310000000
1!
b1111 $
1%
1&
b1111 )
1*
1+
1,
b0000 -
b1111 .
1/
#320000000
0!
0&
#330000000
1!
b0000 $
0%
1&
b0000 )
0*
0+
0,
b0001 -
b0000 .
0/
#340000000
0!
0&
#350000000
1!
b0001 $
1&
b0001 )
b0010 -
b0001 .
#360000000
0!
0&
#370000000
1!
b0010 $
1&
b0010 )
b0011 -
b0010 .
#380000000
0!
0&
#390000000
1!
b0011 $
1&
b0011 )
b0100 -
b0011 .
#400000000
0!
0&
#410000000
1!
b0100 $
1&
b0100 )
b0101 -
b0100 .
#420000000
0!
0&
#430000000
1!
b0101 $
1&
b0101 )
b0110 -
b0101 .
#440000000
0!
0&
#450000000
1!
b0110 $
1&
b0110 )
b0111 -
b0110 .
#460000000
0!
0&
#470000000
1!
b0111 $
1&
b0111 )
b1000 -
b0111 .
#480000000
0!
0&
#490000000
1!
b1000 $
1&
b1000 )
b1001 -
b1000 .
#500000000
0!
0&
#510000000
1!
b1001 $
1&
b1001 )
b1010 -
b1001 .
#520000000
0!
0&
#530000000
1!
b1010 $
1&
b1010 )
b1011 -
b1010 .
#540000000
0!
0&
#550000000
1!
b1011 $
1&
b1011 )
b1100 -
b1011 .
#560000000
0!
0&
#570000000
1!
b1100 $
1&
b1100 )
b1101 -
b1100 .
#580000000
0!
0&
#590000000
1!
b1101 $
1&
b1101 )
b1110 -
b1101 .
#600000000
0!
0&
#610000000
1!
b1110 $
1&
b1110 )
b1111 -
b1110 .
#620000000
0!
0&
#630000000
1!
b1111 $
1%
1&
b1111 )
1*
1+
1,
b0000 -
b1111 .
1/
#640000000
0!
0&
#650000000
1!
b0000 $
0%
1&
b0000 )
0*
0+
0,
b0001 -
b0000 .
0/
#660000000
0!
0&
#670000000
1!
b0001 $
1&
b0001 )
b0010 -
b0001 .
#680000000
0!
0&
#690000000
1!
b0010 $
1&
b0010 )
b0011 -
b0010 .
#700000000
0!
0&
#710000000
1!
b0011 $
1&
b0011 )
b0100 -
b0011 .
#720000000
0!
0&
#730000000
1!
b0100 $
1&
b0100 )
b0101 -
b0100 .
#740000000
0!
0&
#750000000
1!
b0101 $
1&
b0101 )
b0110 -
b0101 .
#760000000
0!
0&
#770000000
1!
b0110 $
1&
b0110 )
b0111 -
b0110 .
#780000000
0!
0&
#790000000
1!
b0111 $
1&
b0111 )
b1000 -
b0111 .
#800000000
0!
0&
#810000000
1!
b1000 $
1&
b1000 )
b1001 -
b1000 .
#820000000
0!
0&
#830000000
1!
b1001 $
1&
b1001 )
b1010 -
b1001 .
#840000000
0!
0&
#850000000
1!
b1010 $
1&
b1010 )
b1011 -
b1010 .
#860000000
0!
0&
#870000000
1!
b1011 $
1&
b1011 )
b1100 -
b1011 .
#880000000
0!
0&
#890000000
1!
b1100 $
1&
b1100 )
b1101 -
b1100 .
#900000000
0!
0&
#910000000
1!
b1101 $
1&
b1101 )
b1110 -
b1101 .
#920000000
0!
0&
#930000000
1!
b1110 $
1&
b1110 )
b1111 -
b1110 .
#940000000
0!
0&
#950000000
1!
b1111 $
1%
1&
b1111 )
1*
1+
1,
b0000 -
b1111 .
1/
#960000000
0!
0&
#970000000
1!
b0000 $
0%
1&
b0000 )
0*
0+
0,
b0001 -
b0000 .
0/
#980000000
0!
0&
#990000000
1!
b0001 $
1&
b0001 )
b0010 -
b0001 .
#1000000000
0!
0&
#1010000000
1!
b0010 $
1&
b0010 )
b0011 -
b0010 .
#1020000000
0!
0&
#1030000000
1!
b0011 $
1&
b0011 )
b0100 -
b0011 .
#1040000000
0!
0&
#1050000000
1!
b0100 $
1&
b0100 )
b0101 -
b0100 .
#1060000000
0!
0&
#1070000000
1!
b0101 $
1&
b0101 )
b0110 -
b0101 .
#1080000000
0!
0&
#1090000000
1!
b0110 $
1&
b0110 )
b0111 -
b0110 .
#1100000000
0!
0&
#1110000000
1!
b0111 $
1&
b0111 )
b1000 -
b0111 .
#1120000000
0!
0&
#1130000000
1!
b1000 $
1&
b1000 )
b1001 -
b1000 .
#1140000000
0!
0&
#1150000000
1!
b1001 $
1&
b1001 )
b1010 -
b1001 .
#1160000000
0!
0&
#1170000000
1!
b1010 $
1&
b1010 )
b1011 -
b1010 .
#1180000000
0!
0&
#1190000000
1!
b1011 $
1&
b1011 )
b1100 -
b1011 .
#1200000000
0!
0&
#1210000000
1!
b1100 $
1&
b1100 )
b1101 -
b1100 .
#1220000000
0!
0&
#1230000000
1!
b1101 $
1&
b1101 )
b1110 -
b1101 .
#1240000000
0!
0&
#1250000000
1!
b1110 $
1&
b1110 )
b1111 -
b1110 .
#1260000000
0!
0&
#1270000000
1!
b1111 $
1%
1&
b1111 )
1*
1+
1,
b0000 -
b1111 .
1/
#1280000000
0!
0&
#1290000000
1!
b0000 $
0%
1&
b0000 )
0*
0+
0,
b0001 -
b0000 .
0/
#1300000000
0!
0&
#1310000000
1!
b0001 $
1&
b0001 )
b0010 -
b0001 .
#1320000000
0!
0&
#1330000000
1!
b0010 $
1&
b0010 )
b0011 -
b0010 .
#1340000000
0!
0&
#1350000000
1!
b0011 $
1&
b0011 )
b0100 -
b0011 .
#1360000000
0!
0&
#1370000000
1!
b0100 $
1&
b0100 )
b0101 -
b0100 .
#1380000000
0!
0&
#1390000000
1!
b0101 $
1&
b0101 )
b0110 -
b0101 .
#1400000000
0!
0&
#1410000000
1!
b0110 $
1&
b0110 )
b0111 -
b0110 .
#1420000000
0!
0&
#1430000000
1!
b0111 $
1&
b0111 )
b1000 -
b0111 .
#1440000000
0!
0&
#1450000000
1!
b1000 $
1&
b1000 )
b1001 -
b1000 .
#1460000000
0!
0&
#1470000000
1!
b1001 $
1&
b1001 )
b1010 -
b1001 .
#1480000000
0!
0&
#1490000000
1!
b1010 $
1&
b1010 )
b1011 -
b1010 .
#1500000000
0!
0&
#1510000000
1!
b1011 $
1&
b1011 )
b1100 -
b1011 .
#1520000000
0!
0&
#1530000000
1!
b1100 $
1&
b1100 )
b1101 -
b1100 .
#1540000000
0!
0&
#1550000000
1!
b1101 $
1&
b1101 )
b1110 -
b1101 .
#1560000000
0!
0&
#1570000000
1!
b1110 $
1&
b1110 )
b1111 -
b1110 .
#1580000000
0!
0&
#1590000000
1!
b1111 $
1%
1&
b1111 )
1*
1+
1,
b0000 -
b1111 .
1/
#1600000000
0!
0&
#1610000000
1!
b0000 $
0%
1&
b0000 )
0*
0+
0,
b0001 -
b0000 .
0/
#1620000000
0!
0&
#1630000000
1!
b0001 $
1&
b0001 )
b0010 -
b0001 .
#1640000000
0!
0&
#1650000000
1!
b0010 $
1&
b0010 )
b0011 -
b0010 .
#1660000000
0!
0&
#1670000000
1!
b0011 $
1&
b0011 )
b0100 -
b0011 .
#1680000000
0!
0&
#1690000000
1!
b0100 $
1&
b0100 )
b0101 -
b0100 .
#1700000000
0!
0&
#1710000000
1!
b0101 $
1&
b0101 )
b0110 -
b0101 .
#1720000000
0!
0&
#1730000000
1!
b0110 $
1&
b0110 )
b0111 -
b0110 .
#1740000000
0!
0&
#1750000000
1!
b0111 $
1&
b0111 )
b1000 -
b0111 .
#1760000000
0!
0&
#1770000000
1!
b1000 $
1&
b1000 )
b1001 -
b1000 .
#1780000000
0!
0&
#1790000000
1!
b1001 $
1&
b1001 )
b1010 -
b1001 .
#1800000000
0!
0&
#1810000000
1!
b1010 $
1&
b1010 )
b1011 -
b1010 .
#1820000000
0!
0&
#1830000000
1!
b1011 $
1&
b1011 )
b1100 -
b1011 .
#1840000000
0!
0&
#1850000000
1!
b1100 $
1&
b1100 )
b1101 -
b1100 .
#1860000000
0!
0&
#1870000000
1!
b1101 $
1&
b1101 )
b1110 -
b1101 .
#1880000000
0!
0&
#1890000000
1!
b1110 $
1&
b1110 )
b1111 -
b1110 .
#1900000000
0!
0&
#1910000000
1!
b1111 $
1%
1&
b1111 )
1*
1+
1,
b0000 -
b1111 .
1/
#1920000000
0!
0&
#1930000000
1!
b0000 $
0%
1&
b0000 )
0*
0+
0,
b0001 -
b0000 .
0/
#1940000000
0!
0&
#1950000000
1!
b0001 $
1&
b0001 )
b0010 -
b0001 .
#1960000000
0!
0&
#1970000000
1!
b0010 $
1&
b0010 )
b0011 -
b0010 .
#1980000000
0!
0&
#1990000000
1!
b0011 $
1&
b0011 )
b0100 -
b0011 .
#2000000000
0!
0&
#2010000000
1!
b0100 $
1&
b0100 )
b0101 -
b0100 .
#2020000000
0!
0&
#2030000000
1!
b0101 $
1&
b0101 )
b0110 -
b0101 .
#2040000000
0!
0&
#2050000000
1!
b0110 $
1&
b0110 )
b0111 -
b0110 .
#2060000000
0!
0&
#2070000000
1!
b0111 $
1&
b0111 )
b1000 -
b0111 .
#2080000000
0!
0&
#2090000000
1!
b1000 $
1&
b1000 )
b1001 -
b1000 .
#2100000000
0!
0&
#2110000000
1!
b1001 $
1&
b1001 )
b1010 -
b1001 .
#2120000000
0!
0&
#2130000000
1!
b1010 $
1&
b1010 )
b1011 -
b1010 .
#2140000000
0!
0&
#2150000000
1!
b1011 $
1&
b1011 )
b1100 -
b1011 .
#2160000000
0!
0&
#2170000000
1!
b1100 $
1&
b1100 )
b1101 -
b1100 .
#2180000000
0!
0&
#2190000000
1!
b1101 $
1&
b1101 )
b1110 -
b1101 .
#2200000000
0!
0&
#2210000000
1!
b1110 $
1&
b1110 )
b1111 -
b1110 .
#2220000000
0!
0&
#2230000000
1!
b1111 $
1%
1&
b1111 )
1*
1+
1,
b0000 -
b1111 .
1/
#2240000000
0!
0&
#2250000000
1!
b0000 $
0%
1&
b0000 )
0*
0+
0,
b0001 -
b0000 .
0/
#2260000000
0!
0&
#2270000000
1!
b0001 $
1&
b0001 )
b0010 -
b0001 .
#2280000000
0!
0&
#2290000000
1!
b0010 $
1&
b0010 )
b0011 -
b0010 .
#2300000000
0!
0&
#2310000000
1!
b0011 $
1&
b0011 )
b0100 -
b0011 .
#2320000000
0!
0&
#2330000000
1!
b0100 $
1&
b0100 )
b0101 -
b0100 .
#2340000000
0!
0&
#2350000000
1!
b0101 $
1&
b0101 )
b0110 -
b0101 .
#2360000000
0!
0&
#2370000000
1!
b0110 $
1&
b0110 )
b0111 -
b0110 .
#2380000000
0!
0&
#2390000000
1!
b0111 $
1&
b0111 )
b1000 -
b0111 .
#2400000000
0!
0&
#2410000000
1!
b1000 $
1&
b1000 )
b1001 -
b1000 .
#2420000000
0!
0&
#2430000000
1!
b1001 $
1&
b1001 )
b1010 -
b1001 .
#2440000000
0!
0&
#2450000000
1!
b1010 $
1&
b1010 )
b1011 -
b1010 .
#2460000000
0!
0&
#2470000000
1!
b1011 $
1&
b1011 )
b1100 -
b1011 .
#2480000000
0!
0&
#2490000000
1!
b1100 $
1&
b1100 )
b1101 -
b1100 .
#2500000000
0!
0&
#2510000000
1!
b1101 $
1&
b1101 )
b1110 -
b1101 .
#2520000000
0!
0&
#2530000000
1!
b1110 $
1&
b1110 )
b1111 -
b1110 .
#2540000000
0!
0&
#2550000000
1!
b1111 $
1%
1&
b1111 )
1*
1+
1,
b0000 -
b1111 .
1/
#2560000000
0!
0&
#2570000000
1!
b0000 $
0%
1&
b0000 )
0*
0+
0,
b0001 -
b0000 .
0/
#2580000000
0!
0&
#2590000000
1!
b0001 $
1&
b0001 )
b0010 -
b0001 .
#2600000000
0!
0&
#2610000000
1!
b0010 $
1&
b0010 )
b0011 -
b0010 .
#2620000000
0!
0&
#2630000000
1!
b0011 $
1&
b0011 )
b0100 -
b0011 .
#2640000000
0!
0&
#2650000000
1!
b0100 $
1&
b0100 )
b0101 -
b0100 .
#2660000000
0!
0&
#2670000000
1!
b0101 $
1&
b0101 )
b0110 -
b0101 .
#2680000000
0!
0&
#2690000000
1!
b0110 $
1&
b0110 )
b0111 -
b0110 .
#2700000000
0!
0&
#2710000000
1!
b0111 $
1&
b0111 )
b1000 -
b0111 .
#2720000000
0!
0&
#2730000000
1!
b1000 $
1&
b1000 )
b1001 -
b1000 .
#2740000000
0!
0&
#2750000000
1!
b1001 $
1&
b1001 )
b1010 -
b1001 .
#2760000000
0!
0&
#2770000000
1!
b1010 $
1&
b1010 )
b1011 -
b1010 .
#2780000000
0!
0&
#2790000000
1!
b1011 $
1&
b1011 )
b1100 -
b1011 .
#2800000000
0!
0&
#2810000000
1!
b1100 $
1&
b1100 )
b1101 -
b1100 .
#2820000000
0!
0&
#2830000000
1!
b1101 $
1&
b1101 )
b1110 -
b1101 .
#2840000000
0!
0&
#2850000000
1!
b1110 $
1&
b1110 )
b1111 -
b1110 .
#2860000000
0!
0&
#2870000000
1!
b1111 $
1%
1&
b1111 )
1*
1+
1,
b0000 -
b1111 .
1/
#2880000000
0!
0&
#2890000000
1!
b0000 $
0%
1&
b0000 )
0*
0+
0,
b0001 -
b0000 .
0/
#2900000000
0!
0&
#2910000000
1!
b0001 $
1&
b0001 )
b0010 -
b0001 .
#2920000000
0!
0&
#2930000000
1!
b0010 $
1&
b0010 )
b0011 -
b0010 .
#2940000000
0!
0&
#2950000000
1!
b0011 $
1&
b0011 )
b0100 -
b0011 .
#2960000000
0!
0&
#2970000000
1!
b0100 $
1&
b0100 )
b0101 -
b0100 .
#2980000000
0!
0&
#2990000000
1!
b0101 $
1&
b0101 )
b0110 -
b0101 .
#3000000000
0!
0&
#3010000000
1!
b0110 $
1&
b0110 )
b0111 -
b0110 .
#3020000000
0!
0&
#3030000000
1!
b0111 $
1&
b0111 )
b1000 -
b0111 .
#3040000000
0!
0&
#3050000000
1!
b1000 $
1&
b1000 )
b1001 -
b1000 .
#3060000000
0!
0&
#3070000000
1!
b1001 $
1&
b1001 )
b1010 -
b1001 .
#3080000000
0!
0&
#3090000000
1!
b1010 $
1&
b1010 )
b1011 -
b1010 .
#3100000000
0!
0&
#3110000000
1!
b1011 $
1&
b1011 )
b1100 -
b1011 .
#3120000000
0!
0&
#3130000000
1!
b1100 $
1&
b1100 )
b1101 -
b1100 .
#3140000000
0!
0&
#3150000000
1!
b1101 $
1&
b1101 )
b1110 -
b1101 .
#3160000000
0!
0&
#3170000000
1!
b1110 $
1&
b1110 )
b1111 -
b1110 .
#3180000000
0!
0&
#3190000000
1!
b1111 $
1%
1&
b1111 )
1*
1+
1,
b0000 -
b1111 .
1/
#3200000000
0!
0&
#3210000000
1!
b0000 $
0%
1&
b0000 )
0*
0+
0,
b0001 -
b0000 .
0/
#3220000000
0!
0&
#3230000000
1!
b0001 $
1&
b0001 )
b0010 -
b0001 .
#3240000000
0!
0&
#3250000000
1!
b0010 $
1&
b0010 )
b0011 -
b0010 .
#3260000000
0!
0&
#3270000000
1!
b0011 $
1&
b0011 )
b0100 -
b0011 .
#3280000000
0!
0&
#3290000000
1!
b0100 $
1&
b0100 )
b0101 -
b0100 .
#3300000000
0!
0&
#3310000000
1!
b0101 $
1&
b0101 )
b0110 -
b0101 .
#3320000000
0!
0&
#3330000000
1!
b0110 $
1&
b0110 )
b0111 -
b0110 .
#3340000000
0!
0&
#3350000000
1!
b0111 $
1&
b0111 )
b1000 -
b0111 .
#3360000000
0!
0&
#3370000000
1!
b1000 $
1&
b1000 )
b1001 -
b1000 .
#3380000000
0!
0&
#3390000000
1!
b1001 $
1&
b1001 )
b1010 -
b1001 .
#3400000000
0!
0&
#3410000000
1!
b1010 $
1&
b1010 )
b1011 -
b1010 .
#3420000000
0!
0&
#3430000000
1!
b1011 $
1&
b1011 )
b1100 -
b1011 .
#3440000000
0!
0&
#3450000000
1!
b1100 $
1&
b1100 )
b1101 -
b1100 .
#3460000000
0!
0&
#3470000000
1!
b1101 $
1&
b1101 )
b1110 -
b1101 .
#3480000000
0!
0&
#3490000000
1!
b1110 $
1&
b1110 )
b1111 -
b1110 .
#3500000000
0!
0&
#3510000000
1!
b1111 $
1%
1&
b1111 )
1*
1+
1,
b0000 -
b1111 .
1/
#3520000000
0!
0&
#3530000000
1!
b0000 $
0%
1&
b0000 )
0*
0+
0,
b0001 -
b0000 .
0/
#3540000000
0!
0&
#3550000000
1!
b0001 $
1&
b0001 )
b0010 -
b0001 .
#3560000000
0!
0&
#3570000000
1!
b0010 $
1&
b0010 )
b0011 -
b0010 .
#3580000000
0!
0&
#3590000000
1!
b0011 $
1&
b0011 )
b0100 -
b0011 .
#3600000000
0!
0&
#3610000000
1!
b0100 $
1&
b0100 )
b0101 -
b0100 .
#3620000000
0!
0&
#3630000000
1!
b0101 $
1&
b0101 )
b0110 -
b0101 .
#3640000000
0!
0&
#3650000000
1!
b0110 $
1&
b0110 )
b0111 -
b0110 .
#3660000000
0!
0&
#3670000000
1!
b0111 $
1&
b0111 )
b1000 -
b0111 .
#3680000000
0!
0&
#3690000000
1!
b1000 $
1&
b1000 )
b1001 -
b1000 .
#3700000000
0!
0&
#3710000000
1!
b1001 $
1&
b1001 )
b1010 -
b1001 .
#3720000000
0!
0&
#3730000000
1!
b1010 $
1&
b1010 )
b1011 -
b1010 .
#3740000000
0!
0&
#3750000000
1!
b1011 $
1&
b1011 )
b1100 -
b1011 .
#3760000000
0!
0&
#3770000000
1!
b1100 $
1&
b1100 )
b1101 -
b1100 .
#3780000000
0!
0&
#3790000000
1!
b1101 $
1&
b1101 )
b1110 -
b1101 .
#3800000000
0!
0&
#3810000000
1!
b1110 $
1&
b1110 )
b1111 -
b1110 .
#3820000000
0!
0&
#3830000000
1!
b1111 $
1%
1&
b1111 )
1*
1+
1,
b0000 -
b1111 .
1/
#3840000000
0!
0&
#3850000000
1!
b0000 $
0%
1&
b0000 )
0*
0+
0,
b0001 -
b0000 .
0/
#3860000000
0!
0&
#3870000000
1!
b0001 $
1&
b0001 )
b0010 -
b0001 .
#3880000000
0!
0&
#3890000000
1!
b0010 $
1&
b0010 )
b0011 -
b0010 .
#3900000000
0!
0&
#3910000000
1!
b0011 $
1&
b0011 )
b0100 -
b0011 .
#3920000000
0!
0&
#3930000000
1!
b0100 $
1&
b0100 )
b0101 -
b0100 .
#3940000000
0!
0&
#3950000000
1!
b0101 $
1&
b0101 )
b0110 -
b0101 .
#3960000000
0!
0&
#3970000000
1!
b0110 $
1&
b0110 )
b0111 -
b0110 .
#3980000000
0!
0&
#3990000000
1!
b0111 $
1&
b0111 )
b1000 -
b0111 .
#4000000000
0!
0&
#4010000000
1!
b1000 $
1&
b1000 )
b1001 -
b1000 .
#4020000000
0!
0&
#4030000000
1!
b1001 $
1&
b1001 )
b1010 -
b1001 .
#4040000000
0!
0&
#4050000000
1!
b1010 $
1&
b1010 )
b1011 -
b1010 .
#4060000000
0!
0&
#4070000000
1!
b1011 $
1&
b1011 )
b1100 -
b1011 .
#4080000000
0!
0&
#4090000000
1!
b1100 $
1&
b1100 )
b1101 -
b1100 .
#4100000000
0!
0&
#4110000000
1!
b1101 $
1&
b1101 )
b1110 -
b1101 .
#4120000000
0!
0&
#4130000000
1!
b1110 $
1&
b1110 )
b1111 -
b1110 .
#4140000000
0!
0&
#4150000000
1!
b1111 $
1%
1&
b1111 )
1*
1+
1,
b0000 -
b1111 .
1/
#4160000000
0!
0&
#4170000000
1!
b0000 $
0%
1&
b0000 )
0*
0+
0,
b0001 -
b0000 .
0/
#4180000000
0!
0&
#4190000000
1!
b0001 $
1&
b0001 )
b0010 -
b0001 .
#4200000000
0!
0&
#4210000000
1!
b0010 $
1&
b0010 )
b0011 -
b0010 .
#4220000000
0!
0&
#4230000000
1!
b0011 $
1&
b0011 )
b0100 -
b0011 .
#4240000000
0!
0&
#4250000000
1!
b0100 $
1&
b0100 )
b0101 -
b0100 .
#4260000000
0!
0&
#4270000000
1!
b0101 $
1&
b0101 )
b0110 -
b0101 .
#4280000000
0!
0&
#4290000000
1!
b0110 $
1&
b0110 )
b0111 -
b0110 .
#4300000000
0!
0&
#4310000000
1!
b0111 $
1&
b0111 )
b1000 -
b0111 .
#4320000000
0!
0&
#4330000000
1!
b1000 $
1&
b1000 )
b1001 -
b1000 .
#4340000000
0!
0&
#4350000000
1!
b1001 $
1&
b1001 )
b1010 -
b1001 .
#4360000000
0!
0&
#4370000000
1!
b1010 $
1&
b1010 )
b1011 -
b1010 .
#4380000000
0!
0&
#4390000000
1!
b1011 $
1&
b1011 )
b1100 -
b1011 .
#4400000000
0!
0&
#4410000000
1!
b1100 $
1&
b1100 )
b1101 -
b1100 .
#4420000000
0!
0&
#4430000000
1!
b1101 $
1&
b1101 )
b1110 -
b1101 .
#4440000000
0!
0&
#4450000000
1!
b1110 $
1&
b1110 )
b1111 -
b1110 .
#4460000000
0!
0&
#4470000000
1!
b1111 $
1%
1&
b1111 )
1*
1+
1,
b0000 -
b1111 .
1/
#4480000000
0!
0&
#4490000000
1!
b0000 $
0%
1&
b0000 )
0*
0+
0,
b0001 -
b0000 .
0/
#4500000000
0!
0&
#4510000000
1!
b0001 $
1&
b0001 )
b0010 -
b0001 .
#4520000000
0!
0&
#4530000000
1!
b0010 $
1&
b0010 )
b0011 -
b0010 .
#4540000000
0!
0&
#4550000000
1!
b0011 $
1&
b0011 )
b0100 -
b0011 .
#4560000000
0!
0&
#4570000000
1!
b0100 $
1&
b0100 )
b0101 -
b0100 .
#4580000000
0!
0&
#4590000000
1!
b0101 $
1&
b0101 )
b0110 -
b0101 .
#4600000000
0!
0&
#4610000000
1!
b0110 $
1&
b0110 )
b0111 -
b0110 .
#4620000000
0!
0&
#4630000000
1!
b0111 $
1&
b0111 )
b1000 -
b0111 .
#4640000000
0!
0&
#4650000000
1!
b1000 $
1&
b1000 )
b1001 -
b1000 .
#4660000000
0!
0&
#4670000000
1!
b1001 $
1&
b1001 )
b1010 -
b1001 .
#4680000000
0!
0&
#4690000000
1!
b1010 $
1&
b1010 )
b1011 -
b1010 .
#4700000000
0!
0&
#4710000000
1!
b1011 $
1&
b1011 )
b1100 -
b1011 .
#4720000000
0!
0&
#4730000000
1!
b1100 $
1&
b1100 )
b1101 -
b1100 .
#4740000000
0!
0&
#4750000000
1!
b1101 $
1&
b1101 )
b1110 -
b1101 .
#4760000000
0!
0&
#4770000000
1!
b1110 $
1&
b1110 )
b1111 -
b1110 .
#4780000000
0!
0&
#4790000000
1!
b1111 $
1%
1&
b1111 )
1*
1+
1,
b0000 -
b1111 .
1/
#4800000000
0!
0&
#4810000000
1!
b0000 $
0%
1&
b0000 )
0*
0+
0,
b0001 -
b0000 .
0/
#4820000000
0!
0&
#4830000000
1!
b0001 $
1&
b0001 )
b0010 -
b0001 .
#4840000000
0!
0&
#4850000000
1!
b0010 $
1&
b0010 )
b0011 -
b0010 .
#4860000000
0!
0&
#4870000000
1!
b0011 $
1&
b0011 )
b0100 -
b0011 .
#4880000000
0!
0&
#4890000000
1!
b0100 $
1&
b0100 )
b0101 -
b0100 .
#4900000000
0!
0&
#4910000000
1!
b0101 $
1&
b0101 )
b0110 -
b0101 .
#4920000000
0!
0&
#4930000000
1!
b0110 $
1&
b0110 )
b0111 -
b0110 .
#4940000000
0!
0&
#4950000000
1!
b0111 $
1&
b0111 )
b1000 -
b0111 .
#4960000000
0!
0&
#4970000000
1!
b1000 $
1&
b1000 )
b1001 -
b1000 .
#4980000000
0!
0&
#4990000000
1!
b1001 $
1&
b1001 )
b1010 -
b1001 .
#5000000000
0!
0&
#5010000000
1!
b1010 $
1&
b1010 )
b1011 -
b1010 .
#5020000000
0!
0&
#5030000000
1!
b1011 $
1&
b1011 )
b1100 -
b1011 .
#5040000000
0!
0&
#5050000000
1!
b1100 $
1&
b1100 )
b1101 -
b1100 .
#5060000000
0!
0&
#5070000000
1!
b1101 $
1&
b1101 )
b1110 -
b1101 .
#5080000000
0!
0&
#5090000000
1!
b1110 $
1&
b1110 )
b1111 -
b1110 .
#5100000000
0!
0&
#5110000000
1!
b1111 $
1%
1&
b1111 )
1*
1+
1,
b0000 -
b1111 .
1/
#5120000000
0!
0&
#5130000000
1!
b0000 $
0%
1&
b0000 )
0*
0+
0,
b0001 -
b0000 .
0/
#5140000000
0!
0&
#5150000000
1!
b0001 $
1&
b0001 )
b0010 -
b0001 .
#5160000000
0!
0&
#5170000000
1!
b0010 $
1&
b0010 )
b0011 -
b0010 .
#5180000000
0!
0&
#5190000000
1!
b0011 $
1&
b0011 )
b0100 -
b0011 .
#5200000000
0!
0&
#5210000000
1!
b0100 $
1&
b0100 )
b0101 -
b0100 .
#5220000000
0!
0&
#5230000000
1!
b0101 $
1&
b0101 )
b0110 -
b0101 .
#5240000000
0!
0&
#5250000000
1!
b0110 $
1&
b0110 )
b0111 -
b0110 .
#5260000000
0!
0&
#5270000000
1!
b0111 $
1&
b0111 )
b1000 -
b0111 .
#5280000000
0!
0&
#5290000000
1!
b1000 $
1&
b1000 )
b1001 -
b1000 .
#5300000000
0!
0&
#5310000000
1!
b1001 $
1&
b1001 )
b1010 -
b1001 .
#5320000000
0!
0&
#5330000000
1!
b1010 $
1&
b1010 )
b1011 -
b1010 .
#5340000000
0!
0&
#5350000000
1!
b1011 $
1&
b1011 )
b1100 -
b1011 .
#5360000000
0!
0&
#5370000000
1!
b1100 $
1&
b1100 )
b1101 -
b1100 .
#5380000000
0!
0&
#5390000000
1!
b1101 $
1&
b1101 )
b1110 -
b1101 .
#5400000000
0!
0&
