Exercises/14.0) count_BCD/sources/ffd.vhd
-- Author: Francesco Cavina <francescocavina98@gmail.com>
-- Brief:  This is the HW description for a flip-flop D

library IEEE;
use IEEE.std_logic_1164.all;

entity ffd is
    port(
        d_i:   in  std_logic;
        ena_i: in  std_logic;
        rst_i: in  std_logic;
        clk_i: in  std_logic;
        q_o:   out std_logic
    );
end entity ffd;

architecture ffd_arch of ffd is
    -- Declaration

begin
    -- Description
    process(clk_i) is
    begin
        if rising_edge(clk_i) then
            if rst_i = '1' then
                q_o <= '0';
            elsif ena_i = '1' then
                q_o <= d_i;
            end if;         
        end if;      
    end process;    
end architecture ffd_arch;

Exercises/05.2) reg_Nbit/sources/reg_Nbit.vhd
-- Author: Francesco Cavina <francescocavina98@gmail.com>
-- Brief:  This is the HW description for a N bit register

library IEEE;
use IEEE.std_logic_1164.all;

entity reg_Nbit is
    generic(
        N: natural := 4
    );
    port(
        d_i:   in  std_logic_vector(N-1 downto 0);
        ena_i: in  std_logic;
        rst_i: in  std_logic;
        clk_i: in  std_logic;
        q_o:   out std_logic_vector(N-1 downto 0)
    );
end entity reg_Nbit;

architecture reg_Nbit_arch of reg_Nbit is
    -- Declaration
    component ffd is
        port(
            d_i:   in  std_logic;
            ena_i: in  std_logic;
            rst_i: in  std_logic;
            clk_i: in  std_logic;
            q_o:   out std_logic
        );
    end component ffd;

begin
    -- Description
    reg_Nbit_i: for i in N-1 downto 0 generate
        ffd_inst: ffd
            port map(
                d_i => d_i(i),
                ena_i => ena_i,
                rst_i => rst_i,
                clk_i => clk_i,
                q_o   => q_o(i)
            );
    end generate;
end architecture reg_Nbit_arch;

Exercises/05.2) reg_Nbit/sources/reg_Nbit_tb.vhd
-- Author: Francesco Cavina <francescocavina98@gmail.com>
-- Brief:  This is the testbench of an N bit register

library IEEE;
use IEEE.std_logic_1164.all;
use IEEE.numeric_std.all;

entity reg_Nbit_tb is
end entity reg_Nbit_tb;

architecture reg_Nbit_tb_arch of reg_Nbit_tb is
    -- Declaration
    component reg_Nbit is
        generic(
            N: natural := 4
        );
        port(
            d_i:   in  std_logic_vector(N-1 downto 0);
            ena_i: in  std_logic;
            rst_i: in  std_logic;
            clk_i: in  std_logic;
            q_o:   out std_logic_vector(N-1 downto 0)
        );
    end component reg_Nbit;

    constant N_tb:   natural := 4; 
    signal   d_tb:   std_logic_vector(N_tb-1 downto 0) := std_logic_vector(to_unsigned(1, N_tb));
    signal   ena_tb: std_logic := '0';
    signal   rst_tb: std_logic := '0';
    signal   clk_tb: std_logic := '0';
    signal   q_tb:   std_logic_vector(N_tb-1 downto 0);

begin
    -- Description
    clk_tb <= not clk_tb after  10 ns;
    d_tb   <= not   d_tb after 100 ns;
    ena_tb <= not ena_tb after 200 ns;
    rst_tb <= not rst_tb after 800 ns;

    DUT: reg_Nbit
        generic map(
            N => N_tb
        )
        port map(
            d_i   => d_tb,
            ena_i => ena_tb,
            rst_i => rst_tb,
            clk_i => clk_tb,
            q_o   => q_tb
        );
end architecture reg_Nbit_tb_arch;

Exercises/05.2) reg_Nbit/simulation/reg_Nbit_tb.vcd
$date
  Mon Sep 18 23:27:22 2023
$end
$version
  GHDL v0
$end
$timescale
  1 fs
$end
$scope module standard $end
$upscope $end
$scope module std_logic_1164 $end
$upscope $end
$scope module numeric_std $end
$upscope $end
$scope module reg_nbit_tb $end
$var reg 4 ! d_tb[3:0] $end
$var reg 1 " ena_tb $end
$var reg 1 # rst_tb $end
$var reg 1 $ clk_tb $end
$var reg 4 % q_tb[3:0] $end
$scope module dut $end
$var reg 4 & d_i[3:0] $end
$var reg 1 ' ena_i $end
$var reg 1 ( rst_i $end
$var reg 1 ) clk_i $end
$var reg 4 * q_o[3:0] $end
$scope module reg_nbit_i(0) $end
$scope module ffd_inst $end
$var reg 1 + d_i $end
$var reg 1 , ena_i $end
$var reg 1 - rst_i $end
$var reg 1 . clk_i $end
$var reg 1 / q_o $end
$upscope $end
$upscope $end
$scope module reg_nbit_i(1) $end
$scope module ffd_inst $end
$var reg 1 0 d_i $end
$var reg 1 1 ena_i $end
$var reg 1 2 rst_i $end
$var reg 1 3 clk_i $end
$var reg 1 4 q_o $end
$upscope $end
$upscope $end
$scope module reg_nbit_i(2) $end
$scope module ffd_inst $end
$var reg 1 5 d_i $end
$var reg 1 6 ena_i $end
$var reg 1 7 rst_i $end
$var reg 1 8 clk_i $end
$var reg 1 9 q_o $end
$upscope $end
$upscope $end
$scope module reg_nbit_i(3) $end
$scope module ffd_inst $end
$var reg 1 : d_i $end
$var reg 1 ; ena_i $end
$var reg 1 < rst_i $end
$var reg 1 = clk_i $end
$var reg 1 > q_o $end
$upscope $end
$upscope $end
$upscope $end
$upscope $end
$enddefinitions $end
#0
b0001 !
0"
0#
0$
bUUUU %
b0001 &
0'
0(
0)
bUUUU *
1+
0,
0-
0.
U/
00
01
02
03
U4
05
06
07
08
U9
0:
0;
0<
0=
U>
#10000000
1$
1)
1.
13
18
1=
#20000000
0$
0)
0.
03
08
0=
#30000000
1$
1)
1.
13
18
1=
#40000000
0$
0)
0.
03
08
0=
#50000000
1$
1)
1.
13
18
1=
#60000000
0$
0)
0.
03
08
0=
#70000000
1$
1)
1.
13
18
1=
#80000000
0$
0)
0.
03
08
0=
#90000000
1$
1)
1.
13
18
1=
#100000000
b1110 !
0$
b1110 &
0)
0+
0.
10
03
15
08
1:
0=
#110000000
1$
1)
1.
13
18
1=
#120000000
0$
0)
0.
03
08
0=
#130000000
1$
1)
1.
13
18
1=
#140000000
0$
0)
0.
03
08
0=
#150000000
1$
1)
1.
13
18
1=
#160000000
0$
0)
0.
03
08
0=
#170000000
1$
1)
1.
13
18
1=
#180000000
0$
0)
0.
03
08
0=
#190000000
1$
1)
1.
13
18
1=
#200000000
b0001 !
1"
0$
b0001 &
1'
0)
1+
1,
0.
00
11
03
05
16
08
0:
1;
0=
#210000000
1$
b0001 %
1)
b0001 *
1.
1/
13
04
18
09
1=
0>
#220000000
0$
0)
0.
03
08
0=
#230000000
1$
1)
1.
13
18
1=
#240000000
0$
0)
0.
03
08
0=
#250000000
1$
1)
1.
13
18
1=
#260000000
0$
0)
0.
03
08
0=
#270000000
1$
1)
1.
13
18
1=
#280000000
0$
0)
0.
03
08
0=
#290000000
1$
1)
1.
13
18
1=
#300000000
b1110 !
0$
b1110 &
0)
0+
0.
10
03
15
08
1:
0=
#310000000
1$
b1110 %
1)
b1110 *
1.
0/
13
14
18
19
1=
1>
#320000000
0$
0)
0.
03
08
0=
#330000000
1$
1)
1.
13
18
1=
#340000000
0$
0)
0.
03
08
0=
#350000000
1$
1)
1.
13
18
1=
#360000000
0$
0)
0.
03
08
0=
#370000000
1$
1)
1.
13
18
1=
#380000000
0$
0)
0.
03
08
0=
#390000000
1$
1)
1.
13
18
1=
#400000000
b0001 !
0"
0$
b0001 &
0'
0)
1+
0,
0.
00
01
03
05
06
08
0:
0;
0=
#410000000
1$
1)
1.
13
18
1=
#420000000
0$
0)
0.
03
08
0=
#430000000
1$
1)
1.
13
18
1=
#440000000
0$
0)
0.
03
08
0=
#450000000
1$
1)
1.
13
18
1=
#460000000
0$
0)
0.
03
08
0=
#470000000
1$
1)
1.
13
18
1=
#480000000
0$
0)
0.
03
08
0=
#490000000
1$
1)
1.
13
18
1=
#500000000
b1110 !
0$
b1110 &
0)
0+
0.
10
03
15
08
1:
0=
#510000000
1$
1)
1.
13
18
1=
#520000000
0$
0)
0.
03
08
0=
#530000000
1$
1)
1.
13
18
1=
#540000000
0$
0)
0.
03
08
0=
#550000000
1$
1)
1.
13
18
1=
#560000000
0$
0)
0.
03
08
0=
#570000000
1$
1)
1.
13
18
1=
#580000000
0$
0)
0.
03
08
0=
#590000000
1$
1)
1.
13
18
1=
#600000000
b0001 !
1"
0$
b0001 &
1'
0)
1+
1,
0.
00
11
03
05
16
08
0:
1;
0=
#610000000
1$
b0001 %
1)
b0001 *
1.
1/
13
04
18
09
1=
0>
#620000000
0$
0)
0.
03
08
0=
#630000000
1$
1)
1.
13
18
1=
#640000000
0$
0)
0.
03
08
0=
#650000000
1$
1)
1.
13
18
1=
#660000000
0$
0)
0.
03
08
0=
#670000000
1$
1)
1.
13
18
1=
#680000000
0$
0)
0.
03
08
0=
#690000000
1$
1)
1.
13
18
1=
#700000000
b1110 !
0$
b1110 &
0)
0+
0.
10
03
15
08
1:
0=
#710000000
1$
b1110 %
1)
b1110 *
1.
0/
13
14
18
19
1=
1>
#720000000
0$
0)
0.
03
08
0=
#730000000
1$
1)
1.
13
18
1=
#740000000
0$
0)
0.
03
08
0=
#750000000
1$
1)
1.
13
18
1=
#760000000
0$
0)
0.
03
08
0=
#770000000
1$
1)
1.
13
18
1=
#780000000
0$
0)
0.
03
08
0=
#790000000
1$
1)
1.
13
18
1=
#800000000
b0001 !
0"
1#
0$
b0001 &
0'
1(
0)
1+
0,
1-
0.
00
01
12
03
05
06
17
08
0:
0;
1<
0=
#810000000
1$
b0000 %
1)
b0000 *
1.
13
04
18
09
1=
0>
#820000000
0$
0)
0.
03
08
0=
#830000000
1$
1)
1.
13
18
1=
#840000000
0$
0)
0.
03
08
0=
#850000000
1$
1)
1.
13
18
1=
#860000000
0$
0)
0.
03
08
0=
#870000000
1$
1)
1.
13
18
1=
#880000000
0$
0)
0.
03
08
0=
#890000000
1$
1)
1.
13
18
1=
#900000000
b1110 !
0$
b1110 &
0)
0+
0.
10
03
15
08
1:
0=
#910000000
1$
1)
1.
13
18
1=
#920000000
0$
0)
0.
03
08
0=
#930000000
1$
1)
1.
13
18
1=
#940000000
0$
0)
0.
03
08
0=
#950000000
1$
1)
1.
13
18
1=
#960000000
0$
0)
0.
03
08
0=
#970000000
1$
1)
1.
13
18
1=
#980000000
0$
0)
0.
03
08
0=
#990000000
1$
1)
1.
13
18
1=
#1000000000
b0001 !
1"
0$
b0001 &
1'
0)
1+
1,
0.
00
11
03
05
16
08
0:
1;
0=
