Exercises/07.1) shift_reg_Nbit/sources/shift_reg_Nbit.vhd
-- Author: Francesco Cavina <francescocavina98@gmail.com>
-- Brief:  This is the HW description for a 4 bit shift register

library IEEE;
use IEEE.std_logic_1164.all;
use IEEE.numeric_std.all;

entity shift_reg_Nbit is
    generic(
        N: natural := 4
    );
    port(
        input_i:  in  std_logic;
        ena_i:    in  std_logic;
        rst_i:    in  std_logic;
        clk_i:    in  std_logic;
        output_o: out std_logic
    );
end entity shift_reg_Nbit;

architecture shift_reg_Nbit_arch of shift_reg_Nbit is
    -- Declaration
    signal d: std_logic_vector(0 to N-1);

begin
    -- Description
    process(clk_i, rst_i)
    begin
        if rst_i = '1' then
            d <= (others => '0');
        elsif rising_edge(clk_i) then
            if ena_i = '1' then
                output_o <= d(N-1);
                d(1 to N-1) <= d(0 to N-2);
                d(0) <= input_i;
            end if;    
        end if;
    end process;
end architecture shift_reg_Nbit_arch;

Exercises/07.1) shift_reg_Nbit/sources/shift_reg_Nbit_tb.vhd
-- Author: Francesco Cavina <francescocavina98@gmail.com>
-- Brief:  This is the testbench of a 4 bit shift register

library IEEE;
use IEEE.std_logic_1164.all;

entity shift_reg_Nbit_tb is
end entity shift_reg_Nbit_tb;

architecture shift_reg_Nbit_tb_arch of shift_reg_Nbit_tb is
    -- Declaration
    component shift_reg_Nbit is
        generic(
            N: natural := 4
        );
        port(
            input_i:  in  std_logic;
            ena_i:    in  std_logic;
            rst_i:    in  std_logic;
            clk_i:    in  std_logic;
            output_o: out std_logic
        );
    end component shift_reg_Nbit;

    constant N_tb:      natural := 8;
    signal   input_tb:  std_logic := '0';
    signal   ena_tb:    std_logic := '1';
    signal   rst_tb:    std_logic := '0';
    signal   clk_tb:    std_logic := '0';
    signal   output_tb: std_logic;

begin
    -- Description
    clk_tb   <= not(clk_tb) after 50 ns;
    input_tb <= '1' after 250 ns, '0' after 450 ns, '1' after 650 ns, '0' after 850 ns;

    DUT: shift_reg_Nbit
        generic map(
            N => N_tb
        ) 
        port map(
            input_i  => input_tb,
            ena_i    => ena_tb,
            rst_i    => rst_tb,
            clk_i    => clk_tb,
            output_o => output_tb
        );
end architecture shift_reg_Nbit_tb_arch;

Exercises/07.1) shift_reg_Nbit/simulation/shift_reg_Nbit_tb.vcd
$date
  Wed Sep 20 01:43:36 2023
$end
$version
  GHDL v0
$end
$timescale
  1 fs
$end
$scope module standard $end
$upscope $end
$scope module std_logic_1164 $end
$upscope $end
$scope module numeric_std $end
$upscope $end
$scope module shift_reg_nbit_tb $end
$var reg 1 ! input_tb $end
$var reg 1 " ena_tb $end
$var reg 1 # rst_tb $end
$var reg 1 $ clk_tb $end
$var reg 1 % output_tb $end
$scope module dut $end
$var reg 1 & input_i $end
$var reg 1 ' ena_i $end
$var reg 1 ( rst_i $end
$var reg 1 ) clk_i $end
$var reg 1 * output_o $end
$var reg 8 + d[0:7] $end
$upscope $end
$upscope $end
$enddefinitions $end
#0
0!
1"
0#
0$
U%
0&
1'
0(
0)
U*
bUUUUUUUU +
#50000000
1$
1)
b0UUUUUUU +
#100000000
0$
0)
#150000000
1$
1)
b00UUUUUU +
#200000000
0$
0)
#250000000
1!
1$
1&
1)
b100UUUUU +
#300000000
0$
0)
#350000000
1$
1)
b1100UUUU +
#400000000
0$
0)
#450000000
0!
1$
0&
1)
b01100UUU +
#500000000
0$
0)
#550000000
1$
1)
b001100UU +
#600000000
0$
0)
#650000000
1!
1$
1&
1)
b1001100U +
#700000000
0$
0)
#750000000
1$
1)
b11001100 +
#800000000
0$
0)
#850000000
0!
1$
0%
0&
1)
0*
b01100110 +
#900000000
0$
0)
#950000000
1$
1)
b00110011 +
#1000000000
0$
0)
#1050000000
1$
1%
1)
1*
b00011001 +
#1100000000
0$
0)
#1150000000
1$
1)
b00001100 +
#1200000000
0$
0)
#1250000000
1$
0%
1)
0*
b00000110 +
#1300000000
0$
0)
#1350000000
1$
1)
b00000011 +
#1400000000
0$
0)
#1450000000
1$
1%
1)
1*
b00000001 +
#1500000000
0$
0)
#1550000000
1$
1)
b00000000 +
#1600000000
0$
0)
#1650000000
1$
0%
1)
0*
