Exercises/14.0) count_BCD/sources/ffd.vhd
-- Author: Francesco Cavina <francescocavina98@gmail.com>
-- Brief:  This is the HW description for a flip-flop D

library IEEE;
use IEEE.std_logic_1164.all;

entity ffd is
    port(
        d_i:   in  std_logic;
        ena_i: in  std_logic;
        rst_i: in  std_logic;
        clk_i: in  std_logic;
        q_o:   out std_logic
    );
end entity ffd;

architecture ffd_arch of ffd is
    -- Declaration

begin
    -- Description
    process(clk_i) is
    begin
        if rising_edge(clk_i) then
            if rst_i = '1' then
                q_o <= '0';
            elsif ena_i = '1' then
                q_o <= d_i;
            end if;         
        end if;      
    end process;    
end architecture ffd_arch;

Exercises/05.2) reg_Nbit/sources/reg_Nbit.vhd
-- Author: Francesco Cavina <francescocavina98@gmail.com>
-- Brief:  This is the HW description for a N bit register

library IEEE;
use IEEE.std_logic_1164.all;

entity reg_Nbit is
    generic(
        N: natural := 4
    );
    port(
        d_i:   in  std_logic_vector(N-1 downto 0);
        ena_i: in  std_logic;
        rst_i: in  std_logic;
        clk_i: in  std_logic;
        q_o:   out std_logic_vector(N-1 downto 0)
    );
end entity reg_Nbit;

architecture reg_Nbit_arch of reg_Nbit is
    -- Declaration
    component ffd is
        port(
            d_i:   in  std_logic;
            ena_i: in  std_logic;
            rst_i: in  std_logic;
            clk_i: in  std_logic;
            q_o:   out std_logic
        );
    end component ffd;

begin
    -- Description
    reg_Nbit_i: for i in N-1 downto 0 generate
        ffd_inst: ffd
            port map(
                d_i => d_i(i),
                ena_i => ena_i,
                rst_i => rst_i,
                clk_i => clk_i,
                q_o   => q_o(i)
            );
    end generate;
end architecture reg_Nbit_arch;

Exercises/10.0) count_4bit/sources/count_4bit.vhd
-- Author: Francesco Cavina <francescocavina98@gmail.com>
-- Brief:  This is the HW description for a 4 bit binary counter

library IEEE;
use IEEE.std_logic_1164.all;
use IEEE.numeric_std.all;

entity count_4bit is
    port(
        clk_i: in  std_logic;
        rst_i: in  std_logic;
        ena_i: in  std_logic;
        q_o:   out std_logic_vector(3 downto 0);
        max_o: out std_logic
    );
end entity count_4bit;

architecture count_4bit_arch of count_4bit is
    -- Declaration
    signal orOutput:   std_logic;
    signal andOutput:  std_logic;
    signal sumOutput:  std_logic_vector(3 downto 0);
    signal qOutput:    std_logic_vector(3 downto 0);
    signal compOutput: std_logic;

begin
    -- Description
    reg_Nbit_ins: entity work.reg_Nbit
        generic map(
            N => 4
        )
        port map(
            clk_i => clk_i,
            rst_i => orOutput,
            ena_i => ena_i,
            d_i   => sumOutput,
            q_o   => qOutput
        );

    sumOutput  <= std_logic_vector(unsigned(qOutput) + 1);    
    compOutput <= '1' when qOutput = std_logic_vector(to_unsigned(15, 4)) else '0';
    orOutput   <= rst_i or andOutput;
    andOutput  <= ena_i and compOutput;
    max_o   <= compOutput;
    q_o     <= qOutput;
end architecture count_4bit_arch;

Exercises/10.0) count_4bit/sources/count_4bit_tb.vhd
-- Author: Francesco Cavina <francescocavina98@gmail.com>
-- Brief:  This is the testbench of a 4 bit binary counter

library IEEE;
use IEEE.std_logic_1164.all;

entity count_4bit_tb is
end entity count_4bit_tb;

architecture count_4bit_tb_arch of count_4bit_tb is
    -- Declaration
    component count_4bit is
         port(
            clk_i: in  std_logic;
            rst_i: in  std_logic;
            ena_i: in  std_logic;
            q_o:   out std_logic_vector(3 downto 0);
            max_o: out std_logic
        );
    end component count_4bit;

    signal   clk_tb:  std_logic := '0';
    signal   rst_tb:  std_logic := '1';
    signal   ena_tb:  std_logic := '1';
    signal   q_tb:    std_logic_vector(3 downto 0);
    signal   max_tb:  std_logic;

begin
    -- Description

    clk_tb <= not clk_tb after 10 ns;
    rst_tb <= '0' after  10 ns, '1' after 800 ns, '0' after 900 ns;
    --ena_tb <= '0' after 500 ns, '1' after 700 ns;

    DUT: count_4bit
         port map(
            clk_i => clk_tb,
            rst_i => rst_tb,
            ena_i => ena_tb,
            q_o   => q_tb,
            max_o => max_tb
        );
end architecture count_4bit_tb_arch;

Exercises/10.0) count_4bit/simulation/count_4bit_tb.vcd
$date
  Wed Sep 20 00:11:15 2023
$end
$version
  GHDL v0
$end
$timescale
  1 fs
$end
$scope module standard $end
$upscope $end
$scope module std_logic_1164 $end
$upscope $end
$scope module numeric_std $end
$upscope $end
$scope module count_4bit_tb $end
$var reg 1 ! clk_tb $end
$var reg 1 " rst_tb $end
$var reg 1 # ena_tb $end
$var reg 4 $ q_tb[3:0] $end
$var reg 1 % max_tb $end
$scope module dut $end
$var reg 1 & clk_i $end
$var reg 1 ' rst_i $end
$var reg 1 ( ena_i $end
$var reg 4 ) q_o[3:0] $end
$var reg 1 * max_o $end
$var reg 1 + oroutput $end
$var reg 1 , andoutput $end
$var reg 4 - sumoutput[3:0] $end
$var reg 4 . qoutput[3:0] $end
$var reg 1 / compoutput $end
$scope module reg_nbit_ins $end
$var reg 4 0 d_i[3:0] $end
$var reg 1 1 ena_i $end
$var reg 1 2 rst_i $end
$var reg 1 3 clk_i $end
$var reg 4 4 q_o[3:0] $end
$scope module reg_nbit_i(0) $end
$scope module ffd_inst $end
$var reg 1 5 d_i $end
$var reg 1 6 ena_i $end
$var reg 1 7 rst_i $end
$var reg 1 8 clk_i $end
$var reg 1 9 q_o $end
$upscope $end
$upscope $end
$scope module reg_nbit_i(1) $end
$scope module ffd_inst $end
$var reg 1 : d_i $end
$var reg 1 ; ena_i $end
$var reg 1 < rst_i $end
$var reg 1 = clk_i $end
$var reg 1 > q_o $end
$upscope $end
$upscope $end
$scope module reg_nbit_i(2) $end
$scope module ffd_inst $end
$var reg 1 ? d_i $end
$var reg 1 @ ena_i $end
$var reg 1 A rst_i $end
$var reg 1 B clk_i $end
$var reg 1 C q_o $end
$upscope $end
$upscope $end
$scope module reg_nbit_i(3) $end
$scope module ffd_inst $end
$var reg 1 D d_i $end
$var reg 1 E ena_i $end
$var reg 1 F rst_i $end
$var reg 1 G clk_i $end
$var reg 1 H q_o $end
$upscope $end
$upscope $end
$upscope $end
$upscope $end
$upscope $end
$enddefinitions $end
#0
0!
1"
1#
bUUUU $
0%
0&
1'
1(
bUUUU )
0*
1+
0,
bXXXX -
bUUUU .
0/
bXXXX 0
11
12
03
bUUUU 4
X5
16
17
08
U9
X:
1;
1<
0=
U>
X?
1@
1A
0B
UC
XD
1E
1F
0G
UH
#10000000
1!
0"
b0000 $
1&
0'
b0000 )
0+
b0001 -
b0000 .
b0001 0
02
13
b0000 4
15
07
18
09
0:
0<
1=
0>
0?
0A
1B
0C
0D
0F
1G
0H
#20000000
0!
0&
03
08
0=
0B
0G
#30000000
1!
b0001 $
1&
b0001 )
b0010 -
b0001 .
b0010 0
13
b0001 4
05
18
19
1:
1=
1B
1G
#40000000
0!
0&
03
08
0=
0B
0G
#50000000
1!
b0010 $
1&
b0010 )
b0011 -
b0010 .
b0011 0
13
b0010 4
15
18
09
1=
1>
1B
1G
#60000000
0!
0&
03
08
0=
0B
0G
#70000000
1!
b0011 $
1&
b0011 )
b0100 -
b0011 .
b0100 0
13
b0011 4
05
18
19
0:
1=
1?
1B
1G
#80000000
0!
0&
03
08
0=
0B
0G
#90000000
1!
b0100 $
1&
b0100 )
b0101 -
b0100 .
b0101 0
13
b0100 4
15
18
09
1=
0>
1B
1C
1G
#100000000
0!
0&
03
08
0=
0B
0G
#110000000
1!
b0101 $
1&
b0101 )
b0110 -
b0101 .
b0110 0
13
b0101 4
05
18
19
1:
1=
1B
1G
#120000000
0!
0&
03
08
0=
0B
0G
#130000000
1!
b0110 $
1&
b0110 )
b0111 -
b0110 .
b0111 0
13
b0110 4
15
18
09
1=
1>
1B
1G
#140000000
0!
0&
03
08
0=
0B
0G
#150000000
1!
b0111 $
1&
b0111 )
b1000 -
b0111 .
b1000 0
13
b0111 4
05
18
19
0:
1=
0?
1B
1D
1G
#160000000
0!
0&
03
08
0=
0B
0G
#170000000
1!
b1000 $
1&
b1000 )
b1001 -
b1000 .
b1001 0
13
b1000 4
15
18
09
1=
0>
1B
0C
1G
1H
#180000000
0!
0&
03
08
0=
0B
0G
#190000000
1!
b1001 $
1&
b1001 )
b1010 -
b1001 .
b1010 0
13
b1001 4
05
18
19
1:
1=
1B
1G
#200000000
0!
0&
03
08
0=
0B
0G
#210000000
1!
b1010 $
1&
b1010 )
b1011 -
b1010 .
b1011 0
13
b1010 4
15
18
09
1=
1>
1B
1G
#220000000
0!
0&
03
08
0=
0B
0G
#230000000
1!
b1011 $
1&
b1011 )
b1100 -
b1011 .
b1100 0
13
b1011 4
05
18
19
0:
1=
1?
1B
1G
#240000000
0!
0&
03
08
0=
0B
0G
#250000000
1!
b1100 $
1&
b1100 )
b1101 -
b1100 .
b1101 0
13
b1100 4
15
18
09
1=
0>
1B
1C
1G
#260000000
0!
0&
03
08
0=
0B
0G
#270000000
1!
b1101 $
1&
b1101 )
b1110 -
b1101 .
b1110 0
13
b1101 4
05
18
19
1:
1=
1B
1G
#280000000
0!
0&
03
08
0=
0B
0G
#290000000
1!
b1110 $
1&
b1110 )
b1111 -
b1110 .
b1111 0
13
b1110 4
15
18
09
1=
1>
1B
1G
#300000000
0!
0&
03
08
0=
0B
0G
#310000000
1!
b1111 $
1%
1&
b1111 )
1*
1+
1,
b0000 -
b1111 .
1/
b0000 0
12
13
b1111 4
05
17
18
19
0:
1<
1=
0?
1A
1B
0D
1F
1G
#320000000
0!
0&
03
08
0=
0B
0G
#330000000
1!
b0000 $
0%
1&
b0000 )
0*
0+
0,
b0001 -
b0000 .
0/
b0001 0
02
13
b0000 4
15
07
18
09
0<
1=
0>
0A
1B
0C
0F
1G
0H
#340000000
0!
0&
03
08
0=
0B
0G
#350000000
1!
b0001 $
1&
b0001 )
b0010 -
b0001 .
b0010 0
13
b0001 4
05
18
19
1:
1=
1B
1G
#360000000
0!
0&
03
08
0=
0B
0G
#370000000
1!
b0010 $
1&
b0010 )
b0011 -
b0010 .
b0011 0
13
b0010 4
15
18
09
1=
1>
1B
1G
#380000000
0!
0&
03
08
0=
0B
0G
#390000000
1!
b0011 $
1&
b0011 )
b0100 -
b0011 .
b0100 0
13
b0011 4
05
18
19
0:
1=
1?
1B
1G
#400000000
0!
0&
03
08
0=
0B
0G
#410000000
1!
b0100 $
1&
b0100 )
b0101 -
b0100 .
b0101 0
13
b0100 4
15
18
09
1=
0>
1B
1C
1G
#420000000
0!
0&
03
08
0=
0B
0G
#430000000
1!
b0101 $
1&
b0101 )
b0110 -
b0101 .
b0110 0
13
b0101 4
05
18
19
1:
1=
1B
1G
#440000000
0!
0&
03
08
0=
0B
0G
#450000000
1!
b0110 $
1&
b0110 )
b0111 -
b0110 .
b0111 0
13
b0110 4
15
18
09
1=
1>
1B
1G
#460000000
0!
0&
03
08
0=
0B
0G
#470000000
1!
b0111 $
1&
b0111 )
b1000 -
b0111 .
b1000 0
13
b0111 4
05
18
19
0:
1=
0?
1B
1D
1G
#480000000
0!
0&
03
08
0=
0B
0G
#490000000
1!
b1000 $
1&
b1000 )
b1001 -
b1000 .
b1001 0
13
b1000 4
15
18
09
1=
0>
1B
0C
1G
1H
#500000000
0!
0&
03
08
0=
0B
0G
#510000000
1!
b1001 $
1&
b1001 )
b1010 -
b1001 .
b1010 0
13
b1001 4
05
18
19
1:
1=
1B
1G
#520000000
0!
0&
03
08
0=
0B
0G
#530000000
1!
b1010 $
1&
b1010 )
b1011 -
b1010 .
b1011 0
13
b1010 4
15
18
09
1=
1>
1B
1G
#540000000
0!
0&
03
08
0=
0B
0G
#550000000
1!
b1011 $
1&
b1011 )
b1100 -
b1011 .
b1100 0
13
b1011 4
05
18
19
0:
1=
1?
1B
1G
#560000000
0!
0&
03
08
0=
0B
0G
#570000000
1!
b1100 $
1&
b1100 )
b1101 -
b1100 .
b1101 0
13
b1100 4
15
18
09
1=
0>
1B
1C
1G
#580000000
0!
0&
03
08
0=
0B
0G
#590000000
1!
b1101 $
1&
b1101 )
b1110 -
b1101 .
b1110 0
13
b1101 4
05
18
19
1:
1=
1B
1G
#600000000
0!
0&
03
08
0=
0B
0G
#610000000
1!
b1110 $
1&
b1110 )
b1111 -
b1110 .
b1111 0
13
b1110 4
15
18
09
1=
1>
1B
1G
#620000000
0!
0&
03
08
0=
0B
0G
#630000000
1!
b1111 $
1%
1&
b1111 )
1*
1+
1,
b0000 -
b1111 .
1/
b0000 0
12
13
b1111 4
05
17
18
19
0:
1<
1=
0?
1A
1B
0D
1F
1G
#640000000
0!
0&
03
08
0=
0B
0G
#650000000
1!
b0000 $
0%
1&
b0000 )
0*
0+
0,
b0001 -
b0000 .
0/
b0001 0
02
13
b0000 4
15
07
18
09
0<
1=
0>
0A
1B
0C
0F
1G
0H
#660000000
0!
0&
03
08
0=
0B
0G
#670000000
1!
b0001 $
1&
b0001 )
b0010 -
b0001 .
b0010 0
13
b0001 4
05
18
19
1:
1=
1B
1G
#680000000
0!
0&
03
08
0=
0B
0G
#690000000
1!
b0010 $
1&
b0010 )
b0011 -
b0010 .
b0011 0
13
b0010 4
15
18
09
1=
1>
1B
1G
#700000000
0!
0&
03
08
0=
0B
0G
#710000000
1!
b0011 $
1&
b0011 )
b0100 -
b0011 .
b0100 0
13
b0011 4
05
18
19
0:
1=
1?
1B
1G
#720000000
0!
0&
03
08
0=
0B
0G
#730000000
1!
b0100 $
1&
b0100 )
b0101 -
b0100 .
b0101 0
13
b0100 4
15
18
09
1=
0>
1B
1C
1G
#740000000
0!
0&
03
08
0=
0B
0G
#750000000
1!
b0101 $
1&
b0101 )
b0110 -
b0101 .
b0110 0
13
b0101 4
05
18
19
1:
1=
1B
1G
#760000000
0!
0&
03
08
0=
0B
0G
#770000000
1!
b0110 $
1&
b0110 )
b0111 -
b0110 .
b0111 0
13
b0110 4
15
18
09
1=
1>
1B
1G
#780000000
0!
0&
03
08
0=
0B
0G
#790000000
1!
b0111 $
1&
b0111 )
b1000 -
b0111 .
b1000 0
13
b0111 4
05
18
19
0:
1=
0?
1B
1D
1G
#800000000
0!
1"
0&
1'
1+
12
03
17
08
1<
0=
1A
0B
1F
0G
#810000000
1!
b0000 $
1&
b0000 )
b0001 -
b0000 .
b0001 0
13
b0000 4
15
18
09
1=
0>
1B
0C
0D
1G
#820000000
0!
0&
03
08
0=
0B
0G
#830000000
1!
1&
13
18
1=
1B
1G
#840000000
0!
0&
03
08
0=
0B
0G
#850000000
1!
1&
13
18
1=
1B
1G
#860000000
0!
0&
03
08
0=
0B
0G
#870000000
1!
1&
13
18
1=
1B
1G
#880000000
0!
0&
03
08
0=
0B
0G
#890000000
1!
1&
13
18
1=
1B
1G
#900000000
0!
0"
0&
0'
0+
02
03
07
08
0<
0=
0A
0B
0F
0G
#910000000
1!
b0001 $
1&
b0001 )
b0010 -
b0001 .
b0010 0
13
b0001 4
05
18
19
1:
1=
1B
1G
#920000000
0!
0&
03
08
0=
0B
0G
#930000000
1!
b0010 $
1&
b0010 )
b0011 -
b0010 .
b0011 0
13
b0010 4
15
18
09
1=
1>
1B
1G
#940000000
0!
0&
03
08
0=
0B
0G
#950000000
1!
b0011 $
1&
b0011 )
b0100 -
b0011 .
b0100 0
13
b0011 4
05
18
19
0:
1=
1?
1B
1G
#960000000
0!
0&
03
08
0=
0B
0G
#970000000
1!
b0100 $
1&
b0100 )
b0101 -
b0100 .
b0101 0
13
b0100 4
15
18
09
1=
0>
1B
1C
1G
#980000000
0!
0&
03
08
0=
0B
0G
#990000000
1!
b0101 $
1&
b0101 )
b0110 -
b0101 .
b0110 0
13
b0101 4
05
18
19
1:
1=
1B
1G
