Exercises/13.0) count_Nbit/sources/count_Nbit.vhd
-- Author: Francesco Cavina <francescocavina98@gmail.com>
-- Brief:  This is the HW description for an N bit binary counter

library IEEE;
use IEEE.std_logic_1164.all;
use IEEE.numeric_std.all;

entity count_Nbit is
    generic(
        N: natural := 4
    );
    port(
        clk_i: in  std_logic;
        rst_i: in  std_logic;
        ena_i: in  std_logic;
        q_o:   out std_logic_vector(N-1 downto 0);
        max_o: out std_logic
    );
end entity count_Nbit;

architecture count_Nbit_arch of count_Nbit is
    -- Declaration
    signal orOutput:   std_logic;
    signal andOutput:  std_logic;
    signal sumOutput:  std_logic_vector(N-1 downto 0);
    signal qOutput:    std_logic_vector(N-1 downto 0);
    signal compOutput: std_logic;

begin
    -- Description
    process(clk_i) is
    begin
        if rising_edge(clk_i) then
            if orOutput = '1' then
                qOutput <= (others => '0');
            elsif ena_i = '1' then
                qOutput <= sumOutput;
            end if;         
        end if;      
    end process;    

    sumOutput  <= std_logic_vector(unsigned(qOutput) + 1);
    compOutput <= '1' when qOutput = std_logic_vector(to_unsigned((2**N)-1, N)) else '0';
    orOutput   <= rst_i or andOutput;
    andOutput  <= ena_i and compOutput;
    max_o   <= compOutput;
    q_o     <= qOutput;
end architecture count_Nbit_arch;

Exercises/13.0) count_Nbit/sources/count_Nbit_tb.vhd
-- Author: Francesco Cavina <francescocavina98@gmail.com>
-- Brief:  This is the testbench of an N bit binary counter

library IEEE;
use IEEE.std_logic_1164.all;

entity count_Nbit_tb is
end entity count_Nbit_tb;

architecture count_Nbit_tb_arch of count_Nbit_tb is
    -- Declaration
    component count_Nbit is
        generic(
            N: natural := 4
        );
        port(
            clk_i: in  std_logic;
            rst_i: in  std_logic;
            ena_i: in  std_logic;
            q_o:   out std_logic_vector(N-1 downto 0);
            max_o: out std_logic
        );
    end component count_Nbit;

    constant N_tb:    natural   := 8;
    signal   clk_tb:  std_logic := '0';
    signal   rst_tb:  std_logic := '1';
    signal   ena_tb:  std_logic := '1';
    signal   q_tb:    std_logic_vector(N_tb-1 downto 0);
    signal   max_tb:  std_logic;

begin
    -- Description
    clk_tb <= not clk_tb after 10 ns;
    rst_tb <= '0' after    10 ns;
    ena_tb <= '0' after 10300 ns;

    DUT: count_Nbit
        generic map(
            N => N_tb
        )
        port map(
            clk_i => clk_tb,
            rst_i => rst_tb,
            ena_i => ena_tb,
            q_o   => q_tb,
            max_o => max_tb
        );
end architecture count_Nbit_tb_arch;

Exercises/13.0) count_Nbit/simulation/count_Nbit_tb.vcd
$date
  Mon Oct  2 19:27:02 2023
$end
$version
  GHDL v0
$end
$timescale
  1 fs
$end
$scope module standard $end
$upscope $end
$scope module std_logic_1164 $end
$upscope $end
$scope module numeric_std $end
$upscope $end
$scope module count_nbit_tb $end
$var reg 1 ! clk_tb $end
$var reg 1 " rst_tb $end
$var reg 1 # ena_tb $end
$var reg 8 $ q_tb[7:0] $end
$var reg 1 % max_tb $end
$scope module dut $end
$var reg 1 & clk_i $end
$var reg 1 ' rst_i $end
$var reg 1 ( ena_i $end
$var reg 8 ) q_o[7:0] $end
$var reg 1 * max_o $end
$var reg 1 + oroutput $end
$var reg 1 , andoutput $end
$var reg 8 - sumoutput[7:0] $end
$var reg 8 . qoutput[7:0] $end
$var reg 1 / compoutput $end
$upscope $end
$upscope $end
$enddefinitions $end
#0
0!
1"
1#
bUUUUUUUU $
0%
0&
1'
1(
bUUUUUUUU )
0*
1+
0,
bXXXXXXXX -
bUUUUUUUU .
0/
#10000000
1!
0"
b00000000 $
1&
0'
b00000000 )
0+
b00000001 -
b00000000 .
#20000000
0!
0&
#30000000
1!
b00000001 $
1&
b00000001 )
b00000010 -
b00000001 .
#40000000
0!
0&
#50000000
1!
b00000010 $
1&
b00000010 )
b00000011 -
b00000010 .
#60000000
0!
0&
#70000000
1!
b00000011 $
1&
b00000011 )
b00000100 -
b00000011 .
#80000000
0!
0&
#90000000
1!
b00000100 $
1&
b00000100 )
b00000101 -
b00000100 .
#100000000
0!
0&
#110000000
1!
b00000101 $
1&
b00000101 )
b00000110 -
b00000101 .
#120000000
0!
0&
#130000000
1!
b00000110 $
1&
b00000110 )
b00000111 -
b00000110 .
#140000000
0!
0&
#150000000
1!
b00000111 $
1&
b00000111 )
b00001000 -
b00000111 .
#160000000
0!
0&
#170000000
1!
b00001000 $
1&
b00001000 )
b00001001 -
b00001000 .
#180000000
0!
0&
#190000000
1!
b00001001 $
1&
b00001001 )
b00001010 -
b00001001 .
#200000000
0!
0&
#210000000
1!
b00001010 $
1&
b00001010 )
b00001011 -
b00001010 .
#220000000
0!
0&
#230000000
1!
b00001011 $
1&
b00001011 )
b00001100 -
b00001011 .
#240000000
0!
0&
#250000000
1!
b00001100 $
1&
b00001100 )
b00001101 -
b00001100 .
#260000000
0!
0&
#270000000
1!
b00001101 $
1&
b00001101 )
b00001110 -
b00001101 .
#280000000
0!
0&
#290000000
1!
b00001110 $
1&
b00001110 )
b00001111 -
b00001110 .
#300000000
0!
0&
#310000000
1!
b00001111 $
1&
b00001111 )
b00010000 -
b00001111 .
#320000000
0!
0&
#330000000
1!
b00010000 $
1&
b00010000 )
b00010001 -
b00010000 .
#340000000
0!
0&
#350000000
1!
b00010001 $
1&
b00010001 )
b00010010 -
b00010001 .
#360000000
0!
0&
#370000000
1!
b00010010 $
1&
b00010010 )
b00010011 -
b00010010 .
#380000000
0!
0&
#390000000
1!
b00010011 $
1&
b00010011 )
b00010100 -
b00010011 .
#400000000
0!
0&
#410000000
1!
b00010100 $
1&
b00010100 )
b00010101 -
b00010100 .
#420000000
0!
0&
#430000000
1!
b00010101 $
1&
b00010101 )
b00010110 -
b00010101 .
#440000000
0!
0&
#450000000
1!
b00010110 $
1&
b00010110 )
b00010111 -
b00010110 .
#460000000
0!
0&
#470000000
1!
b00010111 $
1&
b00010111 )
b00011000 -
b00010111 .
#480000000
0!
0&
#490000000
1!
b00011000 $
1&
b00011000 )
b00011001 -
b00011000 .
#500000000
0!
0&
#510000000
1!
b00011001 $
1&
b00011001 )
b00011010 -
b00011001 .
#520000000
0!
0&
#530000000
1!
b00011010 $
1&
b00011010 )
b00011011 -
b00011010 .
#540000000
0!
0&
#550000000
1!
b00011011 $
1&
b00011011 )
b00011100 -
b00011011 .
#560000000
0!
0&
#570000000
1!
b00011100 $
1&
b00011100 )
b00011101 -
b00011100 .
#580000000
0!
0&
#590000000
1!
b00011101 $
1&
b00011101 )
b00011110 -
b00011101 .
#600000000
0!
0&
#610000000
1!
b00011110 $
1&
b00011110 )
b00011111 -
b00011110 .
#620000000
0!
0&
#630000000
1!
b00011111 $
1&
b00011111 )
b00100000 -
b00011111 .
#640000000
0!
0&
#650000000
1!
b00100000 $
1&
b00100000 )
b00100001 -
b00100000 .
#660000000
0!
0&
#670000000
1!
b00100001 $
1&
b00100001 )
b00100010 -
b00100001 .
#680000000
0!
0&
#690000000
1!
b00100010 $
1&
b00100010 )
b00100011 -
b00100010 .
#700000000
0!
0&
#710000000
1!
b00100011 $
1&
b00100011 )
b00100100 -
b00100011 .
#720000000
0!
0&
#730000000
1!
b00100100 $
1&
b00100100 )
b00100101 -
b00100100 .
#740000000
0!
0&
#750000000
1!
b00100101 $
1&
b00100101 )
b00100110 -
b00100101 .
#760000000
0!
0&
#770000000
1!
b00100110 $
1&
b00100110 )
b00100111 -
b00100110 .
#780000000
0!
0&
#790000000
1!
b00100111 $
1&
b00100111 )
b00101000 -
b00100111 .
#800000000
0!
0&
#810000000
1!
b00101000 $
1&
b00101000 )
b00101001 -
b00101000 .
#820000000
0!
0&
#830000000
1!
b00101001 $
1&
b00101001 )
b00101010 -
b00101001 .
#840000000
0!
0&
#850000000
1!
b00101010 $
1&
b00101010 )
b00101011 -
b00101010 .
#860000000
0!
0&
#870000000
1!
b00101011 $
1&
b00101011 )
b00101100 -
b00101011 .
#880000000
0!
0&
#890000000
1!
b00101100 $
1&
b00101100 )
b00101101 -
b00101100 .
#900000000
0!
0&
#910000000
1!
b00101101 $
1&
b00101101 )
b00101110 -
b00101101 .
#920000000
0!
0&
#930000000
1!
b00101110 $
1&
b00101110 )
b00101111 -
b00101110 .
#940000000
0!
0&
#950000000
1!
b00101111 $
1&
b00101111 )
b00110000 -
b00101111 .
#960000000
0!
0&
#970000000
1!
b00110000 $
1&
b00110000 )
b00110001 -
b00110000 .
#980000000
0!
0&
#990000000
1!
b00110001 $
1&
b00110001 )
b00110010 -
b00110001 .
#1000000000
0!
0&
#1010000000
1!
b00110010 $
1&
b00110010 )
b00110011 -
b00110010 .
#1020000000
0!
0&
#1030000000
1!
b00110011 $
1&
b00110011 )
b00110100 -
b00110011 .
#1040000000
0!
0&
#1050000000
1!
b00110100 $
1&
b00110100 )
b00110101 -
b00110100 .
#1060000000
0!
0&
#1070000000
1!
b00110101 $
1&
b00110101 )
b00110110 -
b00110101 .
#1080000000
0!
0&
#1090000000
1!
b00110110 $
1&
b00110110 )
b00110111 -
b00110110 .
#1100000000
0!
0&
#1110000000
1!
b00110111 $
1&
b00110111 )
b00111000 -
b00110111 .
#1120000000
0!
0&
#1130000000
1!
b00111000 $
1&
b00111000 )
b00111001 -
b00111000 .
#1140000000
0!
0&
#1150000000
1!
b00111001 $
1&
b00111001 )
b00111010 -
b00111001 .
#1160000000
0!
0&
#1170000000
1!
b00111010 $
1&
b00111010 )
b00111011 -
b00111010 .
#1180000000
0!
0&
#1190000000
1!
b00111011 $
1&
b00111011 )
b00111100 -
b00111011 .
#1200000000
0!
0&
#1210000000
1!
b00111100 $
1&
b00111100 )
b00111101 -
b00111100 .
#1220000000
0!
0&
#1230000000
1!
b00111101 $
1&
b00111101 )
b00111110 -
b00111101 .
#1240000000
0!
0&
#1250000000
1!
b00111110 $
1&
b00111110 )
b00111111 -
b00111110 .
#1260000000
0!
0&
#1270000000
1!
b00111111 $
1&
b00111111 )
b01000000 -
b00111111 .
#1280000000
0!
0&
#1290000000
1!
b01000000 $
1&
b01000000 )
b01000001 -
b01000000 .
#1300000000
0!
0&
#1310000000
1!
b01000001 $
1&
b01000001 )
b01000010 -
b01000001 .
#1320000000
0!
0&
#1330000000
1!
b01000010 $
1&
b01000010 )
b01000011 -
b01000010 .
#1340000000
0!
0&
#1350000000
1!
b01000011 $
1&
b01000011 )
b01000100 -
b01000011 .
#1360000000
0!
0&
#1370000000
1!
b01000100 $
1&
b01000100 )
b01000101 -
b01000100 .
#1380000000
0!
0&
#1390000000
1!
b01000101 $
1&
b01000101 )
b01000110 -
b01000101 .
#1400000000
0!
0&
#1410000000
1!
b01000110 $
1&
b01000110 )
b01000111 -
b01000110 .
#1420000000
0!
0&
#1430000000
1!
b01000111 $
1&
b01000111 )
b01001000 -
b01000111 .
#1440000000
0!
0&
#1450000000
1!
b01001000 $
1&
b01001000 )
b01001001 -
b01001000 .
#1460000000
0!
0&
#1470000000
1!
b01001001 $
1&
b01001001 )
b01001010 -
b01001001 .
#1480000000
0!
0&
#1490000000
1!
b01001010 $
1&
b01001010 )
b01001011 -
b01001010 .
#1500000000
0!
0&
#1510000000
1!
b01001011 $
1&
b01001011 )
b01001100 -
b01001011 .
#1520000000
0!
0&
#1530000000
1!
b01001100 $
1&
b01001100 )
b01001101 -
b01001100 .
#1540000000
0!
0&
#1550000000
1!
b01001101 $
1&
b01001101 )
b01001110 -
b01001101 .
#1560000000
0!
0&
#1570000000
1!
b01001110 $
1&
b01001110 )
b01001111 -
b01001110 .
#1580000000
0!
0&
#1590000000
1!
b01001111 $
1&
b01001111 )
b01010000 -
b01001111 .
#1600000000
0!
0&
#1610000000
1!
b01010000 $
1&
b01010000 )
b01010001 -
b01010000 .
#1620000000
0!
0&
#1630000000
1!
b01010001 $
1&
b01010001 )
b01010010 -
b01010001 .
#1640000000
0!
0&
#1650000000
1!
b01010010 $
1&
b01010010 )
b01010011 -
b01010010 .
#1660000000
0!
0&
#1670000000
1!
b01010011 $
1&
b01010011 )
b01010100 -
b01010011 .
#1680000000
0!
0&
#1690000000
1!
b01010100 $
1&
b01010100 )
b01010101 -
b01010100 .
#1700000000
0!
0&
#1710000000
1!
b01010101 $
1&
b01010101 )
b01010110 -
b01010101 .
#1720000000
0!
0&
#1730000000
1!
b01010110 $
1&
b01010110 )
b01010111 -
b01010110 .
#1740000000
0!
0&
#1750000000
1!
b01010111 $
1&
b01010111 )
b01011000 -
b01010111 .
#1760000000
0!
0&
#1770000000
1!
b01011000 $
1&
b01011000 )
b01011001 -
b01011000 .
#1780000000
0!
0&
#1790000000
1!
b01011001 $
1&
b01011001 )
b01011010 -
b01011001 .
#1800000000
0!
0&
#1810000000
1!
b01011010 $
1&
b01011010 )
b01011011 -
b01011010 .
#1820000000
0!
0&
#1830000000
1!
b01011011 $
1&
b01011011 )
b01011100 -
b01011011 .
#1840000000
0!
0&
#1850000000
1!
b01011100 $
1&
b01011100 )
b01011101 -
b01011100 .
#1860000000
0!
0&
#1870000000
1!
b01011101 $
1&
b01011101 )
b01011110 -
b01011101 .
#1880000000
0!
0&
#1890000000
1!
b01011110 $
1&
b01011110 )
b01011111 -
b01011110 .
#1900000000
0!
0&
#1910000000
1!
b01011111 $
1&
b01011111 )
b01100000 -
b01011111 .
#1920000000
0!
0&
#1930000000
1!
b01100000 $
1&
b01100000 )
b01100001 -
b01100000 .
#1940000000
0!
0&
#1950000000
1!
b01100001 $
1&
b01100001 )
b01100010 -
b01100001 .
#1960000000
0!
0&
#1970000000
1!
b01100010 $
1&
b01100010 )
b01100011 -
b01100010 .
#1980000000
0!
0&
#1990000000
1!
b01100011 $
1&
b01100011 )
b01100100 -
b01100011 .
#2000000000
0!
0&
#2010000000
1!
b01100100 $
1&
b01100100 )
b01100101 -
b01100100 .
#2020000000
0!
0&
#2030000000
1!
b01100101 $
1&
b01100101 )
b01100110 -
b01100101 .
#2040000000
0!
0&
#2050000000
1!
b01100110 $
1&
b01100110 )
b01100111 -
b01100110 .
#2060000000
0!
0&
#2070000000
1!
b01100111 $
1&
b01100111 )
b01101000 -
b01100111 .
#2080000000
0!
0&
#2090000000
1!
b01101000 $
1&
b01101000 )
b01101001 -
b01101000 .
#2100000000
0!
0&
#2110000000
1!
b01101001 $
1&
b01101001 )
b01101010 -
b01101001 .
#2120000000
0!
0&
#2130000000
1!
b01101010 $
1&
b01101010 )
b01101011 -
b01101010 .
#2140000000
0!
0&
#2150000000
1!
b01101011 $
1&
b01101011 )
b01101100 -
b01101011 .
#2160000000
0!
0&
#2170000000
1!
b01101100 $
1&
b01101100 )
b01101101 -
b01101100 .
#2180000000
0!
0&
#2190000000
1!
b01101101 $
1&
b01101101 )
b01101110 -
b01101101 .
#2200000000
0!
0&
#2210000000
1!
b01101110 $
1&
b01101110 )
b01101111 -
b01101110 .
#2220000000
0!
0&
#2230000000
1!
b01101111 $
1&
b01101111 )
b01110000 -
b01101111 .
#2240000000
0!
0&
#2250000000
1!
b01110000 $
1&
b01110000 )
b01110001 -
b01110000 .
#2260000000
0!
0&
#2270000000
1!
b01110001 $
1&
b01110001 )
b01110010 -
b01110001 .
#2280000000
0!
0&
#2290000000
1!
b01110010 $
1&
b01110010 )
b01110011 -
b01110010 .
#2300000000
0!
0&
#2310000000
1!
b01110011 $
1&
b01110011 )
b01110100 -
b01110011 .
#2320000000
0!
0&
#2330000000
1!
b01110100 $
1&
b01110100 )
b01110101 -
b01110100 .
#2340000000
0!
0&
#2350000000
1!
b01110101 $
1&
b01110101 )
b01110110 -
b01110101 .
#2360000000
0!
0&
#2370000000
1!
b01110110 $
1&
b01110110 )
b01110111 -
b01110110 .
#2380000000
0!
0&
#2390000000
1!
b01110111 $
1&
b01110111 )
b01111000 -
b01110111 .
#2400000000
0!
0&
#2410000000
1!
b01111000 $
1&
b01111000 )
b01111001 -
b01111000 .
#2420000000
0!
0&
#2430000000
1!
b01111001 $
1&
b01111001 )
b01111010 -
b01111001 .
#2440000000
0!
0&
#2450000000
1!
b01111010 $
1&
b01111010 )
b01111011 -
b01111010 .
#2460000000
0!
0&
#2470000000
1!
b01111011 $
1&
b01111011 )
b01111100 -
b01111011 .
#2480000000
0!
0&
#2490000000
1!
b01111100 $
1&
b01111100 )
b01111101 -
b01111100 .
#2500000000
0!
0&
#2510000000
1!
b01111101 $
1&
b01111101 )
b01111110 -
b01111101 .
#2520000000
0!
0&
#2530000000
1!
b01111110 $
1&
b01111110 )
b01111111 -
b01111110 .
#2540000000
0!
0&
#2550000000
1!
b01111111 $
1&
b01111111 )
b10000000 -
b01111111 .
#2560000000
0!
0&
#2570000000
1!
b10000000 $
1&
b10000000 )
b10000001 -
b10000000 .
#2580000000
0!
0&
#2590000000
1!
b10000001 $
1&
b10000001 )
b10000010 -
b10000001 .
#2600000000
0!
0&
#2610000000
1!
b10000010 $
1&
b10000010 )
b10000011 -
b10000010 .
#2620000000
0!
0&
#2630000000
1!
b10000011 $
1&
b10000011 )
b10000100 -
b10000011 .
#2640000000
0!
0&
#2650000000
1!
b10000100 $
1&
b10000100 )
b10000101 -
b10000100 .
#2660000000
0!
0&
#2670000000
1!
b10000101 $
1&
b10000101 )
b10000110 -
b10000101 .
#2680000000
0!
0&
#2690000000
1!
b10000110 $
1&
b10000110 )
b10000111 -
b10000110 .
#2700000000
0!
0&
#2710000000
1!
b10000111 $
1&
b10000111 )
b10001000 -
b10000111 .
#2720000000
0!
0&
#2730000000
1!
b10001000 $
1&
b10001000 )
b10001001 -
b10001000 .
#2740000000
0!
0&
#2750000000
1!
b10001001 $
1&
b10001001 )
b10001010 -
b10001001 .
#2760000000
0!
0&
#2770000000
1!
b10001010 $
1&
b10001010 )
b10001011 -
b10001010 .
#2780000000
0!
0&
#2790000000
1!
b10001011 $
1&
b10001011 )
b10001100 -
b10001011 .
#2800000000
0!
0&
#2810000000
1!
b10001100 $
1&
b10001100 )
b10001101 -
b10001100 .
#2820000000
0!
0&
#2830000000
1!
b10001101 $
1&
b10001101 )
b10001110 -
b10001101 .
#2840000000
0!
0&
#2850000000
1!
b10001110 $
1&
b10001110 )
b10001111 -
b10001110 .
#2860000000
0!
0&
#2870000000
1!
b10001111 $
1&
b10001111 )
b10010000 -
b10001111 .
#2880000000
0!
0&
#2890000000
1!
b10010000 $
1&
b10010000 )
b10010001 -
b10010000 .
#2900000000
0!
0&
#2910000000
1!
b10010001 $
1&
b10010001 )
b10010010 -
b10010001 .
#2920000000
0!
0&
#2930000000
1!
b10010010 $
1&
b10010010 )
b10010011 -
b10010010 .
#2940000000
0!
0&
#2950000000
1!
b10010011 $
1&
b10010011 )
b10010100 -
b10010011 .
#2960000000
0!
0&
#2970000000
1!
b10010100 $
1&
b10010100 )
b10010101 -
b10010100 .
#2980000000
0!
0&
#2990000000
1!
b10010101 $
1&
b10010101 )
b10010110 -
b10010101 .
#3000000000
0!
0&
#3010000000
1!
b10010110 $
1&
b10010110 )
b10010111 -
b10010110 .
#3020000000
0!
0&
#3030000000
1!
b10010111 $
1&
b10010111 )
b10011000 -
b10010111 .
#3040000000
0!
0&
#3050000000
1!
b10011000 $
1&
b10011000 )
b10011001 -
b10011000 .
#3060000000
0!
0&
#3070000000
1!
b10011001 $
1&
b10011001 )
b10011010 -
b10011001 .
#3080000000
0!
0&
#3090000000
1!
b10011010 $
1&
b10011010 )
b10011011 -
b10011010 .
#3100000000
0!
0&
#3110000000
1!
b10011011 $
1&
b10011011 )
b10011100 -
b10011011 .
#3120000000
0!
0&
#3130000000
1!
b10011100 $
1&
b10011100 )
b10011101 -
b10011100 .
#3140000000
0!
0&
#3150000000
1!
b10011101 $
1&
b10011101 )
b10011110 -
b10011101 .
#3160000000
0!
0&
#3170000000
1!
b10011110 $
1&
b10011110 )
b10011111 -
b10011110 .
#3180000000
0!
0&
#3190000000
1!
b10011111 $
1&
b10011111 )
b10100000 -
b10011111 .
#3200000000
0!
0&
#3210000000
1!
b10100000 $
1&
b10100000 )
b10100001 -
b10100000 .
#3220000000
0!
0&
#3230000000
1!
b10100001 $
1&
b10100001 )
b10100010 -
b10100001 .
#3240000000
0!
0&
#3250000000
1!
b10100010 $
1&
b10100010 )
b10100011 -
b10100010 .
#3260000000
0!
0&
#3270000000
1!
b10100011 $
1&
b10100011 )
b10100100 -
b10100011 .
#3280000000
0!
0&
#3290000000
1!
b10100100 $
1&
b10100100 )
b10100101 -
b10100100 .
#3300000000
0!
0&
#3310000000
1!
b10100101 $
1&
b10100101 )
b10100110 -
b10100101 .
#3320000000
0!
0&
#3330000000
1!
b10100110 $
1&
b10100110 )
b10100111 -
b10100110 .
#3340000000
0!
0&
#3350000000
1!
b10100111 $
1&
b10100111 )
b10101000 -
b10100111 .
#3360000000
0!
0&
#3370000000
1!
b10101000 $
1&
b10101000 )
b10101001 -
b10101000 .
#3380000000
0!
0&
#3390000000
1!
b10101001 $
1&
b10101001 )
b10101010 -
b10101001 .
#3400000000
0!
0&
#3410000000
1!
b10101010 $
1&
b10101010 )
b10101011 -
b10101010 .
#3420000000
0!
0&
#3430000000
1!
b10101011 $
1&
b10101011 )
b10101100 -
b10101011 .
#3440000000
0!
0&
#3450000000
1!
b10101100 $
1&
b10101100 )
b10101101 -
b10101100 .
#3460000000
0!
0&
#3470000000
1!
b10101101 $
1&
b10101101 )
b10101110 -
b10101101 .
#3480000000
0!
0&
#3490000000
1!
b10101110 $
1&
b10101110 )
b10101111 -
b10101110 .
#3500000000
0!
0&
#3510000000
1!
b10101111 $
1&
b10101111 )
b10110000 -
b10101111 .
#3520000000
0!
0&
#3530000000
1!
b10110000 $
1&
b10110000 )
b10110001 -
b10110000 .
#3540000000
0!
0&
#3550000000
1!
b10110001 $
1&
b10110001 )
b10110010 -
b10110001 .
#3560000000
0!
0&
#3570000000
1!
b10110010 $
1&
b10110010 )
b10110011 -
b10110010 .
#3580000000
0!
0&
#3590000000
1!
b10110011 $
1&
b10110011 )
b10110100 -
b10110011 .
#3600000000
0!
0&
#3610000000
1!
b10110100 $
1&
b10110100 )
b10110101 -
b10110100 .
#3620000000
0!
0&
#3630000000
1!
b10110101 $
1&
b10110101 )
b10110110 -
b10110101 .
#3640000000
0!
0&
#3650000000
1!
b10110110 $
1&
b10110110 )
b10110111 -
b10110110 .
#3660000000
0!
0&
#3670000000
1!
b10110111 $
1&
b10110111 )
b10111000 -
b10110111 .
#3680000000
0!
0&
#3690000000
1!
b10111000 $
1&
b10111000 )
b10111001 -
b10111000 .
#3700000000
0!
0&
#3710000000
1!
b10111001 $
1&
b10111001 )
b10111010 -
b10111001 .
#3720000000
0!
0&
#3730000000
1!
b10111010 $
1&
b10111010 )
b10111011 -
b10111010 .
#3740000000
0!
0&
#3750000000
1!
b10111011 $
1&
b10111011 )
b10111100 -
b10111011 .
#3760000000
0!
0&
#3770000000
1!
b10111100 $
1&
b10111100 )
b10111101 -
b10111100 .
#3780000000
0!
0&
#3790000000
1!
b10111101 $
1&
b10111101 )
b10111110 -
b10111101 .
#3800000000
0!
0&
#3810000000
1!
b10111110 $
1&
b10111110 )
b10111111 -
b10111110 .
#3820000000
0!
0&
#3830000000
1!
b10111111 $
1&
b10111111 )
b11000000 -
b10111111 .
#3840000000
0!
0&
#3850000000
1!
b11000000 $
1&
b11000000 )
b11000001 -
b11000000 .
#3860000000
0!
0&
#3870000000
1!
b11000001 $
1&
b11000001 )
b11000010 -
b11000001 .
#3880000000
0!
0&
#3890000000
1!
b11000010 $
1&
b11000010 )
b11000011 -
b11000010 .
#3900000000
0!
0&
#3910000000
1!
b11000011 $
1&
b11000011 )
b11000100 -
b11000011 .
#3920000000
0!
0&
#3930000000
1!
b11000100 $
1&
b11000100 )
b11000101 -
b11000100 .
#3940000000
0!
0&
#3950000000
1!
b11000101 $
1&
b11000101 )
b11000110 -
b11000101 .
#3960000000
0!
0&
#3970000000
1!
b11000110 $
1&
b11000110 )
b11000111 -
b11000110 .
#3980000000
0!
0&
#3990000000
1!
b11000111 $
1&
b11000111 )
b11001000 -
b11000111 .
#4000000000
0!
0&
#4010000000
1!
b11001000 $
1&
b11001000 )
b11001001 -
b11001000 .
#4020000000
0!
0&
#4030000000
1!
b11001001 $
1&
b11001001 )
b11001010 -
b11001001 .
#4040000000
0!
0&
#4050000000
1!
b11001010 $
1&
b11001010 )
b11001011 -
b11001010 .
#4060000000
0!
0&
#4070000000
1!
b11001011 $
1&
b11001011 )
b11001100 -
b11001011 .
#4080000000
0!
0&
#4090000000
1!
b11001100 $
1&
b11001100 )
b11001101 -
b11001100 .
#4100000000
0!
0&
#4110000000
1!
b11001101 $
1&
b11001101 )
b11001110 -
b11001101 .
#4120000000
0!
0&
#4130000000
1!
b11001110 $
1&
b11001110 )
b11001111 -
b11001110 .
#4140000000
0!
0&
#4150000000
1!
b11001111 $
1&
b11001111 )
b11010000 -
b11001111 .
#4160000000
0!
0&
#4170000000
1!
b11010000 $
1&
b11010000 )
b11010001 -
b11010000 .
#4180000000
0!
0&
#4190000000
1!
b11010001 $
1&
b11010001 )
b11010010 -
b11010001 .
#4200000000
0!
0&
#4210000000
1!
b11010010 $
1&
b11010010 )
b11010011 -
b11010010 .
#4220000000
0!
0&
#4230000000
1!
b11010011 $
1&
b11010011 )
b11010100 -
b11010011 .
#4240000000
0!
0&
#4250000000
1!
b11010100 $
1&
b11010100 )
b11010101 -
b11010100 .
#4260000000
0!
0&
#4270000000
1!
b11010101 $
1&
b11010101 )
b11010110 -
b11010101 .
#4280000000
0!
0&
#4290000000
1!
b11010110 $
1&
b11010110 )
b11010111 -
b11010110 .
#4300000000
0!
0&
#4310000000
1!
b11010111 $
1&
b11010111 )
b11011000 -
b11010111 .
#4320000000
0!
0&
#4330000000
1!
b11011000 $
1&
b11011000 )
b11011001 -
b11011000 .
#4340000000
0!
0&
#4350000000
1!
b11011001 $
1&
b11011001 )
b11011010 -
b11011001 .
#4360000000
0!
0&
#4370000000
1!
b11011010 $
1&
b11011010 )
b11011011 -
b11011010 .
#4380000000
0!
0&
#4390000000
1!
b11011011 $
1&
b11011011 )
b11011100 -
b11011011 .
#4400000000
0!
0&
#4410000000
1!
b11011100 $
1&
b11011100 )
b11011101 -
b11011100 .
#4420000000
0!
0&
#4430000000
1!
b11011101 $
1&
b11011101 )
b11011110 -
b11011101 .
#4440000000
0!
0&
#4450000000
1!
b11011110 $
1&
b11011110 )
b11011111 -
b11011110 .
#4460000000
0!
0&
#4470000000
1!
b11011111 $
1&
b11011111 )
b11100000 -
b11011111 .
#4480000000
0!
0&
#4490000000
1!
b11100000 $
1&
b11100000 )
b11100001 -
b11100000 .
#4500000000
0!
0&
#4510000000
1!
b11100001 $
1&
b11100001 )
b11100010 -
b11100001 .
#4520000000
0!
0&
#4530000000
1!
b11100010 $
1&
b11100010 )
b11100011 -
b11100010 .
#4540000000
0!
0&
#4550000000
1!
b11100011 $
1&
b11100011 )
b11100100 -
b11100011 .
#4560000000
0!
0&
#4570000000
1!
b11100100 $
1&
b11100100 )
b11100101 -
b11100100 .
#4580000000
0!
0&
#4590000000
1!
b11100101 $
1&
b11100101 )
b11100110 -
b11100101 .
#4600000000
0!
0&
#4610000000
1!
b11100110 $
1&
b11100110 )
b11100111 -
b11100110 .
#4620000000
0!
0&
#4630000000
1!
b11100111 $
1&
b11100111 )
b11101000 -
b11100111 .
#4640000000
0!
0&
#4650000000
1!
b11101000 $
1&
b11101000 )
b11101001 -
b11101000 .
#4660000000
0!
0&
#4670000000
1!
b11101001 $
1&
b11101001 )
b11101010 -
b11101001 .
#4680000000
0!
0&
#4690000000
1!
b11101010 $
1&
b11101010 )
b11101011 -
b11101010 .
#4700000000
0!
0&
#4710000000
1!
b11101011 $
1&
b11101011 )
b11101100 -
b11101011 .
#4720000000
0!
0&
#4730000000
1!
b11101100 $
1&
b11101100 )
b11101101 -
b11101100 .
#4740000000
0!
0&
#4750000000
1!
b11101101 $
1&
b11101101 )
b11101110 -
b11101101 .
#4760000000
0!
0&
#4770000000
1!
b11101110 $
1&
b11101110 )
b11101111 -
b11101110 .
#4780000000
0!
0&
#4790000000
1!
b11101111 $
1&
b11101111 )
b11110000 -
b11101111 .
#4800000000
0!
0&
#4810000000
1!
b11110000 $
1&
b11110000 )
b11110001 -
b11110000 .
#4820000000
0!
0&
#4830000000
1!
b11110001 $
1&
b11110001 )
b11110010 -
b11110001 .
#4840000000
0!
0&
#4850000000
1!
b11110010 $
1&
b11110010 )
b11110011 -
b11110010 .
#4860000000
0!
0&
#4870000000
1!
b11110011 $
1&
b11110011 )
b11110100 -
b11110011 .
#4880000000
0!
0&
#4890000000
1!
b11110100 $
1&
b11110100 )
b11110101 -
b11110100 .
#4900000000
0!
0&
#4910000000
1!
b11110101 $
1&
b11110101 )
b11110110 -
b11110101 .
#4920000000
0!
0&
#4930000000
1!
b11110110 $
1&
b11110110 )
b11110111 -
b11110110 .
#4940000000
0!
0&
#4950000000
1!
b11110111 $
1&
b11110111 )
b11111000 -
b11110111 .
#4960000000
0!
0&
#4970000000
1!
b11111000 $
1&
b11111000 )
b11111001 -
b11111000 .
#4980000000
0!
0&
#4990000000
1!
b11111001 $
1&
b11111001 )
b11111010 -
b11111001 .
#5000000000
0!
0&
#5010000000
1!
b11111010 $
1&
b11111010 )
b11111011 -
b11111010 .
#5020000000
0!
0&
#5030000000
1!
b11111011 $
1&
b11111011 )
b11111100 -
b11111011 .
#5040000000
0!
0&
#5050000000
1!
b11111100 $
1&
b11111100 )
b11111101 -
b11111100 .
#5060000000
0!
0&
#5070000000
1!
b11111101 $
1&
b11111101 )
b11111110 -
b11111101 .
#5080000000
0!
0&
#5090000000
1!
b11111110 $
1&
b11111110 )
b11111111 -
b11111110 .
#5100000000
0!
0&
#5110000000
1!
b11111111 $
1%
1&
b11111111 )
1*
1+
1,
b00000000 -
b11111111 .
1/
