Exercises/14.0) count_BCD/sources/ffd.vhd
-- Author: Francesco Cavina <francescocavina98@gmail.com>
-- Brief:  This is the HW description for a flip-flop D

library IEEE;
use IEEE.std_logic_1164.all;

entity ffd is
    port(
        d_i:   in  std_logic;
        ena_i: in  std_logic;
        rst_i: in  std_logic;
        clk_i: in  std_logic;
        q_o:   out std_logic
    );
end entity ffd;

architecture ffd_arch of ffd is
    -- Declaration

begin
    -- Description
    process(clk_i) is
    begin
        if rising_edge(clk_i) then
            if rst_i = '1' then
                q_o <= '0';
            elsif ena_i = '1' then
                q_o <= d_i;
            end if;         
        end if;      
    end process;    
end architecture ffd_arch;

Exercises/05.2) reg_Nbit/sources/reg_Nbit.vhd
-- Author: Francesco Cavina <francescocavina98@gmail.com>
-- Brief:  This is the HW description for a N bit register

library IEEE;
use IEEE.std_logic_1164.all;

entity reg_Nbit is
    generic(
        N: natural := 4
    );
    port(
        d_i:   in  std_logic_vector(N-1 downto 0);
        ena_i: in  std_logic;
        rst_i: in  std_logic;
        clk_i: in  std_logic;
        q_o:   out std_logic_vector(N-1 downto 0)
    );
end entity reg_Nbit;

architecture reg_Nbit_arch of reg_Nbit is
    -- Declaration
    component ffd is
        port(
            d_i:   in  std_logic;
            ena_i: in  std_logic;
            rst_i: in  std_logic;
            clk_i: in  std_logic;
            q_o:   out std_logic
        );
    end component ffd;

begin
    -- Description
    reg_Nbit_i: for i in N-1 downto 0 generate
        ffd_inst: ffd
            port map(
                d_i => d_i(i),
                ena_i => ena_i,
                rst_i => rst_i,
                clk_i => clk_i,
                q_o   => q_o(i)
            );
    end generate;
end architecture reg_Nbit_arch;

Exercises/12.0) count_Nbit/sources/count_Nbit.vhd
-- Author: Francesco Cavina <francescocavina98@gmail.com>
-- Brief:  This is the HW description for an N bit binary counter

library IEEE;
use IEEE.std_logic_1164.all;
use IEEE.numeric_std.all;

entity count_Nbit is
    generic(
        N: natural := 4
    );
    port(
        clk_i: in  std_logic;
        rst_i: in  std_logic;
        ena_i: in  std_logic;
        q_o:   out std_logic_vector(N-1 downto 0);
        max_o: out std_logic
    );
end entity count_Nbit;

architecture count_Nbit_arch of count_Nbit is
    -- Declaration
    signal orOutput:   std_logic;
    signal andOutput:  std_logic;
    signal sumOutput:  std_logic_vector(N-1 downto 0);
    signal qOutput:    std_logic_vector(N-1 downto 0);
    signal compOutput: std_logic;

begin
    -- Description
    reg_Nbit_ins: entity work.reg_Nbit
        generic map(
            N => N
        )
        port map(
            clk_i => clk_i,
            rst_i => orOutput,
            ena_i => ena_i,
            d_i   => sumOutput,
            q_o   => qOutput
        );

    sumOutput  <= std_logic_vector(unsigned(qOutput) + 1);    
    compOutput <= '1' when qOutput = std_logic_vector(to_unsigned((2**N)-1, N)) else '0';
    orOutput   <= rst_i or andOutput;
    andOutput  <= ena_i and compOutput;
    max_o   <= compOutput;
    q_o     <= qOutput;
end architecture count_Nbit_arch;

Exercises/12.0) count_Nbit/sources/count_Nbit_tb.vhd
-- Author: Francesco Cavina <francescocavina98@gmail.com>
-- Brief:  This is the testbench of an N bit binary counter

library IEEE;
use IEEE.std_logic_1164.all;

entity count_Nbit_tb is
end entity count_Nbit_tb;

architecture count_Nbit_tb_arch of count_Nbit_tb is
    -- Declaration
    component count_Nbit is
        generic(
            N: natural := 4
        );
        port(
            clk_i: in  std_logic;
            rst_i: in  std_logic;
            ena_i: in  std_logic;
            q_o:   out std_logic_vector(N-1 downto 0);
            max_o: out std_logic
        );
    end component count_Nbit;

    constant N_tb:    natural   := 5;
    signal   clk_tb:  std_logic := '0';
    signal   rst_tb:  std_logic := '1';
    signal   ena_tb:  std_logic := '1';
    signal   q_tb:    std_logic_vector(N_tb-1 downto 0);
    signal   max_tb:  std_logic;

begin
    -- Description

    clk_tb <= not clk_tb after 10 ns;
    rst_tb <= '0' after  10 ns, '1' after 800 ns, '0' after 900 ns;
    --ena_tb <= '0' after 500 ns, '1' after 700 ns;

    DUT: count_Nbit
        generic map(
            N => N_tb
        )
        port map(
            clk_i => clk_tb,
            rst_i => rst_tb,
            ena_i => ena_tb,
            q_o   => q_tb,
            max_o => max_tb
        );
end architecture count_Nbit_tb_arch;

Exercises/12.0) count_Nbit/simulation/count_Nbit_tb.vcd
$date
  Wed Sep 20 00:11:58 2023
$end
$version
  GHDL v0
$end
$timescale
  1 fs
$end
$scope module standard $end
$upscope $end
$scope module std_logic_1164 $end
$upscope $end
$scope module numeric_std $end
$upscope $end
$scope module count_nbit_tb $end
$var reg 1 ! clk_tb $end
$var reg 1 " rst_tb $end
$var reg 1 # ena_tb $end
$var reg 5 $ q_tb[4:0] $end
$var reg 1 % max_tb $end
$scope module dut $end
$var reg 1 & clk_i $end
$var reg 1 ' rst_i $end
$var reg 1 ( ena_i $end
$var reg 5 ) q_o[4:0] $end
$var reg 1 * max_o $end
$var reg 1 + oroutput $end
$var reg 1 , andoutput $end
$var reg 5 - sumoutput[4:0] $end
$var reg 5 . qoutput[4:0] $end
$var reg 1 / compoutput $end
$scope module reg_nbit_ins $end
$var reg 5 0 d_i[4:0] $end
$var reg 1 1 ena_i $end
$var reg 1 2 rst_i $end
$var reg 1 3 clk_i $end
$var reg 5 4 q_o[4:0] $end
$scope module reg_nbit_i(0) $end
$scope module ffd_inst $end
$var reg 1 5 d_i $end
$var reg 1 6 ena_i $end
$var reg 1 7 rst_i $end
$var reg 1 8 clk_i $end
$var reg 1 9 q_o $end
$upscope $end
$upscope $end
$scope module reg_nbit_i(1) $end
$scope module ffd_inst $end
$var reg 1 : d_i $end
$var reg 1 ; ena_i $end
$var reg 1 < rst_i $end
$var reg 1 = clk_i $end
$var reg 1 > q_o $end
$upscope $end
$upscope $end
$scope module reg_nbit_i(2) $end
$scope module ffd_inst $end
$var reg 1 ? d_i $end
$var reg 1 @ ena_i $end
$var reg 1 A rst_i $end
$var reg 1 B clk_i $end
$var reg 1 C q_o $end
$upscope $end
$upscope $end
$scope module reg_nbit_i(3) $end
$scope module ffd_inst $end
$var reg 1 D d_i $end
$var reg 1 E ena_i $end
$var reg 1 F rst_i $end
$var reg 1 G clk_i $end
$var reg 1 H q_o $end
$upscope $end
$upscope $end
$scope module reg_nbit_i(4) $end
$scope module ffd_inst $end
$var reg 1 I d_i $end
$var reg 1 J ena_i $end
$var reg 1 K rst_i $end
$var reg 1 L clk_i $end
$var reg 1 M q_o $end
$upscope $end
$upscope $end
$upscope $end
$upscope $end
$upscope $end
$enddefinitions $end
#0
0!
1"
1#
bUUUUU $
0%
0&
1'
1(
bUUUUU )
0*
1+
0,
bXXXXX -
bUUUUU .
0/
bXXXXX 0
11
12
03
bUUUUU 4
X5
16
17
08
U9
X:
1;
1<
0=
U>
X?
1@
1A
0B
UC
XD
1E
1F
0G
UH
XI
1J
1K
0L
UM
#10000000
1!
0"
b00000 $
1&
0'
b00000 )
0+
b00001 -
b00000 .
b00001 0
02
13
b00000 4
15
07
18
09
0:
0<
1=
0>
0?
0A
1B
0C
0D
0F
1G
0H
0I
0K
1L
0M
#20000000
0!
0&
03
08
0=
0B
0G
0L
#30000000
1!
b00001 $
1&
b00001 )
b00010 -
b00001 .
b00010 0
13
b00001 4
05
18
19
1:
1=
1B
1G
1L
#40000000
0!
0&
03
08
0=
0B
0G
0L
#50000000
1!
b00010 $
1&
b00010 )
b00011 -
b00010 .
b00011 0
13
b00010 4
15
18
09
1=
1>
1B
1G
1L
#60000000
0!
0&
03
08
0=
0B
0G
0L
#70000000
1!
b00011 $
1&
b00011 )
b00100 -
b00011 .
b00100 0
13
b00011 4
05
18
19
0:
1=
1?
1B
1G
1L
#80000000
0!
0&
03
08
0=
0B
0G
0L
#90000000
1!
b00100 $
1&
b00100 )
b00101 -
b00100 .
b00101 0
13
b00100 4
15
18
09
1=
0>
1B
1C
1G
1L
#100000000
0!
0&
03
08
0=
0B
0G
0L
#110000000
1!
b00101 $
1&
b00101 )
b00110 -
b00101 .
b00110 0
13
b00101 4
05
18
19
1:
1=
1B
1G
1L
#120000000
0!
0&
03
08
0=
0B
0G
0L
#130000000
1!
b00110 $
1&
b00110 )
b00111 -
b00110 .
b00111 0
13
b00110 4
15
18
09
1=
1>
1B
1G
1L
#140000000
0!
0&
03
08
0=
0B
0G
0L
#150000000
1!
b00111 $
1&
b00111 )
b01000 -
b00111 .
b01000 0
13
b00111 4
05
18
19
0:
1=
0?
1B
1D
1G
1L
#160000000
0!
0&
03
08
0=
0B
0G
0L
#170000000
1!
b01000 $
1&
b01000 )
b01001 -
b01000 .
b01001 0
13
b01000 4
15
18
09
1=
0>
1B
0C
1G
1H
1L
#180000000
0!
0&
03
08
0=
0B
0G
0L
#190000000
1!
b01001 $
1&
b01001 )
b01010 -
b01001 .
b01010 0
13
b01001 4
05
18
19
1:
1=
1B
1G
1L
#200000000
0!
0&
03
08
0=
0B
0G
0L
#210000000
1!
b01010 $
1&
b01010 )
b01011 -
b01010 .
b01011 0
13
b01010 4
15
18
09
1=
1>
1B
1G
1L
#220000000
0!
0&
03
08
0=
0B
0G
0L
#230000000
1!
b01011 $
1&
b01011 )
b01100 -
b01011 .
b01100 0
13
b01011 4
05
18
19
0:
1=
1?
1B
1G
1L
#240000000
0!
0&
03
08
0=
0B
0G
0L
#250000000
1!
b01100 $
1&
b01100 )
b01101 -
b01100 .
b01101 0
13
b01100 4
15
18
09
1=
0>
1B
1C
1G
1L
#260000000
0!
0&
03
08
0=
0B
0G
0L
#270000000
1!
b01101 $
1&
b01101 )
b01110 -
b01101 .
b01110 0
13
b01101 4
05
18
19
1:
1=
1B
1G
1L
#280000000
0!
0&
03
08
0=
0B
0G
0L
#290000000
1!
b01110 $
1&
b01110 )
b01111 -
b01110 .
b01111 0
13
b01110 4
15
18
09
1=
1>
1B
1G
1L
#300000000
0!
0&
03
08
0=
0B
0G
0L
#310000000
1!
b01111 $
1&
b01111 )
b10000 -
b01111 .
b10000 0
13
b01111 4
05
18
19
0:
1=
0?
1B
0D
1G
1I
1L
#320000000
0!
0&
03
08
0=
0B
0G
0L
#330000000
1!
b10000 $
1&
b10000 )
b10001 -
b10000 .
b10001 0
13
b10000 4
15
18
09
1=
0>
1B
0C
1G
0H
1L
1M
#340000000
0!
0&
03
08
0=
0B
0G
0L
#350000000
1!
b10001 $
1&
b10001 )
b10010 -
b10001 .
b10010 0
13
b10001 4
05
18
19
1:
1=
1B
1G
1L
#360000000
0!
0&
03
08
0=
0B
0G
0L
#370000000
1!
b10010 $
1&
b10010 )
b10011 -
b10010 .
b10011 0
13
b10010 4
15
18
09
1=
1>
1B
1G
1L
#380000000
0!
0&
03
08
0=
0B
0G
0L
#390000000
1!
b10011 $
1&
b10011 )
b10100 -
b10011 .
b10100 0
13
b10011 4
05
18
19
0:
1=
1?
1B
1G
1L
#400000000
0!
0&
03
08
0=
0B
0G
0L
#410000000
1!
b10100 $
1&
b10100 )
b10101 -
b10100 .
b10101 0
13
b10100 4
15
18
09
1=
0>
1B
1C
1G
1L
#420000000
0!
0&
03
08
0=
0B
0G
0L
#430000000
1!
b10101 $
1&
b10101 )
b10110 -
b10101 .
b10110 0
13
b10101 4
05
18
19
1:
1=
1B
1G
1L
#440000000
0!
0&
03
08
0=
0B
0G
0L
#450000000
1!
b10110 $
1&
b10110 )
b10111 -
b10110 .
b10111 0
13
b10110 4
15
18
09
1=
1>
1B
1G
1L
#460000000
0!
0&
03
08
0=
0B
0G
0L
#470000000
1!
b10111 $
1&
b10111 )
b11000 -
b10111 .
b11000 0
13
b10111 4
05
18
19
0:
1=
0?
1B
1D
1G
1L
#480000000
0!
0&
03
08
0=
0B
0G
0L
#490000000
1!
b11000 $
1&
b11000 )
b11001 -
b11000 .
b11001 0
13
b11000 4
15
18
09
1=
0>
1B
0C
1G
1H
1L
#500000000
0!
0&
03
08
0=
0B
0G
0L
#510000000
1!
b11001 $
1&
b11001 )
b11010 -
b11001 .
b11010 0
13
b11001 4
05
18
19
1:
1=
1B
1G
1L
#520000000
0!
0&
03
08
0=
0B
0G
0L
#530000000
1!
b11010 $
1&
b11010 )
b11011 -
b11010 .
b11011 0
13
b11010 4
15
18
09
1=
1>
1B
1G
1L
#540000000
0!
0&
03
08
0=
0B
0G
0L
#550000000
1!
b11011 $
1&
b11011 )
b11100 -
b11011 .
b11100 0
13
b11011 4
05
18
19
0:
1=
1?
1B
1G
1L
#560000000
0!
0&
03
08
0=
0B
0G
0L
#570000000
1!
b11100 $
1&
b11100 )
b11101 -
b11100 .
b11101 0
13
b11100 4
15
18
09
1=
0>
1B
1C
1G
1L
#580000000
0!
0&
03
08
0=
0B
0G
0L
#590000000
1!
b11101 $
1&
b11101 )
b11110 -
b11101 .
b11110 0
13
b11101 4
05
18
19
1:
1=
1B
1G
1L
#600000000
0!
0&
03
08
0=
0B
0G
0L
#610000000
1!
b11110 $
1&
b11110 )
b11111 -
b11110 .
b11111 0
13
b11110 4
15
18
09
1=
1>
1B
1G
1L
#620000000
0!
0&
03
08
0=
0B
0G
0L
#630000000
1!
b11111 $
1%
1&
b11111 )
1*
1+
1,
b00000 -
b11111 .
1/
b00000 0
12
13
b11111 4
05
17
18
19
0:
1<
1=
0?
1A
1B
0D
1F
1G
0I
1K
1L
#640000000
0!
0&
03
08
0=
0B
0G
0L
#650000000
1!
b00000 $
0%
1&
b00000 )
0*
0+
0,
b00001 -
b00000 .
0/
b00001 0
02
13
b00000 4
15
07
18
09
0<
1=
0>
0A
1B
0C
0F
1G
0H
0K
1L
0M
#660000000
0!
0&
03
08
0=
0B
0G
0L
#670000000
1!
b00001 $
1&
b00001 )
b00010 -
b00001 .
b00010 0
13
b00001 4
05
18
19
1:
1=
1B
1G
1L
#680000000
0!
0&
03
08
0=
0B
0G
0L
#690000000
1!
b00010 $
1&
b00010 )
b00011 -
b00010 .
b00011 0
13
b00010 4
15
18
09
1=
1>
1B
1G
1L
#700000000
0!
0&
03
08
0=
0B
0G
0L
#710000000
1!
b00011 $
1&
b00011 )
b00100 -
b00011 .
b00100 0
13
b00011 4
05
18
19
0:
1=
1?
1B
1G
1L
#720000000
0!
0&
03
08
0=
0B
0G
0L
#730000000
1!
b00100 $
1&
b00100 )
b00101 -
b00100 .
b00101 0
13
b00100 4
15
18
09
1=
0>
1B
1C
1G
1L
#740000000
0!
0&
03
08
0=
0B
0G
0L
#750000000
1!
b00101 $
1&
b00101 )
b00110 -
b00101 .
b00110 0
13
b00101 4
05
18
19
1:
1=
1B
1G
1L
#760000000
0!
0&
03
08
0=
0B
0G
0L
#770000000
1!
b00110 $
1&
b00110 )
b00111 -
b00110 .
b00111 0
13
b00110 4
15
18
09
1=
1>
1B
1G
1L
#780000000
0!
0&
03
08
0=
0B
0G
0L
#790000000
1!
b00111 $
1&
b00111 )
b01000 -
b00111 .
b01000 0
13
b00111 4
05
18
19
0:
1=
0?
1B
1D
1G
1L
#800000000
0!
1"
0&
1'
1+
12
03
17
08
1<
0=
1A
0B
1F
0G
1K
0L
#810000000
1!
b00000 $
1&
b00000 )
b00001 -
b00000 .
b00001 0
13
b00000 4
15
18
09
1=
0>
1B
0C
0D
1G
1L
#820000000
0!
0&
03
08
0=
0B
0G
0L
#830000000
1!
1&
13
18
1=
1B
1G
1L
#840000000
0!
0&
03
08
0=
0B
0G
0L
#850000000
1!
1&
13
18
1=
1B
1G
1L
#860000000
0!
0&
03
08
0=
0B
0G
0L
#870000000
1!
1&
13
18
1=
1B
1G
1L
#880000000
0!
0&
03
08
0=
0B
0G
0L
#890000000
1!
1&
13
18
1=
1B
1G
1L
#900000000
0!
0"
0&
0'
0+
02
03
07
08
0<
0=
0A
0B
0F
0G
0K
0L
#910000000
1!
b00001 $
1&
b00001 )
b00010 -
b00001 .
b00010 0
13
b00001 4
05
18
19
1:
1=
1B
1G
1L
#920000000
0!
0&
03
08
0=
0B
0G
0L
#930000000
1!
b00010 $
1&
b00010 )
b00011 -
b00010 .
b00011 0
13
b00010 4
15
18
09
1=
1>
1B
1G
1L
#940000000
0!
0&
03
08
0=
0B
0G
0L
#950000000
1!
b00011 $
1&
b00011 )
b00100 -
b00011 .
b00100 0
13
b00011 4
05
18
19
0:
1=
1?
1B
1G
1L
#960000000
0!
0&
03
08
0=
0B
0G
0L
#970000000
1!
b00100 $
1&
b00100 )
b00101 -
b00100 .
b00101 0
13
b00100 4
15
18
09
1=
0>
1B
1C
1G
1L
#980000000
0!
0&
03
08
0=
0B
0G
0L
#990000000
1!
b00101 $
1&
b00101 )
b00110 -
b00101 .
b00110 0
13
b00101 4
05
18
19
1:
1=
1B
1G
1L
