Final Work - Floating Point Adder/sources/floating_point_adder.vhd
-- Author: Francesco Cavina <francescocavina98@gmail.com>
-- Brief:  This is the HW description for a floating point adder

library IEEE;
use IEEE.std_logic_1164.all;
use IEEE.numeric_std.all;

entity floating_point_adder is
    generic(
        -- Default values for single precision floating point IEEE 754
        PRECISION_BITS: natural := 32; -- Single precision floating point IEEE 754
        EXPONENT_BITS:  natural := 8;  -- Single precision floating point IEEE 754
        MANTISSA_BITS:  natural := 23; -- Single precision floating point IEEE 754
        SIGN_BITS:      natural := 1   -- Single precision floating point IEEE 754

        -- Default values for double precision floating point IEEE 754
        -- PRECISION_BITS: natural := 64  -- Double precision floating point IEEE 754
        -- EXPONENT_BITS:  natural := 11; -- Double precision floating point IEEE 754
        -- MANTISSA_BITS:  natural := 52  -- Double precision floating point IEEE 754
        -- SIGN_BITS:      natural := 1   -- Double precision floating point IEEE 754
    );
    port(
        clk_i:  in  std_logic;
        numA_i: in  std_logic_vector(PRECISION_BITS-1 downto 0);
        numB_i: in  std_logic_vector(PRECISION_BITS-1 downto 0);
        init_i: in  std_logic;
        rst_i:  in  std_logic;
        c_o:    out std_logic_vector(PRECISION_BITS-1 downto 0);
        done_o: out std_logic
    );
end entity floating_point_adder;

architecture floating_point_adder_arch of floating_point_adder is
    -- States
    type STATE is (WAIT_STATE, ALIGNMENT_STATE, ADDITION_STATE, NORMALIZATION_STATE, ROUNDING_STATE, RENORMALIZATION_STATE, DONE_STATE);
    signal current_state, next_state: STATE;

    -- Constants
    constant MAX_EXPONENT: natural := 1023;

    -- Internal signals
    signal exponent_a:       std_logic_vector(EXPONENT_BITS   downto 0) := (others => '0');
    signal exponent_b:       std_logic_vector(EXPONENT_BITS   downto 0) := (others => '0');
    signal mantissa_a:       std_logic_vector(MANTISSA_BITS+1 downto 0) := (others => '0');
    signal mantissa_b:       std_logic_vector(MANTISSA_BITS+1 downto 0) := (others => '0');
    signal sign_a:           std_logic := '0';
    signal sign_b:           std_logic := '0';

    signal mantissa_a_aux:   std_logic_vector(MANTISSA_BITS+1+MAX_EXPONENT downto 0) := (others => '0');
    signal mantissa_b_aux:   std_logic_vector(MANTISSA_BITS+1+MAX_EXPONENT downto 0) := (others => '0');
    
    signal sum_exponent:     std_logic_vector(EXPONENT_BITS downto 0) := (others => '0');
    signal sum_mantissa:     std_logic_vector(MANTISSA_BITS+1+MAX_EXPONENT downto 0) := (others => '0');
    signal sum_mantissa_aux: std_logic_vector(MANTISSA_BITS+1+MAX_EXPONENT downto 0) := (others => '0');
    signal sum_sign:         std_logic := '0';

begin
    -- Description
    process(clk_i, rst_i) is
        -- Declarations
        variable exponents_diff: unsigned(EXPONENT_BITS downto 0);
        variable guard_bit:      unsigned(0 downto 0);
        variable round_bit:      unsigned(0 downto 0);
        variable sticky_bit:     unsigned(0 downto 0);
        variable lsb_bit:        unsigned(0 downto 0);
        
    begin
        if(rst_i = '1') then
            -- If reset
            next_state <= WAIT_STATE;
            c_o        <= (others => '0');
            done_o     <= '0';
        elsif(rising_edge(clk_i)) then
            -- If clock rising edge
            current_state <= next_state;

            case current_state is
                when WAIT_STATE =>
                    if(init_i = '1') then
                        -- Extract exponents from numbers
                        exponent_a <= '0' & numA_i(PRECISION_BITS-1-SIGN_BITS downto PRECISION_BITS-SIGN_BITS-EXPONENT_BITS);
                        exponent_b <= '0' & numB_i(PRECISION_BITS-1-SIGN_BITS downto PRECISION_BITS-SIGN_BITS-EXPONENT_BITS);

                        -- Extract mantissas from numbers
                        mantissa_a <= "01" & numA_i(PRECISION_BITS-1-SIGN_BITS-EXPONENT_BITS downto 0);
                        mantissa_b <= "01" & numB_i(PRECISION_BITS-1-SIGN_BITS-EXPONENT_BITS downto 0);

                        -- Extract signs from numbers
                        sign_a <= numA_i(PRECISION_BITS-1);
                        sign_b <= numB_i(PRECISION_BITS-1);

                        -- Next state
                        next_state <= ALIGNMENT_STATE;
                    else
                        -- Next state
                        next_state <= WAIT_STATE;
                    end if;   
                    
                when ALIGNMENT_STATE =>
                    -- Check if exponents are equal
                    if(exponent_a = exponent_b) then
                        sum_exponent <= exponent_a;
                        
                        mantissa_a_aux(MANTISSA_BITS+1+MAX_EXPONENT downto MAX_EXPONENT) <= mantissa_a; 
                        mantissa_b_aux(MANTISSA_BITS+1+MAX_EXPONENT downto MAX_EXPONENT) <= mantissa_b; 
                    elsif(exponent_a > exponent_b) then
                        -- Calculate difference between exponents
                        exponents_diff := unsigned(exponent_a) - unsigned(exponent_b);

                        sum_exponent <= exponent_a;
                        mantissa_a_aux(MANTISSA_BITS+1+MAX_EXPONENT downto MAX_EXPONENT) <= mantissa_a; 
                        
                        -- Down-shift mantissa B by exponents difference
                        mantissa_b_aux <= (others => '0');
                        mantissa_b_aux(MANTISSA_BITS+1+MAX_EXPONENT-to_integer(exponents_diff) downto MAX_EXPONENT-to_integer(exponents_diff)) <= mantissa_b; 
                    elsif(exponent_b > exponent_a) then
                        -- Calculate difference between exponents
                        exponents_diff := unsigned(exponent_b) - unsigned(exponent_a);

                        sum_exponent <= exponent_b;
                        mantissa_b_aux(MANTISSA_BITS+1+MAX_EXPONENT downto MAX_EXPONENT) <= mantissa_b; 

                        -- Down-shift mantissa A by exponents difference
                        mantissa_a_aux <= (others => '0');
                        mantissa_a_aux(MANTISSA_BITS+1+MAX_EXPONENT-to_integer(exponents_diff) downto MAX_EXPONENT-to_integer(exponents_diff)) <= mantissa_a;
                    end if;

                    -- Next state
                    next_state <= ADDITION_STATE;
                
                when ADDITION_STATE =>
                    if(sign_a = sign_b) then
                        -- If signs are equal
                        -- Add mantissas
                        sum_mantissa <= std_logic_vector(unsigned(mantissa_a_aux) + unsigned(mantissa_b_aux));
                        sum_sign     <= sign_a;
                    else
                        if(unsigned(mantissa_a_aux) >= unsigned(mantissa_b_aux)) then
                            -- If number A is greater than number B
                            sum_mantissa <= std_logic_vector(unsigned(mantissa_a_aux) - unsigned(mantissa_b_aux));
                            sum_sign     <= sign_a;
                        end if;

                        if(unsigned(mantissa_b_aux) > unsigned(mantissa_a_aux)) then
                            -- If number B is greater than number A
                            sum_mantissa <= std_logic_vector(unsigned(mantissa_b_aux) - unsigned(mantissa_a_aux));
                            sum_sign     <= sign_b;
                        end if;
                    end if;

                    -- Next state
                    next_state <= NORMALIZATION_STATE;

                when NORMALIZATION_STATE =>
                    if(unsigned(sum_mantissa) = to_unsigned(0, MANTISSA_BITS+1)) then
                        -- If sum is 0
                        sum_exponent <= (others => '0');
                        sum_mantissa <= (others => '0');
                        sum_sign     <= '0';

                        -- Next state
                        next_state <= ROUNDING_STATE;
                    elsif(sum_mantissa(MANTISSA_BITS+1+MAX_EXPONENT) = '1') then
                        -- If mantissas sum produces overflow
                        -- Down-shift mantissas sum by one
                        sum_exponent  <= std_logic_vector(unsigned(sum_exponent)+1);
                        sum_mantissa  <= '0' & sum_mantissa(MANTISSA_BITS+1+MAX_EXPONENT downto 1);

                        -- Next state
                        next_state <= ROUNDING_STATE;
                    elsif(sum_mantissa(MANTISSA_BITS+MAX_EXPONENT) = '0') then
                        -- If mantissas sum most significant bit is not '0'
                        -- Up-shift mantissas sum by one
                        sum_exponent  <= std_logic_vector(unsigned(sum_exponent)-1);
                        sum_mantissa  <= sum_mantissa(MANTISSA_BITS+MAX_EXPONENT downto 0) & '0';

                        -- Next state
                        next_state <= NORMALIZATION_STATE;
                    else
                        -- If mantissas sum is already normalized
                        -- Next state
                        next_state <= ROUNDING_STATE;
                    end if;

                when ROUNDING_STATE =>
                    -- Get Guard, Round and Sticky bits
                    if(mantissa_a_aux(MAX_EXPONENT-1 downto 0) = std_logic_vector(to_unsigned(0, MAX_EXPONENT-1))) then
                        -- If mantissa B was shifted
                        guard_bit  := unsigned(mantissa_b_aux(MAX_EXPONENT-1 downto MAX_EXPONENT-1));
                        round_bit  := unsigned(mantissa_b_aux(MAX_EXPONENT-2 downto MAX_EXPONENT-2));

                        if(to_integer(unsigned(mantissa_b_aux(MAX_EXPONENT-3 downto 1+MAX_EXPONENT-to_integer(exponents_diff)))) >= 1) then
                            sticky_bit := to_unsigned(1, 1);
                        else 
                            sticky_bit := to_unsigned(0, 1);
                        end if;    
                    else
                        -- If mantissa A was shifted
                        guard_bit  := unsigned(mantissa_a_aux(MAX_EXPONENT-1 downto MAX_EXPONENT-1));
                        round_bit  := unsigned(mantissa_a_aux(MAX_EXPONENT-2 downto MAX_EXPONENT-2));

                        if(to_integer(unsigned(mantissa_a_aux(MAX_EXPONENT-3 downto 1+MAX_EXPONENT-to_integer(exponents_diff)))) >= 1) then
                            sticky_bit := to_unsigned(1, 1);
                        else 
                            sticky_bit := to_unsigned(0, 1);
                        end if; 
                    end if;

                    -- Round up or down based on Guard, Round and Sticky bits
                    if(to_integer(guard_bit) = 0) then
                        -- If Guard bit is 0
                        -- Round down = do nothing

                    elsif(to_integer(round_bit or sticky_bit) = 0) then
                        -- If Guard bit is 1 and (Round bit or Stikcy bit) is 0
                        -- It is a tie, so rounding up or down depends whether the
                        -- mantissa is even or odd
                        if(sum_mantissa(MAX_EXPONENT) = '0') then
                            -- If mantissa is even
                            -- Round down = do nothing

                        else
                            -- If mantissa is odd
                            -- Round up
                            sum_mantissa_aux <= (others => '0');
                            sum_mantissa_aux(MAX_EXPONENT) <= '1';
                            sum_mantissa <= std_logic_vector(unsigned(sum_mantissa) + unsigned(sum_mantissa_aux));
                        end if;    
                    else
                        -- If Guard bit is 1 and (Round bit or Stikcy bit) is 1
                        -- Round up
                        sum_mantissa_aux <= (others => '0');
                        sum_mantissa_aux(MAX_EXPONENT) <= '1';
                        sum_mantissa <= std_logic_vector(unsigned(sum_mantissa) + unsigned(sum_mantissa_aux));
                    end if;    

                    -- Next state
                    next_state <= RENORMALIZATION_STATE;

                when RENORMALIZATION_STATE =>
                    if(sum_mantissa(MANTISSA_BITS+1+MAX_EXPONENT) = '1') then
                        -- If due to the rounding up, overflow was produced
                        -- Down-shift mantissas sum by one
                        sum_exponent  <= std_logic_vector(unsigned(sum_exponent)+1);
                        sum_mantissa  <= '0' & sum_mantissa(MANTISSA_BITS+1+MAX_EXPONENT downto 1);
                    end if;
                    
                -- Next state
                next_state <= DONE_STATE;
                
                when DONE_STATE =>
                    -- Compound addition result 
                    c_o(PRECISION_BITS-1) <= sum_sign;
                    c_o(PRECISION_BITS-1-SIGN_BITS downto PRECISION_BITS-SIGN_BITS-EXPONENT_BITS) <= sum_exponent(EXPONENT_BITS-1 downto 0);
                    c_o(PRECISION_BITS-1-SIGN_BITS-EXPONENT_BITS downto 0) <= sum_mantissa(MANTISSA_BITS-1+MAX_EXPONENT downto MAX_EXPONENT);

                    -- Flag that addition is done
                    done_o <= '1';
                    if(init_i = '0') then 
                        done_o <= '0';

                        -- Next state
                        next_state <= WAIT_STATE;
                    end if;
                    
                when others =>
                    -- Next state    
                    next_state <= WAIT_STATE;
            end case;
        end if;    
    end process;
end architecture floating_point_adder_arch;

Final Work - Floating Point Adder/sources/double_floating_point_adder_tb.vhd
-- Author: Francesco Cavina <francescocavina98@gmail.com>
-- Brief:  This is the testbench of a DOUBLE floating point adder

library IEEE;
use IEEE.std_logic_1164.all;
use IEEE.numeric_std.all;

entity double_floating_point_adder_tb is
    -- Void entity
end entity double_floating_point_adder_tb;
    
architecture double_floating_point_adder_tb_arch of double_floating_point_adder_tb is
    -- Declaration
    component floating_point_adder is
        generic(
            -- Default values for double precision floating point IEEE 754
            PRECISION_BITS: natural := 32;
            EXPONENT_BITS:  natural := 8;
            MANTISSA_BITS:  natural := 23;
            SIGN_BITS:      natural := 1
        );
        port(
            clk_i:  in  std_logic;
            numA_i: in  std_logic_vector(PRECISION_BITS-1 downto 0);
            numB_i: in  std_logic_vector(PRECISION_BITS-1 downto 0);
            init_i: in  std_logic;
            rst_i:  in  std_logic;
            c_o:    out std_logic_vector(PRECISION_BITS-1 downto 0);
            done_o: out std_logic
        );
    end component floating_point_adder;

    constant PRECISION_BITS_tb: natural := 64; -- Double precision floating point IEEE 754
    constant EXPONENT_BITS_tb:  natural := 11; -- Double precision floating point IEEE 754
    constant MANTISSA_BITS_tb:  natural := 52; -- Double precision floating point IEEE 754
    constant SIGN_BITS_tb:      natural := 1;  -- Double precision floating point IEEE 754

    signal clk_tb:  std_logic := '0';
    signal numA_tb: std_logic_vector(PRECISION_BITS_tb-1 downto 0) := (others => '0');
    signal numB_tb: std_logic_vector(PRECISION_BITS_tb-1 downto 0) := (others => '0');
    signal init_tb: std_logic := '0';
    signal rst_tb:  std_logic := '0';
    signal c_tb:    std_logic_vector(PRECISION_BITS_tb-1 downto 0);
    signal done_tb: std_logic;

begin
    -- Description

    clk_tb  <= not clk_tb after 50 ns;
    rst_tb  <= '1' after 20 ns, '0' after 40 ns;
    init_tb <= '1' after 75 ns;

    -- TEST CASE #01 / expected result = +3.845 (0x400EC28F5C28F400) (result is 0x400EC28F5C28F5C2)
    -- numA_tb <= "0011111111110101100001010001111010111000010100011110101110000101" after 0 ns; -- numA_tb = +1.345           (0x3FF5851EB851EC00)
    -- numB_tb <= "0100000000000100000000000000000000000000000000000000000000000000" after 0 ns; -- numB_tb = +2.5             (0x4004000000000000)
 
    -- TEST CASE #02 / expected result = +15.5434 (0x402F163886594C00) (result is 0x402F163886594AF4)
    -- numA_tb <= "0100000000001000101111110100100001111111110010111001001000111010" after 0 ns; -- numA_tb = +3.0934          (0x4008BF487FCB9400)
    -- numB_tb <= "0100000000101000111001100110011001100110011001100110011001100110" after 0 ns; -- numB_tb = +12.45           (0x4028E66666666800)

    -- TEST CASE #03 / expected result = 1,588.23359 (0x4098D0EF32378C00) (result is 0x4098D0EF32378AB0)
    -- numA_tb <= "0100000010010100111100001111000000111000010111000110011111100000" after 0 ns; -- numA_tb = +1,340.23459     (0x4094F0F0385C6800)
    -- numB_tb <= "0100000001101110111111111111011111001110110110010001011010000111" after 0 ns; -- numA_tb = +247.999         (0x406EFFF7CED91800)

    -- TEST CASE #04 / expected result = +5.577 (0x40164ED916872C00)
    numA_tb <= "0100000000100001001000001100010010011011101001011110001101010100" after 0 ns; -- numA_tb = +8.564           (0x402120C49BA5E400)
    numB_tb <= "1100000000000111111001010110000001000001100010010011011101001100" after 0 ns; -- numA_tb = -2.987           (0xC007E56041893800)

    -- TEST CASE #05 / expected result = +5.577 (0x40164ED916872C00)
    -- numA_tb <= "1100000000000111111001010110000001000001100010010011011101001100" after 0 ns; -- numA_tb = -2.987           (0xC007E56041893800)
    -- numB_tb <= "0100000000100001001000001100010010011011101001011110001101010100" after 0 ns; -- numA_tb = +8.564           (0x402120C49BA5E400)

    -- TEST CASE #06 / expected result = +316.110013 (0x4073C1C29CFDD400)
    -- numA_tb <= "0100000001110100100011111101001000011111111100101110010010001111" after 0 ns; -- numA_tb = +328.9888        (0x40748FD21FF2E400)
    -- numB_tb <= "1100000000101001110000011111000001011110101000100100110011000111" after 0 ns; -- numA_tb = -12.878787       (0xC029C1F05EA25000)

    -- TEST CASE #07 / expected result = +316.110013 (0x4073C1C29CFDD400)
    -- numA_tb <= "0100000001110100100011111101001000011111111100101110010010001111" after 0 ns; -- numA_tb = -12.878787       (0xC029C1F05EA25000)
    -- numB_tb <= "1100000000101001110000011111000001011110101000100100110011000111" after 0 ns; -- numA_tb = +328.9888        (0x40748FD21FF2E400)

    -- TEST CASE #08 / expected result = -2,140.8947 (0xC0A0B9CA161E5000)
    -- numA_tb <= "0100000001010110010000000101101111000000000110100011011011100011" after 0 ns; -- numA_tb = +89.0056         (0x4056405BC01A3800)
    -- numB_tb <= "1100000010100001011010111100110011110100000111110010000100101101" after 0 ns; -- numA_tb = -2,229.9003      (0xC0A16BCCF41F2000)

    -- TEST CASE #09 / expected result = -2,244.0003 (0xC0A1880027525800)
    -- numA_tb <= "1100000010100001011010111100110011110100000111110010000100101101" after 0 ns; -- numA_tb = -2,229.9003      (0xC0A16BCCF41F2000)
    -- numB_tb <= "1100000000101100001100110011001100110011001100110011001100110011" after 0 ns; -- numA_tb = -14.1            (0xC02C333333333000)

    -- TEST CASE #10 / expected result = +104.356833617123 (0x405A16D65CAAEC00)
    -- numA_tb <= "0100000000111001100100010100011011100011101110101110000100100011" after 0 ns; -- numA_tb = +25.567487939    (0x40399146E3BAE000)
    -- numB_tb <= "0100000001010011101100101000010010100011101111000011000110111110" after 0 ns; -- numA_tb = +78.789345678123 (0x4053B284A3BC3000)
    
    DUT: floating_point_adder
    generic map(
        PRECISION_BITS => PRECISION_BITS_tb,
        EXPONENT_BITS  => EXPONENT_BITS_tb,
        MANTISSA_BITS  => MANTISSA_BITS_tb,
        SIGN_BITS      => SIGN_BITS_tb
    )
    port map(
        clk_i  => clk_tb,
        numA_i => numA_tb,
        numB_i => numB_tb,
        init_i => init_tb,
        rst_i  => rst_tb,
        c_o    => c_tb,
        done_o => done_tb
    );
end architecture double_floating_point_adder_tb_arch;

Final Work - Floating Point Adder/simulation/double_floating_point_adder_tb.vcd
$date
  Mon Oct  9 19:43:20 2023
$end
$version
  GHDL v0
$end
$timescale
  1 fs
$end
$scope module standard $end
$upscope $end
$scope module std_logic_1164 $end
$upscope $end
$scope module numeric_std $end
$upscope $end
$scope module double_floating_point_adder_tb $end
$var reg 1 ! clk_tb $end
$var reg 64 " numa_tb[63:0] $end
$var reg 64 # numb_tb[63:0] $end
$var reg 1 $ init_tb $end
$var reg 1 % rst_tb $end
$var reg 64 & c_tb[63:0] $end
$var reg 1 ' done_tb $end
$scope module dut $end
$var reg 1 ( clk_i $end
$var reg 64 ) numa_i[63:0] $end
$var reg 64 * numb_i[63:0] $end
$var reg 1 + init_i $end
$var reg 1 , rst_i $end
$var reg 64 - c_o[63:0] $end
$var reg 1 . done_o $end
$comment current_state is not handled $end
$comment next_state is not handled $end
$var reg 12 / exponent_a[11:0] $end
$var reg 12 0 exponent_b[11:0] $end
$var reg 54 1 mantissa_a[53:0] $end
$var reg 54 2 mantissa_b[53:0] $end
$var reg 1 3 sign_a $end
$var reg 1 4 sign_b $end
$var reg 1077 5 mantissa_a_aux[1076:0] $end
$var reg 1077 6 mantissa_b_aux[1076:0] $end
$var reg 12 7 sum_exponent[11:0] $end
$var reg 1077 8 sum_mantissa[1076:0] $end
$var reg 1077 9 sum_mantissa_aux[1076:0] $end
$var reg 1 : sum_sign $end
$upscope $end
$upscope $end
$enddefinitions $end
#0
0!
b0100000010010100111100001111000000111000010111000110011111100000 "
b0100000001101110111111111111011111001110110110010001011010000111 #
0$
0%
bUUUUUUUUUUUUUUUUUUUUUUUUUUUUUUUUUUUUUUUUUUUUUUUUUUUUUUUUUUUUUUUU &
U'
0(
b0100000010010100111100001111000000111000010111000110011111100000 )
b0100000001101110111111111111011111001110110110010001011010000111 *
0+
0,
bUUUUUUUUUUUUUUUUUUUUUUUUUUUUUUUUUUUUUUUUUUUUUUUUUUUUUUUUUUUUUUUU -
U.
b000000000000 /
b000000000000 0
b000000000000000000000000000000000000000000000000000000 1
b000000000000000000000000000000000000000000000000000000 2
03
04
b000000000000000000000000000000000000000000000000000000000000000000000000000000000000000000000000000000000000000000000000000000000000000000000000000000000000000000000000000000000000000000000000000000000000000000000000000000000000000000000000000000000000000000000000000000000000000000000000000000000000000000000000000000000000000000000000000000000000000000000000000000000000000000000000000000000000000000000000000000000000000000000000000000000000000000000000000000000000000000000000000000000000000000000000000000000000000000000000000000000000000000000000000000000000000000000000000000000000000000000000000000000000000000000000000000000000000000000000000000000000000000000000000000000000000000000000000000000000000000000000000000000000000000000000000000000000000000000000000000000000000000000000000000000000000000000000000000000000000000000000000000000000000000000000000000000000000000000000000000000000000000000000000000000000000000000000000000000000000000000000000000000000000000000000000000000000000000000000000000000000000000000000000000000000000000000000000000000000000000000 5
b000000000000000000000000000000000000000000000000000000000000000000000000000000000000000000000000000000000000000000000000000000000000000000000000000000000000000000000000000000000000000000000000000000000000000000000000000000000000000000000000000000000000000000000000000000000000000000000000000000000000000000000000000000000000000000000000000000000000000000000000000000000000000000000000000000000000000000000000000000000000000000000000000000000000000000000000000000000000000000000000000000000000000000000000000000000000000000000000000000000000000000000000000000000000000000000000000000000000000000000000000000000000000000000000000000000000000000000000000000000000000000000000000000000000000000000000000000000000000000000000000000000000000000000000000000000000000000000000000000000000000000000000000000000000000000000000000000000000000000000000000000000000000000000000000000000000000000000000000000000000000000000000000000000000000000000000000000000000000000000000000000000000000000000000000000000000000000000000000000000000000000000000000000000000000000000000000000000000000000000 6
b000000000000 7
b000000000000000000000000000000000000000000000000000000000000000000000000000000000000000000000000000000000000000000000000000000000000000000000000000000000000000000000000000000000000000000000000000000000000000000000000000000000000000000000000000000000000000000000000000000000000000000000000000000000000000000000000000000000000000000000000000000000000000000000000000000000000000000000000000000000000000000000000000000000000000000000000000000000000000000000000000000000000000000000000000000000000000000000000000000000000000000000000000000000000000000000000000000000000000000000000000000000000000000000000000000000000000000000000000000000000000000000000000000000000000000000000000000000000000000000000000000000000000000000000000000000000000000000000000000000000000000000000000000000000000000000000000000000000000000000000000000000000000000000000000000000000000000000000000000000000000000000000000000000000000000000000000000000000000000000000000000000000000000000000000000000000000000000000000000000000000000000000000000000000000000000000000000000000000000000000000000000000000000000 8
b000000000000000000000000000000000000000000000000000000000000000000000000000000000000000000000000000000000000000000000000000000000000000000000000000000000000000000000000000000000000000000000000000000000000000000000000000000000000000000000000000000000000000000000000000000000000000000000000000000000000000000000000000000000000000000000000000000000000000000000000000000000000000000000000000000000000000000000000000000000000000000000000000000000000000000000000000000000000000000000000000000000000000000000000000000000000000000000000000000000000000000000000000000000000000000000000000000000000000000000000000000000000000000000000000000000000000000000000000000000000000000000000000000000000000000000000000000000000000000000000000000000000000000000000000000000000000000000000000000000000000000000000000000000000000000000000000000000000000000000000000000000000000000000000000000000000000000000000000000000000000000000000000000000000000000000000000000000000000000000000000000000000000000000000000000000000000000000000000000000000000000000000000000000000000000000000000000000000000000000 9
0:
#20000000
1%
b0000000000000000000000000000000000000000000000000000000000000000 &
0'
1,
b0000000000000000000000000000000000000000000000000000000000000000 -
0.
#40000000
0%
0,
#50000000
1!
1(
#75000000
1$
1+
#100000000
0!
0(
#150000000
1!
1(
b010000001001 /
b010000000110 0
b010100111100001111000000111000010111000110011111100000 1
b011110111111111111011111001110110110010001011010000111 2
#200000000
0!
0(
#250000000
1!
1(
#300000000
0!
0(
#350000000
1!
1(
b010100111100001111000000111000010111000110011111100000000000000000000000000000000000000000000000000000000000000000000000000000000000000000000000000000000000000000000000000000000000000000000000000000000000000000000000000000000000000000000000000000000000000000000000000000000000000000000000000000000000000000000000000000000000000000000000000000000000000000000000000000000000000000000000000000000000000000000000000000000000000000000000000000000000000000000000000000000000000000000000000000000000000000000000000000000000000000000000000000000000000000000000000000000000000000000000000000000000000000000000000000000000000000000000000000000000000000000000000000000000000000000000000000000000000000000000000000000000000000000000000000000000000000000000000000000000000000000000000000000000000000000000000000000000000000000000000000000000000000000000000000000000000000000000000000000000000000000000000000000000000000000000000000000000000000000000000000000000000000000000000000000000000000000000000000000000000000000000000000000000000000000000000000000000000000000000000000000000000000000 5
b000011110111111111111011111001110110110010001011010000111000000000000000000000000000000000000000000000000000000000000000000000000000000000000000000000000000000000000000000000000000000000000000000000000000000000000000000000000000000000000000000000000000000000000000000000000000000000000000000000000000000000000000000000000000000000000000000000000000000000000000000000000000000000000000000000000000000000000000000000000000000000000000000000000000000000000000000000000000000000000000000000000000000000000000000000000000000000000000000000000000000000000000000000000000000000000000000000000000000000000000000000000000000000000000000000000000000000000000000000000000000000000000000000000000000000000000000000000000000000000000000000000000000000000000000000000000000000000000000000000000000000000000000000000000000000000000000000000000000000000000000000000000000000000000000000000000000000000000000000000000000000000000000000000000000000000000000000000000000000000000000000000000000000000000000000000000000000000000000000000000000000000000000000000000000000000000000000000000000000000 6
b010000001001 7
#400000000
0!
0(
#450000000
1!
1(
#500000000
0!
0(
#550000000
1!
1(
b011000110100001110111100110010001101111000101010110000111000000000000000000000000000000000000000000000000000000000000000000000000000000000000000000000000000000000000000000000000000000000000000000000000000000000000000000000000000000000000000000000000000000000000000000000000000000000000000000000000000000000000000000000000000000000000000000000000000000000000000000000000000000000000000000000000000000000000000000000000000000000000000000000000000000000000000000000000000000000000000000000000000000000000000000000000000000000000000000000000000000000000000000000000000000000000000000000000000000000000000000000000000000000000000000000000000000000000000000000000000000000000000000000000000000000000000000000000000000000000000000000000000000000000000000000000000000000000000000000000000000000000000000000000000000000000000000000000000000000000000000000000000000000000000000000000000000000000000000000000000000000000000000000000000000000000000000000000000000000000000000000000000000000000000000000000000000000000000000000000000000000000000000000000000000000000000000000000000000000000 8
#600000000
0!
0(
#650000000
1!
1(
#700000000
0!
0(
#750000000
1!
1(
#800000000
0!
0(
#850000000
1!
1(
#900000000
0!
0(
#950000000
1!
1(
#1000000000
0!
0(
#1050000000
1!
1(
#1100000000
0!
0(
#1150000000
1!
1(
#1200000000
0!
0(
#1250000000
1!
1(
#1300000000
0!
0(
#1350000000
1!
b0100000010011000110100001110111100110010001101111000101010110000 &
1'
1(
b0100000010011000110100001110111100110010001101111000101010110000 -
1.
