Final Work - Floating Point Adder/sources/floating_point_adder.vhd
-- Author: Francesco Cavina <francescocavina98@gmail.com>
-- Brief:  This is the HW description for a floating point adder

library IEEE;
use IEEE.std_logic_1164.all;
use IEEE.numeric_std.all;

entity floating_point_adder is
    generic(
        -- Default values for single precision floating point IEEE 754
        PRECISION_BITS: natural := 32; -- Single precision floating point IEEE 754
        EXPONENT_BITS:  natural := 8;  -- Single precision floating point IEEE 754
        MANTISSA_BITS:  natural := 23; -- Single precision floating point IEEE 754
        SIGN_BITS:      natural := 1   -- Single precision floating point IEEE 754

        -- Default values for double precision floating point IEEE 754
        -- PRECISION_BITS: natural := 64  -- Double precision floating point IEEE 754
        -- EXPONENT_BITS:  natural := 11; -- Double precision floating point IEEE 754
        -- MANTISSA_BITS:  natural := 52  -- Double precision floating point IEEE 754
        -- SIGN_BITS:      natural := 1   -- Double precision floating point IEEE 754
    );
    port(
        clk_i:  in  std_logic;
        numA_i: in  std_logic_vector(PRECISION_BITS-1 downto 0);
        numB_i: in  std_logic_vector(PRECISION_BITS-1 downto 0);
        init_i: in  std_logic;
        rst_i:  in  std_logic;
        c_o:    out std_logic_vector(PRECISION_BITS-1 downto 0);
        done_o: out std_logic
    );
end entity floating_point_adder;

architecture floating_point_adder_arch of floating_point_adder is
    -- States
    type STATE is (WAIT_STATE, ALIGNMENT_STATE, ADDITION_STATE, NORMALIZATION_STATE, ROUNDING_STATE, DONE_STATE);
    signal current_state, next_state: STATE;

    -- Internal signals
    signal exponent_a:     std_logic_vector(EXPONENT_BITS   downto 0);
    signal exponent_b:     std_logic_vector(EXPONENT_BITS   downto 0);
    signal mantissa_a:     std_logic_vector(MANTISSA_BITS+1 downto 0);
    signal mantissa_b:     std_logic_vector(MANTISSA_BITS+1 downto 0);
    signal sign_a:         std_logic;
    signal sign_b:         std_logic;
        
    signal sum_exponent:   std_logic_vector(EXPONENT_BITS   downto 0);
    signal sum_mantissa:   std_logic_vector(MANTISSA_BITS+1 downto 0);
    signal sum_sign:       std_logic;

begin
    -- Description
    process(clk_i, rst_i) is
        -- Declarations
        variable exponents_diff: unsigned(EXPONENT_BITS downto 0);
        
    begin
        if(rst_i = '1') then
            -- If reset
            current_state <= WAIT_STATE;
            done_o <= '0';
        elsif(rising_edge(clk_i)) then
            -- If clock rising edge
            case current_state is
                when WAIT_STATE =>
                    if(init_i = '1') then
                        -- Extract exponents from numbers
                        exponent_a <= '0' & numA_i(PRECISION_BITS-1-SIGN_BITS downto PRECISION_BITS-1-SIGN_BITS-EXPONENT_BITS+1);
                        exponent_b <= '0' & numB_i(PRECISION_BITS-1-SIGN_BITS downto PRECISION_BITS-1-SIGN_BITS-EXPONENT_BITS+1);

                        -- Extract mantissas from numbers
                        mantissa_a <= "01" & numA_i(PRECISION_BITS-1-SIGN_BITS-EXPONENT_BITS downto 0);
                        mantissa_b <= "01" & numB_i(PRECISION_BITS-1-SIGN_BITS-EXPONENT_BITS downto 0);

                        -- Extract signs from numbers
                        sign_a <= numA_i(PRECISION_BITS-1);
                        sign_b <= numB_i(PRECISION_BITS-1);

                        -- Next state
                        current_state <= ALIGNMENT_STATE;
                    else
                        -- Next state
                        current_state <= WAIT_STATE;
                    end if;   
                    
                when ALIGNMENT_STATE =>
                    -- Check if exponents are equal
                    if(exponent_a = exponent_b) then
                        -- Next state
                        current_state <= ADDITION_STATE;
                        
                    elsif(exponent_a > exponent_b) then
                        -- Calculate difference between exponents
                        exponents_diff := unsigned(exponent_a) - unsigned(exponent_b);

                        if(exponents_diff > MANTISSA_BITS) then
                            -- If number B is too small
                            -- Addition result is directly number A
                            sum_exponent <= exponent_a;
                            sum_mantissa <= mantissa_a;
                            sum_sign     <= sign_a;

                            -- Next state
                            current_state <= DONE_STATE;
                        else
                            -- Down-shift exponent B by exponents difference
                            sum_exponent <= exponent_a;

                            mantissa_b(MANTISSA_BITS+1-to_integer(exponents_diff) downto 0)  <= mantissa_b(MANTISSA_BITS+1 downto to_integer(exponents_diff));
                            mantissa_b(MANTISSA_BITS+1 downto MANTISSA_BITS+1-to_integer(exponents_diff)+1) <= (others => '0');

                            -- Next state
                            current_state <= ADDITION_STATE;
                        end if;
                    else
                        -- Calculate difference between exponents
                        exponents_diff := unsigned(exponent_b) - unsigned(exponent_a);

                        if(exponents_diff > MANTISSA_BITS) then
                            -- If number A is too small
                            -- Addition result is directly number B
                            sum_exponent <= exponent_b;
                            sum_mantissa <= mantissa_b;
                            sum_sign     <= sign_b;

                            -- Next state
                            current_state <= DONE_STATE;
                        else
                            -- Down-shift exponent A by exponents difference
                            sum_exponent <= exponent_b;

                            mantissa_a(MANTISSA_BITS+1-to_integer(exponents_diff) downto 0)  <= mantissa_a(MANTISSA_BITS+1 downto to_integer(exponents_diff));
                            mantissa_a(MANTISSA_BITS downto MANTISSA_BITS+1-to_integer(exponents_diff)+1) <= (others => '0');

                            -- Next state
                            current_state <= ADDITION_STATE;
                        end if;
                    end if;
                
                when ADDITION_STATE =>
                    if(sign_a = sign_b) then
                        -- If signs are equal
                        -- Add mantissas
                        sum_mantissa <= std_logic_vector(unsigned(mantissa_a) + unsigned(mantissa_b));
                        sum_sign     <= sign_a;
                    else
                        if(unsigned(mantissa_a) >= unsigned(mantissa_b)) then
                            -- If number A is greater than number B
                            sum_mantissa <= std_logic_vector(unsigned(mantissa_a) - unsigned(mantissa_b));
                            sum_sign     <= sign_a;
                        end if;

                        if(unsigned(mantissa_b) > unsigned(mantissa_a)) then
                            -- If number B is greater than number A
                            sum_mantissa <= std_logic_vector(unsigned(mantissa_b) - unsigned(mantissa_a));
                            sum_sign     <= sign_b;
                        end if;
                    end if;

                    -- Next state
                    current_state <= NORMALIZATION_STATE;
                            
                when NORMALIZATION_STATE =>
                    if(unsigned(sum_mantissa) = to_unsigned(0, MANTISSA_BITS+1)) then
                        -- If sum is 0
                        sum_exponent <= (others => '0');
                        sum_mantissa <= (others => '0');
                        sum_sign     <= '0';

                        -- Next state
                        current_state <= DONE_STATE;
                    elsif(sum_mantissa(MANTISSA_BITS+1) = '1') then
                        -- If mantissas sum produces overflow
                        -- Down-shift mantissas sum by one
                        sum_exponent  <= std_logic_vector(unsigned(sum_exponent)+1);
                        sum_mantissa  <= '0' & sum_mantissa(MANTISSA_BITS+1 downto 1);

                        -- Next state
                        current_state <= DONE_STATE;
                    elsif(sum_mantissa(MANTISSA_BITS) = '0') then
                        -- If mantissas sum most significant bit is not '0'
                        -- Up-shift mantissas sum by one
                        sum_exponent  <= std_logic_vector(unsigned(sum_exponent)-1);
                        sum_mantissa  <= sum_mantissa(MANTISSA_BITS downto 0) & '0';

                        -- Next state
                        current_state <= NORMALIZATION_STATE;
                    else
                        -- If mantissas sum is already normalized
                        -- Next state
                        current_state <= DONE_STATE;
                    end if;

                when ROUNDING_STATE =>


                when DONE_STATE =>
                    -- Compound addition result 
                    c_o(PRECISION_BITS-1) <= sum_sign;
                    c_o(PRECISION_BITS-1-SIGN_BITS downto PRECISION_BITS-1-SIGN_BITS-EXPONENT_BITS+1) <= sum_exponent(EXPONENT_BITS-1 downto 0);
                    c_o(PRECISION_BITS-1-SIGN_BITS-EXPONENT_BITS downto 0) <= sum_mantissa(MANTISSA_BITS-1 downto 0);

                    -- Flag that addition is done
                    done_o <= '1';
                    if(init_i = '0') then 
                        done_o <= '0';

                        -- Next state
                        current_state <= WAIT_STATE;
                    end if;
                    
                when others =>
                    -- Next state    
                    current_state <= WAIT_STATE;
            end case;
        end if;    
    end process;
end architecture floating_point_adder_arch;

Final Work - Floating Point Adder/sources/single_floating_point_adder_tb.vhd
-- Author: Francesco Cavina <francescocavina98@gmail.com>
-- Brief:  This is the testbench of a SINGLE floating point adder

library IEEE;
use IEEE.std_logic_1164.all;
use IEEE.numeric_std.all;

entity single_floating_point_adder_tb is
    -- Void entity
end entity single_floating_point_adder_tb;
    
architecture single_floating_point_adder_tb_arch of single_floating_point_adder_tb is
    -- Declaration
    component floating_point_adder is
        generic(
            -- Default values for single precision floating point IEEE 754
            PRECISION_BITS: natural := 32;
            EXPONENT_BITS:  natural := 8;
            MANTISSA_BITS:  natural := 23;
            SIGN_BITS:      natural := 1
        );
        port(
            clk_i:  in  std_logic;
            numA_i: in  std_logic_vector(PRECISION_BITS-1 downto 0);
            numB_i: in  std_logic_vector(PRECISION_BITS-1 downto 0);
            init_i: in  std_logic;
            rst_i:  in  std_logic;
            c_o:    out std_logic_vector(PRECISION_BITS-1 downto 0);
            done_o: out std_logic
        );
    end component floating_point_adder;

    constant PRECISION_BITS_tb: natural := 32; -- Single precision floating point IEEE 754
    constant EXPONENT_BITS_tb:  natural := 8;  -- Single precision floating point IEEE 754
    constant MANTISSA_BITS_tb:  natural := 23; -- Single precision floating point IEEE 754
    constant SIGN_BITS_tb:      natural := 1;  -- Single precision floating point IEEE 754

    signal clk_tb:  std_logic := '0';
    signal numA_tb: std_logic_vector(PRECISION_BITS_tb-1 downto 0) := (others => '0');
    signal numB_tb: std_logic_vector(PRECISION_BITS_tb-1 downto 0) := (others => '0');
    signal init_tb: std_logic := '0';
    signal rst_tb:  std_logic := '0';
    signal c_tb:    std_logic_vector(PRECISION_BITS_tb-1 downto 0);
    signal done_tb: std_logic;

begin
    -- Description

    clk_tb  <= not clk_tb after 50 ns;
    rst_tb  <= '1' after 20 ns, '0' after 40 ns;
    init_tb <= '1' after 75 ns;

    -- TEST CASE #01 / expected result = +3.845 (0x4076147B)
    numA_tb <= "00111111101011000010100011110110" after 0 ns; -- numA_tb = +1.345           (0x3FAC28F6)
    numB_tb <= "01000000001000000000000000000000" after 0 ns; -- numB_tb = +2.5             (0x40200000)

    -- TEST CASE #02 / expected result = +15.5434 (0x4178B1C4)
    -- numA_tb <= "01000000010001011111101001000100" after 0 ns; -- numA_tb = +3.0934          (0x4045FA44)
    -- numB_tb <= "01000001010001110011001100110011" after 0 ns; -- numB_tb = +12.45           (0x41473333)

    -- TEST CASE #03 / expected result = 1,588.23359 (0x44C6877A) (result is 0x44C68779)
    -- numA_tb <= "01000100101001111000011110000010" after 0 ns; -- numA_tb = +1,340.23459     (0x44A78782)
    -- numB_tb <= "01000011011101111111111110111110" after 0 ns; -- numA_tb = +247.999         (0x4377FFBE)

    -- TEST CASE #04 / expected result = +5.577 (0x40B276C9) (result is 0x40B276CA)
    -- numA_tb <= "01000001000010010000011000100101" after 0 ns; -- numA_tb = +8.564           (0x41090625)
    -- numB_tb <= "11000000001111110010101100000010" after 0 ns; -- numA_tb = -2.987           (0xC03F2B02)

    -- TEST CASE #05 / expected result = +5.577 (0x40B276C9) (result is 0x40B276CA)
    -- numA_tb <= "11000000001111110010101100000010" after 0 ns; -- numA_tb = -2.987           (0xC03F2B02)
    -- numB_tb <= "01000001000010010000011000100101" after 0 ns; -- numA_tb = +8.564           (0x41090625)

    -- TEST CASE #06 / expected result = +316.110013 (0x439E0E15)
    -- numA_tb <= "01000011101001000111111010010001" after 0 ns; -- numA_tb = +328.9888        (0x43A47E91)
    -- numB_tb <= "11000001010011100000111110000011" after 0 ns; -- numA_tb = -12.878787       (0xC14E0F83)

    -- TEST CASE #07 / expected result = +316.110013 (0x439E0E15)
    -- numA_tb <= "11000001010011100000111110000011" after 0 ns; -- numA_tb = -12.878787       (0xC14E0F83)
    -- numB_tb <= "01000011101001000111111010010001" after 0 ns; -- numA_tb = +328.9888        (0x43A47E91)

    -- TEST CASE #08 / expected result = -2,140.8947 (0xC505CE51) (result is 0xC505CE52)
    -- numA_tb <= "01000010101100100000001011011110" after 0 ns; -- numA_tb = +89.0056         (0x42B202DE)
    -- numB_tb <= "11000101000010110101111001101000" after 0 ns; -- numA_tb = -2,229.9003      (0xC50B5E68)

    -- TEST CASE #09 / expected result = -2,244.0003 (0xC50C400E) (result is 0xC50C4001)
    -- numA_tb <= "11000101000010110101111001101000" after 0 ns; -- numA_tb = -2,229.9003      (0xC50B5E68)
    -- numB_tb <= "11000001011000011001100110011010" after 0 ns; -- numA_tb = -14.1            (0xC161999A)

    -- TEST CASE #10 / expected result = +104.356833617123 (0x42D0B6B3) (result is 0x42D0B6B2)
    -- numA_tb <= "01000001110011001000101000110111" after 0 ns; -- numA_tb = +25.567487939    (0x41CC8A37)
    -- numB_tb <= "01000010100111011001010000100101" after 0 ns; -- numA_tb = +78.789345678123 (0x429D9425)
    
    DUT: floating_point_adder
    generic map(
        PRECISION_BITS => PRECISION_BITS_tb,
        EXPONENT_BITS  => EXPONENT_BITS_tb,
        MANTISSA_BITS  => MANTISSA_BITS_tb,
        SIGN_BITS      => SIGN_BITS_tb
    )
    port map(
        clk_i  => clk_tb,
        numA_i => numA_tb,
        numB_i => numB_tb,
        init_i => init_tb,
        rst_i  => rst_tb,
        c_o    => c_tb,
        done_o => done_tb
    );
end architecture single_floating_point_adder_tb_arch;

Final Work - Floating Point Adder/simulation/single_floating_point_adder_tb.vcd
$date
  Sun Oct  8 20:44:48 2023
$end
$version
  GHDL v0
$end
$timescale
  1 fs
$end
$scope module standard $end
$upscope $end
$scope module std_logic_1164 $end
$upscope $end
$scope module numeric_std $end
$upscope $end
$scope module single_floating_point_adder_tb $end
$var reg 1 ! clk_tb $end
$var reg 32 " numa_tb[31:0] $end
$var reg 32 # numb_tb[31:0] $end
$var reg 1 $ init_tb $end
$var reg 1 % rst_tb $end
$var reg 32 & c_tb[31:0] $end
$var reg 1 ' done_tb $end
$scope module dut $end
$var reg 1 ( clk_i $end
$var reg 32 ) numa_i[31:0] $end
$var reg 32 * numb_i[31:0] $end
$var reg 1 + init_i $end
$var reg 1 , rst_i $end
$var reg 32 - c_o[31:0] $end
$var reg 1 . done_o $end
$comment current_state is not handled $end
$comment next_state is not handled $end
$var reg 9 / exponent_a[8:0] $end
$var reg 9 0 exponent_b[8:0] $end
$var reg 25 1 mantissa_a[24:0] $end
$var reg 25 2 mantissa_b[24:0] $end
$var reg 1 3 sign_a $end
$var reg 1 4 sign_b $end
$var reg 9 5 sum_exponent[8:0] $end
$var reg 25 6 sum_mantissa[24:0] $end
$var reg 1 7 sum_sign $end
$upscope $end
$upscope $end
$enddefinitions $end
#0
0!
b00111111101011000010100011110110 "
b01000000001000000000000000000000 #
0$
0%
bUUUUUUUUUUUUUUUUUUUUUUUUUUUUUUUU &
U'
0(
b00111111101011000010100011110110 )
b01000000001000000000000000000000 *
0+
0,
bUUUUUUUUUUUUUUUUUUUUUUUUUUUUUUUU -
U.
bUUUUUUUUU /
bUUUUUUUUU 0
bUUUUUUUUUUUUUUUUUUUUUUUUU 1
bUUUUUUUUUUUUUUUUUUUUUUUUU 2
U3
U4
bUUUUUUUUU 5
bUUUUUUUUUUUUUUUUUUUUUUUUU 6
U7
#20000000
1%
0'
1,
0.
#40000000
0%
0,
#50000000
1!
1(
#75000000
1$
1+
#100000000
0!
0(
#150000000
1!
1(
b001111111 /
b010000000 0
b0101011000010100011110110 1
b0101000000000000000000000 2
03
04
#200000000
0!
0(
#250000000
1!
1(
b0010101100001010001111011 1
b010000000 5
#300000000
0!
0(
#350000000
1!
1(
b0111101100001010001111011 6
07
#400000000
0!
0(
#450000000
1!
1(
#500000000
0!
0(
#550000000
1!
b01000000011101100001010001111011 &
1'
1(
b01000000011101100001010001111011 -
1.
