Exercises/05.0) ffd/sources/ffd.vhd
-- Author: Francesco Cavina <francescocavina98@gmail.com>
-- Brief:  This is the HW description for a flip-flop D

library IEEE;
use IEEE.std_logic_1164.all;

entity ffd is
    port(
        d_i:   in  std_logic;
        ena_i: in  std_logic;
        rst_i: in  std_logic;
        clk_i: in  std_logic;
        q_o:   out std_logic
    );
end entity ffd;

architecture ffd_arch of ffd is
    -- Declaration

    begin
        -- Description
        process(clk_i) is
        begin
            if rising_edge(clk_i) then
                if rst_i = '1' then
                    q_o <= '0';
                elsif ena_i = '1' then
                    q_o <= d_i;
                end if;         
            end if;      
        end process;    
end architecture ffd_arch;

Exercises/05.1) reg_2bit/sources/reg_2bit.vhd
-- Author: Francesco Cavina <francescocavina98@gmail.com>
-- Brief:  This is the HW description for a 2 bit register

library IEEE;
use IEEE.std_logic_1164.all;

entity reg_2bit is
    port(
        d_i:   in  std_logic_vector(1 downto 0);
        ena_i: in  std_logic;
        rst_i: in  std_logic;
        clk_i: in  std_logic;
        q_o:   out std_logic_vector(1 downto 0)
    );
end entity reg_2bit;

architecture reg_2bit_arch of reg_2bit is
    -- Declaration
    component ffd is
        port(
            d_i:   in  std_logic;
            ena_i: in  std_logic;
            rst_i: in  std_logic;
            clk_i: in  std_logic;
            q_o:   out std_logic
        );
    end component ffd;

    begin
        -- Description
        ffd0_inst: ffd
            port map(
                d_i   => d_i(0),
                ena_i => ena_i,
                rst_i => rst_i,
                clk_i => clk_i,
                q_o   => q_o(0)
            );

        ffd1_inst: ffd
            port map(
                d_i   => d_i(1),
                ena_i => ena_i,
                rst_i => rst_i,
                clk_i => clk_i,
                q_o   => q_o(1)
            );
end architecture reg_2bit_arch;

Exercises/05.1) reg_2bit/sources/reg_2bit_tb.vhd
-- Author: Francesco Cavina <francescocavina98@gmail.com>
-- Brief:  This is the HW description for a 2 bit register

library IEEE;
use IEEE.std_logic_1164.all;

entity reg_2bit_tb is
end entity reg_2bit_tb;

architecture reg_2bit_tb_arch of reg_2bit_tb is
    -- Declaration
    component reg_2bit is
        port(
            d_i:   in  std_logic_vector(1 downto 0);
            ena_i: in  std_logic;
            rst_i: in  std_logic;
            clk_i: in  std_logic;
            q_o:   out std_logic_vector(1 downto 0)
        );
    end component reg_2bit;

    signal d_tb:    std_logic_vector(1 downto 0) := "01";
    signal ena_tb:  std_logic := '0';
    signal rst_tb:  std_logic := '0';
    signal clk_tb:  std_logic := '0';
    signal q_tb:    std_logic_vector(1 downto 0);

    begin
        -- Description
        clk_tb <= not clk_tb after  10 ns;
        d_tb   <= not   d_tb after 100 ns;
        ena_tb <= not ena_tb after 200 ns;
        rst_tb <= not rst_tb after 800 ns;

        DUT: reg_2bit
            port map(
                d_i   => d_tb,
                ena_i => ena_tb,
                rst_i => rst_tb,
                clk_i => clk_tb,
                q_o   => q_tb
            );
end architecture reg_2bit_tb_arch;

Exercises/05.1) reg_2bit/simulation/reg_2bit_tb.vcd
$date
  Tue Sep 12 23:46:21 2023
$end
$version
  GHDL v0
$end
$timescale
  1 fs
$end
$scope module standard $end
$upscope $end
$scope module std_logic_1164 $end
$upscope $end
$scope module reg_2bit_tb $end
$var reg 2 ! d_tb[1:0] $end
$var reg 1 " ena_tb $end
$var reg 1 # rst_tb $end
$var reg 1 $ clk_tb $end
$var reg 2 % q_tb[1:0] $end
$scope module dut $end
$var reg 2 & d_i[1:0] $end
$var reg 1 ' ena_i $end
$var reg 1 ( rst_i $end
$var reg 1 ) clk_i $end
$var reg 2 * q_o[1:0] $end
$scope module ffd0_inst $end
$var reg 1 + d_i $end
$var reg 1 , ena_i $end
$var reg 1 - rst_i $end
$var reg 1 . clk_i $end
$var reg 1 / q_o $end
$upscope $end
$scope module ffd1_inst $end
$var reg 1 0 d_i $end
$var reg 1 1 ena_i $end
$var reg 1 2 rst_i $end
$var reg 1 3 clk_i $end
$var reg 1 4 q_o $end
$upscope $end
$upscope $end
$upscope $end
$enddefinitions $end
#0
b01 !
0"
0#
0$
bUU %
b01 &
0'
0(
0)
bUU *
1+
0,
0-
0.
U/
00
01
02
03
U4
#10000000
1$
1)
1.
13
#20000000
0$
0)
0.
03
#30000000
1$
1)
1.
13
#40000000
0$
0)
0.
03
#50000000
1$
1)
1.
13
#60000000
0$
0)
0.
03
#70000000
1$
1)
1.
13
#80000000
0$
0)
0.
03
#90000000
1$
1)
1.
13
#100000000
b10 !
0$
b10 &
0)
0+
0.
10
03
#110000000
1$
1)
1.
13
#120000000
0$
0)
0.
03
#130000000
1$
1)
1.
13
#140000000
0$
0)
0.
03
#150000000
1$
1)
1.
13
#160000000
0$
0)
0.
03
#170000000
1$
1)
1.
13
#180000000
0$
0)
0.
03
#190000000
1$
1)
1.
13
#200000000
b01 !
1"
0$
b01 &
1'
0)
1+
1,
0.
00
11
03
#210000000
1$
b01 %
1)
b01 *
1.
1/
13
04
#220000000
0$
0)
0.
03
#230000000
1$
1)
1.
13
#240000000
0$
0)
0.
03
#250000000
1$
1)
1.
13
#260000000
0$
0)
0.
03
#270000000
1$
1)
1.
13
#280000000
0$
0)
0.
03
#290000000
1$
1)
1.
13
#300000000
b10 !
0$
b10 &
0)
0+
0.
10
03
#310000000
1$
b10 %
1)
b10 *
1.
0/
13
14
#320000000
0$
0)
0.
03
#330000000
1$
1)
1.
13
#340000000
0$
0)
0.
03
#350000000
1$
1)
1.
13
#360000000
0$
0)
0.
03
#370000000
1$
1)
1.
13
#380000000
0$
0)
0.
03
#390000000
1$
1)
1.
13
#400000000
b01 !
0"
0$
b01 &
0'
0)
1+
0,
0.
00
01
03
#410000000
1$
1)
1.
13
#420000000
0$
0)
0.
03
#430000000
1$
1)
1.
13
#440000000
0$
0)
0.
03
#450000000
1$
1)
1.
13
#460000000
0$
0)
0.
03
#470000000
1$
1)
1.
13
#480000000
0$
0)
0.
03
#490000000
1$
1)
1.
13
#500000000
b10 !
0$
b10 &
0)
0+
0.
10
03
#510000000
1$
1)
1.
13
#520000000
0$
0)
0.
03
#530000000
1$
1)
1.
13
#540000000
0$
0)
0.
03
#550000000
1$
1)
1.
13
#560000000
0$
0)
0.
03
#570000000
1$
1)
1.
13
#580000000
0$
0)
0.
03
#590000000
1$
1)
1.
13
#600000000
b01 !
1"
0$
b01 &
1'
0)
1+
1,
0.
00
11
03
#610000000
1$
b01 %
1)
b01 *
1.
1/
13
04
#620000000
0$
0)
0.
03
#630000000
1$
1)
1.
13
#640000000
0$
0)
0.
03
#650000000
1$
1)
1.
13
#660000000
0$
0)
0.
03
#670000000
1$
1)
1.
13
#680000000
0$
0)
0.
03
#690000000
1$
1)
1.
13
#700000000
b10 !
0$
b10 &
0)
0+
0.
10
03
#710000000
1$
b10 %
1)
b10 *
1.
0/
13
14
#720000000
0$
0)
0.
03
#730000000
1$
1)
1.
13
#740000000
0$
0)
0.
03
#750000000
1$
1)
1.
13
#760000000
0$
0)
0.
03
#770000000
1$
1)
1.
13
#780000000
0$
0)
0.
03
#790000000
1$
1)
1.
13
#800000000
b01 !
0"
1#
0$
b01 &
0'
1(
0)
1+
0,
1-
0.
00
01
12
03
#810000000
1$
b00 %
1)
b00 *
1.
13
04
#820000000
0$
0)
0.
03
#830000000
1$
1)
1.
13
#840000000
0$
0)
0.
03
#850000000
1$
1)
1.
13
#860000000
0$
0)
0.
03
#870000000
1$
1)
1.
13
#880000000
0$
0)
0.
03
#890000000
1$
1)
1.
13
#900000000
b10 !
0$
b10 &
0)
0+
0.
10
03
#910000000
1$
1)
1.
13
#920000000
0$
0)
0.
03
#930000000
1$
1)
1.
13
#940000000
0$
0)
0.
03
#950000000
1$
1)
1.
13
#960000000
0$
0)
0.
03
#970000000
1$
1)
1.
13
#980000000
0$
0)
0.
03
#990000000
1$
1)
1.
13
#1000000000
b01 !
1"
0$
b01 &
1'
0)
1+
1,
0.
00
11
03
